Workbook

Sheet Uçak sayıları
A1: 13.10.2025 Tarihli YYB Filo bilgisine göre filoda yer alan uçak sayıları | I1: Kişi bazlı inceleme adetleri
A2: Uçak Tipi | B2: Adet | I2: İlgili | J2: A310 | K2: A319 | L2: A320 | M2: A321 | N2: A330 | O2: A350 | P2: B737 | Q2: B747 | R2: B777 | S2: B787 | T2: Beklenen | U2: Toplam | V2: Hedef | W2: Tamamlanan
A3: A310 | B3: 3 | I3: Emre | J3: =COUNTIF('A310'!C:C,"EMRE") -> 0 | K3: =COUNTIF('A319'!C:C,"EMRE") -> 0 | L3: =COUNTIF('A320'!C:C,"EMRE") -> 0 | M3: =COUNTIF('A321'!C:C,"EMRE") -> 0 | N3: =COUNTIF('A330'!C:C,"EMRE") -> 0 | O3: =COUNTIF('A350'!C:C,"EMRE") -> 0 | P3: =COUNTIF('B737'!C:C,"EMRE") -> 0 | Q3: =COUNTIF('B747'!C:C,"EMRE") -> 0 | R3: =COUNTIF('B787'!C:C,"EMRE") -> 0 | S3: =COUNTIF('B787'!C:C,"EMRE") -> 0 | T3: =INT(((TODAY()-B33)/7)*5) -> 35 | U3: =SUM(J3:S3) -> 0 | V3: =IF(U3>=T3,"✔","✖") -> ✖ | W3: =IFERROR(U3/T3,0) -> 0
A4: A319 | B4: 6 | I4: Enis | J4: =COUNTIF('A310'!C:C,"ENİS") -> 0 | K4: =COUNTIF('A319'!C:C,"ENİS") -> 0 | L4: =COUNTIF('A320'!C:C,"ENİS") -> 0 | M4: =COUNTIF('A321'!C:C,"ENİS") -> 5 | N4: =COUNTIF('A330'!C:C,"ENİS") -> 0 | O4: =COUNTIF('A350'!C:C,"ENİS") -> 0 | P4: =COUNTIF('B737'!C:C,"ENİS") -> 6 | Q4: =COUNTIF('B747'!C:C,"ENİS") -> 0 | R4: =COUNTIF('B777'!C:C,"ENİS") -> 0 | S4: =COUNTIF('B787'!C:C,"ENİS") -> 0 | T4: =INT(((TODAY()-B33)/7)*5) -> 35 | U4: =SUM(J4:S4) -> 11 | V4: =IF(U4>=T4,"✔","✖") -> ✖ | W4: =IFERROR(U4/T4,0) -> 0.31428571
A5: A320 | B5: 46 | I5: Umut | J5: =COUNTIF('A310'!C:C,"UMUT") -> 0 | K5: =COUNTIF('A319'!C:C,"UMUT") -> 0 | L5: =COUNTIF('A320'!C:C,"UMUT") -> 0 | M5: =COUNTIF('A321'!C:C,"UMUT") -> 0 | N5: =COUNTIF('A330'!C:C,"UMUT") -> 0 | O5: =COUNTIF('A350'!C:C,"UMUT") -> 0 | P5: =COUNTIF('B737'!C:C,"UMUT") -> 0 | Q5: =COUNTIF('B747'!C:C,"UMUT") -> 0 | R5: =COUNTIF('B777'!C:C,"UMUT") -> 0 | S5: =COUNTIF('B787'!C:C,"UMUT") -> 0 | T5: =INT(((TODAY()-B33)/7)*5) -> 35 | U5: =SUM(J5:S5) -> 0 | V5: =IF(U5>=T5,"✔","✖") -> ✖ | W5: =IFERROR(U5/T5,0) -> 0
A6: A321 | B6: 154 | I6: Taha | J6: =COUNTIF('A310'!C:C,"TAHA") -> 2 | K6: =COUNTIF('A319'!C:C,"TAHA") -> 3 | L6: =COUNTIF('A320'!C:C,"TAHA") -> 10 | M6: =COUNTIF('A321'!C:C,"TAHA") -> 3 | N6: =COUNTIF('A330'!C:C,"TAHA") -> 2 | O6: =COUNTIF('A350'!C:C,"TAHA") -> 3 | P6: =COUNTIF('B737'!C:C,"TAHA") -> 5 | Q6: =COUNTIF('B747'!C:C,"TAHA") -> 3 | R6: =COUNTIF('B777'!C:C,"TAHA") -> 2 | S6: =COUNTIF('B787'!C:C,"TAHA") -> 2 | T6: =INT(((TODAY()-B33)/7)*5) -> 35 | U6: =SUM(J6:S6) -> 35 | V6: =IF(U6>=T6,"✔","✖") -> ✔ | W6: =IFERROR(U6/T6,0) -> 1
A7: A330 | B7: 61 | I7: Tamamlanan | J7: =J3+J4+J5+J6 -> 2 | K7: =K3+K4+K5+K6 -> 3 | L7: =L3+L4+L5+L6 -> 10 | M7: =M3+M4+M5+M6 -> 8 | N7: =N3+N4+N5+N6 -> 2 | O7: =O3+O4+O5+O6 -> 3 | P7: =P3+P4+P5+P6 -> 11 | Q7: =Q3+Q4+Q5+Q6 -> 3 | ... S7: =S3+S4+S5+S6 -> 2
A8: A350 | B8: 30
A9: B737 | B9: 137
A10: B747 | B10: 2
A11: B777 | B11: 42
A12: B787 | B12: 25
A13: Toplam: | B13: =SUM(B3:B12) -> 506 | I13: Boş hücre sayıları
I14: Hücre Tipi | J14: A310 | K14: A319 | L14: A320 | M14: A321 | N14: A330 | O14: A350 | P14: B737 | Q14: B747 | R14: B777 | S14: B787
I15: Toplam Hücre | J15: 2933 | K15: 3464 | L15: 4727 | M15: 4829 | N15: 5093 | O15: 1889 | P15: 5548 | Q15: 1006 | R15: 2933 | S15: 1594
I16: Boş Fonksiyon | J16: =COUNTBLANK('A310'!H2:H2934) -> 2931 | K16: =COUNTBLANK('A319'!H2:H3465) -> 3461 | L16: =COUNTBLANK('A320'!H2:H4728) -> 4717 | M16: =COUNTBLANK('A321'!H2:H4830) -> 4826 | N16: =COUNTBLANK('A330'!H2:H5094) -> 5091 | O16: =COUNTBLANK('A350'!H2:H1890) -> 1886 | P16: =COUNTBLANK('B737'!H2:H5549) -> 5543 | Q16: =COUNTBLANK('B747'!H2:H1007) -> 1003 | R16: =COUNTBLANK('B777'!H2:H2934) -> 2931 | S16: =COUNTBLANK('B787'!H2:H1595) -> 1592
I17: Boş resim | J17: =COUNTBLANK('A310'!J2:J2934) -> 2931 | K17: =COUNTBLANK('A319'!J2:J3465) -> 3461 | L17: =COUNTBLANK('A320'!J2:J4728) -> 4717 | M17: =COUNTBLANK('A321'!J2:J4830) -> 4821 | N17: =COUNTBLANK('A330'!J2:J5094) -> 5091 | O17: =COUNTBLANK('A350'!J2:J1890) -> 1886 | P17: =COUNTBLANK('B737'!J2:J5549) -> 5543 | Q17: =COUNTBLANK('B747'!J2:J1007) -> 1003 | R17: =COUNTBLANK('B777'!J2:J2934) -> 2931 | S17: =COUNTBLANK('B787'!J2:J1595) -> 1592
I18: Tamamlanan | J18: =IFERROR((J15-J16)/J15,0) -> 0.00068189567 | K18: =IFERROR((K15-K16)/K15,0) -> 0.00086605081 | L18: =IFERROR((L15-L16)/L15,0) -> 0.0021155067 | M18: =IFERROR((M15-M16)/M15,0) -> 0.00062124663 | N18: =IFERROR((N15-N16)/N15,0) -> 0.00039269586 | O18: =IFERROR((O15-O16)/O15,0) -> 0.0015881419 | P18: =IFERROR((P15-P16)/P15,0) -> 0.00090122567 | Q18: =IFERROR((Q15-Q16)/Q15,0) -> 0.0029821074 | ... S18: =IFERROR((S15-S16)/S15,0) -> 0.0012547051
A21: Firma bazında uçak sayıları
A22: Turkish Airlines | B22: 361
A23: Ajet | B23: 117
A24: Turkish Cargo | B24: 28
A33: Başlangıç tarihi | B33: 45931

Sheet A310
A1: PID_PN | B1: PN DESC | C1: ilgili | D1: Chapter | E1: Sub Category | F1: QTY | G1: FA Amount | H1: Fonksiyonu | I1: Görsel | J1: Resim Notu
A2: RD-AA8061-11 | B2: (FOR SALE/ 3 RD PARTY) - LAN HUB | D2: 23 | E2: IFE | F2: 3 | G2: 23085.6 | I2: =HYPERLINK("\\avrasya\THY_BSK_TEKNIK\MD_TEKNIK_ANLASMALAR_VE_ODEMELER\Teknik Envanter Takip Şefliği\IPC\A310\" &D2&"\"& A2 & ".png", "Resim için basınız") -> Resim için basınız
A3: 184186-1 | B3: 2 WINDOW TILLER GEARBOX | D3: 56 | E3: MECHANIC | F3: 79 | G3: 4279.1 | I3: =HYPERLINK("\\avrasya\THY_BSK_TEKNIK\MD_TEKNIK_ANLASMALAR_VE_ODEMELER\Teknik Envanter Takip Şefliği\IPC\A310\" &D3&"\"& A3 & ".png", "Resim için basınız") -> Resim için basınız
A4: RD-AA8190-01 | B4: 4G ENHANCED CELL MODEM (4G ECM) | D4: 23 | E4: IFE | F4: 247 | G4: 898253.44 | I4: =HYPERLINK("\\avrasya\THY_BSK_TEKNIK\MD_TEKNIK_ANLASMALAR_VE_ODEMELER\Teknik Envanter Takip Şefliği\IPC\A310\" &D4&"\"& A4 & ".png", "Resim için basınız") -> Resim için basınız
A5: 256W2140-1 | B5: 7,8 SLAT GEARBOX | D5: 27 | E5: MECHANIC | F5: 4 | G5: 38546.82 | I5: =HYPERLINK("\\avrasya\THY_BSK_TEKNIK\MD_TEKNIK_ANLASMALAR_VE_ODEMELER\Teknik Envanter Takip Şefliği\IPC\A310\" &D5&"\"& A5 & ".png", "Resim için basınız") -> Resim için basınız
A6: RD-AA7790-01 | B6: 9-IN VGA MONITOR | D6: 23 | E6: IFE | F6: 2 | G6: 228400.37 | I6: =HYPERLINK("\\avrasya\THY_BSK_TEKNIK\MD_TEKNIK_ANLASMALAR_VE_ODEMELER\Teknik Envanter Takip Şefliği\IPC\A310\" &D6&"\"& A6 & ".png", "Resim için basınız") -> Resim için basınız
A7: 180944-201 | B7: 10.6" IN SEATBACK SVDU | D7: 23 | E7: IFE | F7: 167 | G7: 32505.09 | I7: =HYPERLINK("\\avrasya\THY_BSK_TEKNIK\MD_TEKNIK_ANLASMALAR_VE_ODEMELER\Teknik Envanter Takip Şefliği\IPC\A310\" &D7&"\"& A7 & ".png", "Resim için basınız") -> Resim için basınız
A8: 180199-204 | B8: 10.6" IN-ARM SVDU | D8: 23 | E8: IFE | F8: 17 | G8: 33862.6 | I8: =HYPERLINK("\\avrasya\THY_BSK_TEKNIK\MD_TEKNIK_ANLASMALAR_VE_ODEMELER\Teknik Envanter Takip Şefliği\IPC\A310\" &D8&"\"& A8 & ".png", "Resim için basınız") -> Resim için basınız
A9: RD-FE7805-65 | B9: 10.6" LCD MONITOR | D9: 23 | E9: IFE | F9: 2297 | G9: 30052.47 | I9: =HYPERLINK("\\avrasya\THY_BSK_TEKNIK\MD_TEKNIK_ANLASMALAR_VE_ODEMELER\Teknik Envanter Takip Şefliği\IPC\A310\" &D9&"\"& A9 & ".png", "Resim için basınız") -> Resim için basınız
A10: RD-FE7800-64 | B10: 10.6" SMART MONITOR | D10: 23 | E10: IFE | F10: 9034 | G10: 63162.74 | I10: =HYPERLINK("\\avrasya\THY_BSK_TEKNIK\MD_TEKNIK_ANLASMALAR_VE_ODEMELER\Teknik Envanter Takip Şefliği\IPC\A310\" &D10&"\"& A10 & ".png", "Resim için basınız") -> Resim için basınız
A11: RD-FD6815-51 | B11: 11.1" ECO MONITOR | D11: 23 | E11: IFE | F11: 5997 | G11: 318878.74 | I11: =HYPERLINK("\\avrasya\THY_BSK_TEKNIK\MD_TEKNIK_ANLASMALAR_VE_ODEMELER\Teknik Envanter Takip Şefliği\IPC\A310\" &D11&"\"& A11 & ".png", "Resim için basınız") -> Resim için basınız
A12: RD-FW9715-01 | B12: 15.4? LCD WALL MOUNT | D12: 23 | E12: IFE | F12: 169 | G12: 6484.66 | I12: =HYPERLINK("\\avrasya\THY_BSK_TEKNIK\MD_TEKNIK_ANLASMALAR_VE_ODEMELER\Teknik Envanter Takip Şefliği\IPC\A310\" &D12&"\"& A12 & ".png", "Resim için basınız") -> Resim için basınız
A13: RD-FE9816-01 | B13: 16" WALL MOUNTED MONITOR | D13: 23 | E13: IFE | F13: 262 | G13: 91048.72 | I13: =HYPERLINK("\\avrasya\THY_BSK_TEKNIK\MD_TEKNIK_ANLASMALAR_VE_ODEMELER\Teknik Envanter Takip Şefliği\IPC\A310\" &D13&"\"& A13 & ".png", "Resim için basınız") -> Resim için basınız
... A15: RD-FW9723-01 | B15: 23-IN WALL MOUNT LCD MON | D15: 23 | E15: IFE | F15: 58 | G15: 9935.45 | I15: =HYPERLINK("\\avrasya\THY_BSK_TEKNIK\MD_TEKNIK_ANLASMALAR_VE_ODEMELER\Teknik Envanter Takip Şefliği\IPC\A310\" &D15&"\"& A15 & ".png", "Resim için basınız") -> Resim için basınız
A16: RD-FW7239-01 | B16: 23? LCD MONITOR | C16: TAHA | D16: 23 | E16: IFE | F16: 1 | G16: 17279.03 | H16: Yolculara Uçuş bilgilerini duyuruları ve eğlence içeriklerini sağlayarak kabin içi bilgilendirme ve konforu oluşturur. | I16: =HYPERLINK("\\avrasya\THY_BSK_TEKNIK\MD_TEKNIK_ANLASMALAR_VE_ODEMELER\Teknik Envanter Takip Şefliği\IPC\A310\" &D16&"\"& A16 & ".png", "Resim için basınız") -> Resim için basınız | J16: Resim Girildi
A17: 822-0006-105 | B17: A/P FLIGHT DIREC.COMPUTER | D17: 22 | E17: ATE | F17: 136 | G17: 356872.8 | I17: =HYPERLINK("\\avrasya\THY_BSK_TEKNIK\MD_TEKNIK_ANLASMALAR_VE_ODEMELER\Teknik Envanter Takip Şefliği\IPC\A310\" &D17&"\"& A17 & ".png", "Resim için basınız") -> Resim için basınız
A18: F5746268800400 | B18: A330 SLAT NO 6(LH) | D18: 27 | E18: COMPOSIT | F18: 23 | G18: 0 | I18: =HYPERLINK("\\avrasya\THY_BSK_TEKNIK\MD_TEKNIK_ANLASMALAR_VE_ODEMELER\Teknik Envanter Takip Şefliği\IPC\A310\" &D18&"\"& A18 & ".png", "Resim için basınız") -> Resim için basınız
A19: F5746268800500 | B19: A330 SLAT NO 6(RH) | C19: TAHA | D19: 27 | E19: COMPOSIT | F19: 24 | G19: 0 | H19: Uçus sırasında sağ kanat hücum kenarındaki hava akışını düzenleyerek kaldırmayı artırır ve düşük hızlarda uçağın kontrolünü iyileştirir. | I19: =HYPERLINK("\\avrasya\THY_BSK_TEKNIK\MD_TEKNIK_ANLASMALAR_VE_ODEMELER\Teknik Envanter Takip Şefliği\IPC\A310\" &D19&"\"& A19 & ".png", "Resim için basınız") -> Resim için basınız | J19: Resim Girildi
A20: 212C139-3 | B20: ABSOLUTE PRESS SWITCH | D20: 29 | E20: HYDRAUL | F20: 132 | G20: 3769.61 | I20: =HYPERLINK("\\avrasya\THY_BSK_TEKNIK\MD_TEKNIK_ANLASMALAR_VE_ODEMELER\Teknik Envanter Takip Şefliği\IPC\A310\" &D20&"\"& A20 & ".png", "Resim için basınız") -> Resim için basınız
A21: 9000003-3 | B21: ACCELEROMETER | D21: 27 | E21: ATE | F21: 92 | G21: 81870.61 | I21: =HYPERLINK("\\avrasya\THY_BSK_TEKNIK\MD_TEKNIK_ANLASMALAR_VE_ODEMELER\Teknik Envanter Takip Şefliği\IPC\A310\" &D21&"\"& A21 & ".png", "Resim için basınız") -> Resim için basınız
A22: 30730 | B22: ACCUMULATOR ASSY | D22: 29 | E22: HYDRAUL | F22: 143 | G22: 31304.18 | I22: =HYPERLINK("\\avrasya\THY_BSK_TEKNIK\MD_TEKNIK_ANLASMALAR_VE_ODEMELER\Teknik Envanter Takip Şefliği\IPC\A310\" &D22&"\"& A22 & ".png", "Resim için basınız") -> Resim için basınız
A23: RD-FA3951-01 | B23: ACTIVE USB HUB | D23: 23 | E23: IFE | F23: 562 | G23: 70033.79 | I23: =HYPERLINK("\\avrasya\THY_BSK_TEKNIK\MD_TEKNIK_ANLASMALAR_VE_ODEMELER\Teknik Envanter Takip Şefliği\IPC\A310\" &D23&"\"& A23 & ".png", "Resim için basınız") -> Resim için basınız
A24: LPB1030 | B24: ACTUATOR | D24: 25 | E24: ELECTMEC | F24: 499 | G24: 544563.53 | I24: =HYPERLINK("\\avrasya\THY_BSK_TEKNIK\MD_TEKNIK_ANLASMALAR_VE_ODEMELER\Teknik Envanter Takip Şefliği\IPC\A310\" &D24&"\"& A24 & ".png", "Resim için basınız") -> Resim için basınız
A25: AD8650503 | B25: ACTUATOR | D25: 25 | E25: ELECTMEC | F25: 73 | G25: 96214.98 | I25: =HYPERLINK("\\avrasya\THY_BSK_TEKNIK\MD_TEKNIK_ANLASMALAR_VE_ODEMELER\Teknik Envanter Takip Şefliği\IPC\A310\" &D25&"\"& A25 & ".png", "Resim için basınız") -> Resim için basınız
A26: 904800-01 | B26: ACTUATOR | D26: 52 | E26: ELECTMEC | F26: 387 | G26: 123899.77 | I26: =HYPERLINK("\\avrasya\THY_BSK_TEKNIK\MD_TEKNIK_ANLASMALAR_VE_ODEMELER\Teknik Envanter Takip Şefliği\IPC\A310\" &D26&"\"& A26 & ".png", "Resim için basınız") -> Resim için basınız
A27: RPB1030 | B27: ACTUATOR | D27: 25 | E27: SEAT | F27: 89 | G27: 32838.27 | I27: =HYPERLINK("\\avrasya\THY_BSK_TEKNIK\MD_TEKNIK_ANLASMALAR_VE_ODEMELER\Teknik Envanter Takip Şefliği\IPC\A310\" &D27&"\"& A27 & ".png", "Resim için basınız") -> Resim için basınız
A28: MA30A1001 | B28: ACTUATOR | D28: 28 | E28: ELECTMEC | F28: 555 | G28: 154544.89 | I28: =HYPERLINK("\\avrasya\THY_BSK_TEKNIK\MD_TEKNIK_ANLASMALAR_VE_ODEMELER\Teknik Envanter Takip Şefliği\IPC\A310\" &D28&"\"& A28 & ".png", "Resim için basınız") -> Resim için basınız
A29: MA30A1017 | B29: ACTUATOR | D29: 28 | E29: ELECTMEC | F29: 408 | G29: 154544.89 | I29: =HYPERLINK("\\avrasya\THY_BSK_TEKNIK\MD_TEKNIK_ANLASMALAR_VE_ODEMELER\Teknik Envanter Takip Şefliği\IPC\A310\" &D29&"\"& A29 & ".png", "Resim için basınız") -> Resim için basınız
A30: MA20A2027 | B30: ACTUATOR | D30: 28 | E30: ELECTMEC | F30: 10 | G30: 49740.75 | I30: =HYPERLINK("\\avrasya\THY_BSK_TEKNIK\MD_TEKNIK_ANLASMALAR_VE_ODEMELER\Teknik Envanter Takip Şefliği\IPC\A310\" &D30&"\"& A30 & ".png", "Resim için basınız") -> Resim için basınız
A31: 2A258-0487 | B31: ACTUATOR | D31: 25 | E31: ELECTMEC | F31: 50 | G31: 96298.38 | I31: =HYPERLINK("\\avrasya\THY_BSK_TEKNIK\MD_TEKNIK_ANLASMALAR_VE_ODEMELER\Teknik Envanter Takip Şefliği\IPC\A310\" &D31&"\"& A31 & ".png", "Resim için basınız") -> Resim için basınız
... A2934: 2253M40G06 | B2934: INNER LINER COMBUSTOR | D2934: 72 | E2934: ENGINE | F2934: 1 | G2934: 0 | I2934: =HYPERLINK("\\avrasya\THY_BSK_TEKNIK\MD_TEKNIK_ANLASMALAR_VE_ODEMELER\Teknik Envanter Takip Şefliği\IPC\A310\" &D2934&"\"& A2934 & ".png", "Resim için basınız") -> Resim için basınız

Sheet A319
A1: PID_PN | B1: PN DESC | C1: ilgili | D1: Chapter | E1: Sub Category | F1: QTY | G1: Fa Amount | H1: Fonksiyonu | I1: Görsel | J1: Resim Notu
A2: 3840160-8 | B2: 1.STG.TURBINE ROTOR ASSY. | C2: TAHA | D2: 49 | E2: WHEEL | F2: 6 | G2: 143000 | H2: Yanma odasından çıkan sıcak ve yüksek basınçlı (Bleed Air) gazı enerjiye çevirerek kompresörün ve motor aksesuarlarının dönmesini sağlar | I2: =HYPERLINK("\\avrasya\THY_BSK_TEKNIK\MD_TEKNIK_ANLASMALAR_VE_ODEMELER\Teknik Envanter Takip Şefliği\IPC\A319\" &D2&"\"& A2 & ".png", "Resim için basınız") -> Resim için basınız | J2: Resim girildi
A3: 3840310-3 | B3: 1.STG.TURBINE ROTOR ASSY. | C3: TAHA | D3: 49 | E3: WHEEL | F3: 31 | G3: 1885048.1 | H3: Yanma odasından çıkan sıcak ve yüksek basınçlı (Bleed Air) gazı enerjiye çevirerek kompresörün ve motor aksesuarlarının dönmesini sağlar | I3: =HYPERLINK("\\avrasya\THY_BSK_TEKNIK\MD_TEKNIK_ANLASMALAR_VE_ODEMELER\Teknik Envanter Takip Şefliği\IPC\A319\" &D3&"\"& A3 & ".png", "Resim için basınız") -> Resim için basınız | J3: Resim girildi
A4: 3840310-4 | B4: 1.STG.TURBINE ROTOR ASSY. | C4: TAHA | D4: 49 | E4: WHEEL | F4: 242 | G4: 1913751.7 | H4: Yanma odasından çıkan sıcak ve yüksek basınçlı (Bleed Air) gazı enerjiye çevirerek kompresörün ve motor aksesuarlarının dönmesini sağlar | I4: =HYPERLINK("\\avrasya\THY_BSK_TEKNIK\MD_TEKNIK_ANLASMALAR_VE_ODEMELER\Teknik Envanter Takip Şefliği\IPC\A319\" &D4&"\"& A4 & ".png", "Resim için basınız") -> Resim için basınız | J4: Resim girildi
A5: D23627000 | B5: 1M UPPER ELEC.HARNESS | D5: 32 | E5: INSTRMNT | F5: 82 | G5: 18208.8 | I5: =HYPERLINK("\\avrasya\THY_BSK_TEKNIK\MD_TEKNIK_ANLASMALAR_VE_ODEMELER\Teknik Envanter Takip Şefliği\IPC\A319\" &D5&"\"& A5 & ".png", "Resim için basınız") -> Resim için basınız
A6: D23627000-1 | B6: 1M UPPER ELEC.HARNESS | D6: 32 | E6: INSTRMNT | F6: 8 | G6: 463103.89 | I6: =HYPERLINK("\\avrasya\THY_BSK_TEKNIK\MD_TEKNIK_ANLASMALAR_VE_ODEMELER\Teknik Envanter Takip Şefliği\IPC\A319\" &D6&"\"& A6 & ".png", "Resim için basınız") -> Resim için basınız
A7: 4520563 | B7: 1ST STG TURBINE DISK ASSEMBLY | D7: 49 | E7: FUEL | F7: 7 | G7: 3416407.5 | I7: =HYPERLINK("\\avrasya\THY_BSK_TEKNIK\MD_TEKNIK_ANLASMALAR_VE_ODEMELER\Teknik Envanter Takip Şefliği\IPC\A319\" &D7&"\"& A7 & ".png", "Resim için basınız") -> Resim için basınız
A8: 4505475 | B8: 1ST STG TURBINE WHEEL ASY | D8: 49 | E8: FUEL | F8: 36 | G8: 3129113.3 | I8: =HYPERLINK("\\avrasya\THY_BSK_TEKNIK\MD_TEKNIK_ANLASMALAR_VE_ODEMELER\Teknik Envanter Takip Şefliği\IPC\A319\" &D8&"\"& A8 & ".png", "Resim için basınız") -> Resim için basınız
A9: 2A9002 | B9: 2.STG HPT BLADE | D9: 72 | E9: ENGINE | F9: 471 | G9: 17899.87 | I9: =HYPERLINK("\\avrasya\THY_BSK_TEKNIK\MD_TEKNIK_ANLASMALAR_VE_ODEMELER\Teknik Envanter Takip Şefliği\IPC\A319\" &D9&"\"& A9 & ".png", "Resim için basınız") -> Resim için basınız
A10: 3840165-4 | B10: 2.STG. TURBINE ROTOR ASSY | D10: 49 | E10: WHEEL | F10: 95 | G10: 1177872.9 | I10: =HYPERLINK("\\avrasya\THY_BSK_TEKNIK\MD_TEKNIK_ANLASMALAR_VE_ODEMELER\Teknik Envanter Takip Şefliği\IPC\A319\" &D10&"\"& A10 & ".png", "Resim için basınız") -> Resim için basınız
A11: 3840165-9 | B11: 2.STG. TURBINE WHEEL | D11: 49 | E11: WHEEL | F11: 188 | G11: 1208340.3 | I11: =HYPERLINK("\\avrasya\THY_BSK_TEKNIK\MD_TEKNIK_ANLASMALAR_VE_ODEMELER\Teknik Envanter Takip Şefliği\IPC\A319\" &D11&"\"& A11 & ".png", "Resim için basınız") -> Resim için basınız
A12: D23628000-1 | B12: 2M UPPER ELEC.HARNESS | D12: 32 | E12: INSTRMNT | F12: 73 | G12: 15393.69 | I12: =HYPERLINK("\\avrasya\THY_BSK_TEKNIK\MD_TEKNIK_ANLASMALAR_VE_ODEMELER\Teknik Envanter Takip Şefliği\IPC\A319\" &D12&"\"& A12 & ".png", "Resim için basınız") -> Resim için basınız
A13: D23628000 | B13: 2M UPPER ELEC.HARNESS | D13: 32 | E13: INSTRMNT | F13: 6 | G13: 0 | I13: =HYPERLINK("\\avrasya\THY_BSK_TEKNIK\MD_TEKNIK_ANLASMALAR_VE_ODEMELER\Teknik Envanter Takip Şefliği\IPC\A319\" &D13&"\"& A13 & ".png", "Resim için basınız") -> Resim için basınız
A14: D23628000-2 | B14: 2M UPPER ELEC.HARNESS | D14: 32 | E14: INSTRMNT | F14: 8 | G14: 542362.78 | I14: =HYPERLINK("\\avrasya\THY_BSK_TEKNIK\MD_TEKNIK_ANLASMALAR_VE_ODEMELER\Teknik Envanter Takip Şefliği\IPC\A319\" &D14&"\"& A14 & ".png", "Resim için basınız") -> Resim için basınız
A15: 4505477B | B15: 2ND STG TURBINE WHEEL | D15: 49 | E15: FUEL | F15: 71 | G15: 2587126 | I15: =HYPERLINK("\\avrasya\THY_BSK_TEKNIK\MD_TEKNIK_ANLASMALAR_VE_ODEMELER\Teknik Envanter Takip Şefliği\IPC\A319\" &D15&"\"& A15 & ".png", "Resim için basınız") -> Resim için basınız
A16: 4505477 | B16: 2ND STG TURBINE WHEEL | D16: 49 | E16: FUEL | F16: 3 | G16: 2810163.6 | I16: =HYPERLINK("\\avrasya\THY_BSK_TEKNIK\MD_TEKNIK_ANLASMALAR_VE_ODEMELER\Teknik Envanter Takip Şefliği\IPC\A319\" &D16&"\"& A16 & ".png", "Resim için basınız") -> Resim için basınız
... A45: 5913667-3 | B45: AC GENERATOR | D45: 24 | E45: MECHANIC | F45: 2 | G45: 80270.36 | I45: =HYPERLINK("\\avrasya\THY_BSK_TEKNIK\MD_TEKNIK_ANLASMALAR_VE_ODEMELER\Teknik Envanter Takip Şefliği\IPC\A319\" &D45&"\"& A45 & ".png", "Resim için basınız") -> Resim için basınız
A46: 10826B01E02 | B46: AC POWER DISTRIBUTION UNIT (PDU) | D46: 24 | E46: #N/A | F46: 1 | G46: 89776.05 | I46: =HYPERLINK("\\avrasya\THY_BSK_TEKNIK\MD_TEKNIK_ANLASMALAR_VE_ODEMELER\Teknik Envanter Takip Şefliği\IPC\A319\" &D46&"\"& A46 & ".png", "Resim için basınız") -> Resim için basınız
A47: 5860017-139 | B47: ACC ACTUATOR | D47: 75 | E47: MECHANIC | F47: 9 | G47: 75923.7 | I47: =HYPERLINK("\\avrasya\THY_BSK_TEKNIK\MD_TEKNIK_ANLASMALAR_VE_ODEMELER\Teknik Envanter Takip Şefliği\IPC\A319\" &D47&"\"& A47 & ".png", "Resim için basınız") -> Resim için basınız
A48: 5860017-144 | B48: ACC ACTUATOR | D48: 75 | E48: MECHANIC | F48: 217 | G48: 59572.3 | I48: =HYPERLINK("\\avrasya\THY_BSK_TEKNIK\MD_TEKNIK_ANLASMALAR_VE_ODEMELER\Teknik Envanter Takip Şefliği\IPC\A319\" &D48&"\"& A48 & ".png", "Resim için basınız") -> Resim için basınız
A49: 5860016-139 | B49: ACC VALVE | D49: 75 | E49: MECHANIC | F49: 224 | G49: 827900 | I49: =HYPERLINK("\\avrasya\THY_BSK_TEKNIK\MD_TEKNIK_ANLASMALAR_VE_ODEMELER\Teknik Envanter Takip Şefliği\IPC\A319\" &D49&"\"& A49 & ".png", "Resim için basınız") -> Resim için basınız
A50: J172ABM01 | B50: ACCELEROMETER UNIT | D50: 27 | E50: INSTRMNT | F50: 888 | G50: 223548.8 | I50: =HYPERLINK("\\avrasya\THY_BSK_TEKNIK\MD_TEKNIK_ANLASMALAR_VE_ODEMELER\Teknik Envanter Takip Şefliği\IPC\A319\" &D50&"\"& A50 & ".png", "Resim için basınız") -> Resim için basınız
A51: J172ABM | B51: ACCELEROMETER UNIT | D51: 27 | E51: INSTRMNT | F51: 39 | G51: 83711.36 | I51: =HYPERLINK("\\avrasya\THY_BSK_TEKNIK\MD_TEKNIK_ANLASMALAR_VE_ODEMELER\Teknik Envanter Takip Şefliği\IPC\A319\" &D51&"\"& A51 & ".png", "Resim için basınız") -> Resim için basınız
A52: D5248570001000 | B52: ACCESS DOOR RH | D52: 52 | E52: INSTRMNT | F52: 26 | G52: 1722.95 | I52: =HYPERLINK("\\avrasya\THY_BSK_TEKNIK\MD_TEKNIK_ANLASMALAR_VE_ODEMELER\Teknik Envanter Takip Şefliği\IPC\A319\" &D52&"\"& A52 & ".png", "Resim için basınız") -> Resim için basınız
A53: D2827105300600 | B53: ACT 3 | D53: 28 | E53: INSTRMNT | F53: 1 | G53: 0 | I53: =HYPERLINK("\\avrasya\THY_BSK_TEKNIK\MD_TEKNIK_ANLASMALAR_VE_ODEMELER\Teknik Envanter Takip Şefliği\IPC\A319\" &D53&"\"& A53 & ".png", "Resim için basınız") -> Resim için basınız
A54: D2827105500600 | B54: ACT 5 | D54: 28 | E54: INSTRMNT | F54: 1 | G54: 0 | I54: =HYPERLINK("\\avrasya\THY_BSK_TEKNIK\MD_TEKNIK_ANLASMALAR_VE_ODEMELER\Teknik Envanter Takip Şefliği\IPC\A319\" &D54&"\"& A54 & ".png", "Resim için basınız") -> Resim için basınız
A55: D2827105600600 | B55: ACT 6 | D55: 28 | E55: INSTRMNT | F55: 1 | G55: 0 | I55: =HYPERLINK("\\avrasya\THY_BSK_TEKNIK\MD_TEKNIK_ANLASMALAR_VE_ODEMELER\Teknik Envanter Takip Şefliği\IPC\A319\" &D55&"\"& A55 & ".png", "Resim için basınız") -> Resim için basınız
A56: 738275-3-5 | B56: ACT.FUEL MANAGE. QTY.COMP | D56: 28 | E56: SANITARY | F56: 3 | G56: 39601.04 | I56: =HYPERLINK("\\avrasya\THY_BSK_TEKNIK\MD_TEKNIK_ANLASMALAR_VE_ODEMELER\Teknik Envanter Takip Şefliği\IPC\A319\" &D56&"\"& A56 & ".png", "Resim için basınız") -> Resim için basınız
A57: D3221408000000 | B57: ACTUATING CYL.PIN ASSY | D57: 32 | E57: INSTRMNT | F57: 179 | G57: 33921.27 | I57: =HYPERLINK("\\avrasya\THY_BSK_TEKNIK\MD_TEKNIK_ANLASMALAR_VE_ODEMELER\Teknik Envanter Takip Şefliği\IPC\A319\" &D57&"\"& A57 & ".png", "Resim için basınız") -> Resim için basınız
A58: D3221407920000 | B58: ACTUATING CYLINDER SLEEVE | D58: 32 | E58: INSTRMNT | F58: 179 | G58: 29207.43 | I58: =HYPERLINK("\\avrasya\THY_BSK_TEKNIK\MD_TEKNIK_ANLASMALAR_VE_ODEMELER\Teknik Envanter Takip Şefliği\IPC\A319\" &D58&"\"& A58 & ".png", "Resim için basınız") -> Resim için basınız
... A69: A06L00 | B69: ACTUATOR ELECTRIC | D69: 29 | E69: GALLEY | F69: 62 | G69: 7537.61 | I69: =HYPERLINK("\\avrasya\THY_BSK_TEKNIK\MD_TEKNIK_ANLASMALAR_VE_ODEMELER\Teknik Envanter Takip Şefliği\IPC\A319\" &D69&"\"& A69 & ".png", "Resim için basınız") -> Resim için basınız
A70: 41-2-1100-02 | B70: ACTUATOR EMERGENCY RAM | D70: 21 | E70: FUEL | F70: 203 | G70: 17687.02 | I70: =HYPERLINK("\\avrasya\THY_BSK_TEKNIK\MD_TEKNIK_ANLASMALAR_VE_ODEMELER\Teknik Envanter Takip Şefliği\IPC\A320\" &D70&"\"& A70 & ".png", "Resim için basınız") -> Resim için basınız
A71: 321-409-900-0 | B71: ACTUATOR JUNCTION BOX | D71: 78 | E71: WHEEL | F71: 2 | G71: 39386.55 | I71: =HYPERLINK("\\avrasya\THY_BSK_TEKNIK\MD_TEKNIK_ANLASMALAR_VE_ODEMELER\Teknik Envanter Takip Şefliği\IPC\A320\" &D71&"\"& A71 & ".png", "Resim için basınız") -> Resim için basınız
A72: 4136290006 | B72: ACTUATOR_LABINAL | D72: 25 | E72: FUEL | F72: 505 | G72: 300126.96 | I72: =HYPERLINK("\\avrasya\THY_BSK_TEKNIK\MD_TEKNIK_ANLASMALAR_VE_ODEMELER\Teknik Envanter Takip Şefliği\IPC\A320\" &D72&"\"& A72 & ".png", "Resim için basınız") -> Resim için basınız
A73: 4136290007 | B73: ACTUATOR_LABINAL | D73: 25 | E73: FUEL | F73: 4 | G73: 35645.16 | I73: =HYPERLINK("\\avrasya\THY_BSK_TEKNIK\MD_TEKNIK_ANLASMALAR_VE_ODEMELER\Teknik Envanter Takip Şefliği\IPC\A320\" &D73&"\"& A73 & ".png", "Resim için basınız") -> Resim için basınız
A74: 321-400-705-0 | B74: ACTUATOR-DOOR OPENING | D74: 78 | E74: WHEEL | F74: 5 | G74: 432432.9 | I74: =HYPERLINK("\\avrasya\THY_BSK_TEKNIK\MD_TEKNIK_ANLASMALAR_VE_ODEMELER\Teknik Envanter Takip Şefliği\IPC\A320\" &D74&"\"& A74 & ".png", "Resim için basınız") -> Resim için basınız
A75: 321-400-707-0 | B75: ACTUATOR-DOOR OPENING | D75: 78 | E75: WHEEL | F75: 4 | G75: 538782.94 | I75: =HYPERLINK("\\avrasya\THY_BSK_TEKNIK\MD_TEKNIK_ANLASMALAR_VE_ODEMELER\Teknik Envanter Takip Şefliği\IPC\A320\" &D75&"\"& A75 & ".png", "Resim için basınız") -> Resim için basınız
A76: S4-3300520-01 | B76: ACTUATOR-HYDRAULIC | D76: 52 | E76: INSTRMNT | F76: 16 | G76: 5095.35 | I76: =HYPERLINK("\\avrasya\THY_BSK_TEKNIK\MD_TEKNIK_ANLASMALAR_VE_ODEMELER\Teknik Envanter Takip Şefliği\IPC\A320\" &D76&"\"& A76 & ".png", "Resim için basınız") -> Resim için basınız
A77: E20000 | B77: ACTUATOR-HYDRAULIC | D77: 52 | E77: INSTRMNT | F77: 806 | G77: 99641 | I77: =HYPERLINK("\\avrasya\THY_BSK_TEKNIK\MD_TEKNIK_ANLASMALAR_VE_ODEMELER\Teknik Envanter Takip Şefliği\IPC\A320\" &D77&"\"& A77 & ".png", "Resim için basınız") -> Resim için basınız
A78: S4-3300520 | B78: ACTUATOR-HYDRAULIC | D78: 52 | E78: INSTRMNT | F78: 4 | G78: 59727.68 | I78: =HYPERLINK("\\avrasya\THY_BSK_TEKNIK\MD_TEKNIK_ANLASMALAR_VE_ODEMELER\Teknik Envanter Takip Şefliği\IPC\A320\" &D78&"\"& A78 & ".png", "Resim için basınız") -> Resim için basınız
A79: 761B0000-01 | B79: ACTUATOR-RAM AIR INLET | D79: 21 | E79: SANITARY | F79: 7 | G79: 11871.68 | I79: =HYPERLINK("\\avrasya\THY_BSK_TEKNIK\MD_TEKNIK_ANLASMALAR_VE_ODEMELER\Teknik Envanter Takip Şefliği\IPC\A320\" &D79&"\"& A79 & ".png", "Resim için basınız") -> Resim için basınız
A80: 761A0000-04 | B80: ACTUATOR-RAM AIR INLET | D80: 21 | E80: SANITARY | F80: 2 | G80: 8699.4 | I80: =HYPERLINK("\\avrasya\THY_BSK_TEKNIK\MD_TEKNIK_ANLASMALAR_VE_ODEMELER\Teknik Envanter Takip Şefliği\IPC\A320\" &D80&"\"& A80 & ".png", "Resim için basınız") -> Resim için basınız
A81: 829C0000-01 | B81: ACTUATOR-ROTARY,SLAT | D81: 27 | E81: SANITARY | F81: 280 | G81: 9011.98 | I81: =HYPERLINK("\\avrasya\THY_BSK_TEKNIK\MD_TEKNIK_ANLASMALAR_VE_ODEMELER\Teknik Envanter Takip Şefliği\IPC\A320\" &D81&"\"& A81 & ".png", "Resim için basınız") -> Resim için basınız
... A88: 615-2630-102 | B88: ADF ANTENNA | D88: 34 | E88: MECHANIC | F88: 209 | G88: 483360.4 | I88: =HYPERLINK("\\avrasya\THY_BSK_TEKNIK\MD_TEKNIK_ANLASMALAR_VE_ODEMELER\Teknik Envanter Takip Şefliği\IPC\A320\" &D88&"\"& A88 & ".png", "Resim için basınız") -> Resim için basınız
A89: 066-50014-0202 | B89: ADF RECEIVER | D89: 34 | E89: #N/A | F89: 106 | G89: 12840.07 | I89: =HYPERLINK("\\avrasya\THY_BSK_TEKNIK\MD_TEKNIK_ANLASMALAR_VE_ODEMELER\Teknik Envanter Takip Şefliği\IPC\A320\" &D89&"\"& A89 & ".png", "Resim için basınız") -> Resim için basınız
A90: 822-0299-020 | B90: ADF RECEIVER | D90: 34 | E90: SANITARY | F90: 235 | G90: 12840.07 | I90: =HYPERLINK("\\avrasya\THY_BSK_TEKNIK\MD_TEKNIK_ANLASMALAR_VE_ODEMELER\Teknik Envanter Takip Şefliği\IPC\A320\" &D90&"\"& A90 & ".png", "Resim için basınız") -> Resim için basınız
A91: 465010-0300-0300 | B91: ADIRS CDU | D91: 34 | E91: FUEL | F91: 1 | G91: 35697.31 | I91: =HYPERLINK("\\avrasya\THY_BSK_TEKNIK\MD_TEKNIK_ANLASMALAR_VE_ODEMELER\Teknik Envanter Takip Şefliği\IPC\A320\" &D91&"\"& A91 & ".png", "Resim için basınız") -> Resim için basınız
A92: CG1151AC03 | B92: ADIRS CDU | D92: 34 | E92: INSTRMNT | F92: 26 | G92: 122761.5 | I92: =HYPERLINK("\\avrasya\THY_BSK_TEKNIK\MD_TEKNIK_ANLASMALAR_VE_ODEMELER\Teknik Envanter Takip Şefliği\IPC\A320\" &D92&"\"& A92 & ".png", "Resim için basınız") -> Resim için basınız
A93: 465020-03030318 | B93: ADIRU | D93: 34 | E93: FUEL | F93: 17 | G93: 54022.7 | I93: =HYPERLINK("\\avrasya\THY_BSK_TEKNIK\MD_TEKNIK_ANLASMALAR_VE_ODEMELER\Teknik Envanter Takip Şefliği\IPC\A320\" &D93&"\"& A93 & ".png", "Resim için basınız") -> Resim için basınız
A94: HG2030BE04 | B94: ADIRU | D94: 34 | E94: INSTRMNT | F94: 544 | G94: 11803404 | I94: =HYPERLINK("\\avrasya\THY_BSK_TEKNIK\MD_TEKNIK_ANLASMALAR_VE_ODEMELER\Teknik Envanter Takip Şefliği\IPC\A320\" &D94&"\"& A94 & ".png", "Resim için basınız") -> Resim için basınız
A95: HG2030AC13 | B95: ADIRU | D95: 34 | E95: INSTRMNT | F95: 5 | G95: 113832.32 | I95: =HYPERLINK("\\avrasya\THY_BSK_TEKNIK\MD_TEKNIK_ANLASMALAR_VE_ODEMELER\Teknik Envanter Takip Şefliği\IPC\A320\" &D95&"\"& A95 & ".png", "Resim için basınız") -> Resim için basınız
A96: HG2030AE23 | B96: ADIRU | D96: 34 | E96: INSTRMNT | F96: 9 | G96: 783094.5 | I96: =HYPERLINK("\\avrasya\THY_BSK_TEKNIK\MD_TEKNIK_ANLASMALAR_VE_ODEMELER\Teknik Envanter Takip Şefliği\IPC\A320\" &D96&"\"& A96 & ".png", "Resim için basınız") -> Resim için basınız
A97: 465020-03030316 | B97: ADIRU | D97: 34 | E97: FUEL | F97: 3 | G97: 68985.8 | I97: =HYPERLINK("\\avrasya\THY_BSK_TEKNIK\MD_TEKNIK_ANLASMALAR_VE_ODEMELER\Teknik Envanter Takip Şefliği\IPC\A320\" &D97&"\"& A97 & ".png", "Resim için basınız") -> Resim için basınız
A98: HG2030BE03 | B98: ADIRU | D98: 34 | E98: INSTRMNT | F98: 124 | G98: 11561484 | I98: =HYPERLINK("\\avrasya\THY_BSK_TEKNIK\MD_TEKNIK_ANLASMALAR_VE_ODEMELER\Teknik Envanter Takip Şefliği\IPC\A320\" &D98&"\"& A98 & ".png", "Resim için basınız") -> Resim için basınız
A99: HG2030AE24 | B99: ADIRU | D99: 34 | E99: INSTRMNT | F99: 14 | G99: 48186.45 | I99: =HYPERLINK("\\avrasya\THY_BSK_TEKNIK\MD_TEKNIK_ANLASMALAR_VE_ODEMELER\Teknik Envanter Takip Şefliği\IPC\A320\" &D99&"\"& A99 & ".png", "Resim için basınız") -> Resim için basınız
A100: HG2030AE43 | B100: ADIRU | D100: 34 | E100: INSTRMNT | F100: 9 | G100: 130169.01 | I100: =HYPERLINK("\\avrasya\THY_BSK_TEKNIK\MD_TEKNIK_ANLASMALAR_VE_ODEMELER\Teknik Envanter Takip Şefliği\IPC\A320\" &D100&"\"& A100 & ".png", "Resim için basınız") -> Resim için basınız
A101: Z120H050830B | B101: AFT ATTENDANT PANEL | D101: 23 | E101: INSTRMNT | F101: 31 | G101: 338887.04 | I101: =HYPERLINK("\\avrasya\THY_BSK_TEKNIK\MD_TEKNIK_ANLASMALAR_VE_ODEMELER\Teknik Envanter Takip Şefliği\IPC\A320\" &D101&"\"& A101 & ".png", "Resim için basınız") -> Resim için basınız
... A154: 2123M63P02 | B154: ALTERNATOR STATOR | D154: 73 | E154: INSTRMNT | F154: 3 | G154: 51682.88 | I154: =HYPERLINK("\\avrasya\THY_BSK_TEKNIK\MD_TEKNIK_ANLASMALAR_VE_ODEMELER\Teknik Envanter Takip Şefliği\IPC\A320\" &D154&"\"& A154 & ".png", "Resim için basınız") -> Resim için basınız
A155: 101809 | B155: ALTITUDE SWITCH | D155: 35 | E155: #N/A | F155: 24 | G155: 3889.8 | I155: =HYPERLINK("\\avrasya\THY_BSK_TEKNIK\MD_TEKNIK_ANLASMALAR_VE_ODEMELER\Teknik Envanter Takip Şefliği\IPC\A320\" &D155&"\"& A155 & ".png", "Resim için basınız") -> Resim için basınız
A156: 0861ED | B156: ANGLE OF ATTACK SENSOR | D156: 34 | E156: #N/A | F156: 139 | G156: 69937.53 | I156: =HYPERLINK("\\avrasya\THY_BSK_TEKNIK\MD_TEKNIK_ANLASMALAR_VE_ODEMELER\Teknik Envanter Takip Şefliği\IPC\A320\" &D156&"\"& A156 & ".png", "Resim için basınız") -> Resim için basınız
A157: 5A1753 | B157: ANNULUS FILLER | D157: 72 | E157: MECHANIC | F157: 114 | G157: 10674.36 | I157: =HYPERLINK("\\avrasya\THY_BSK_TEKNIK\MD_TEKNIK_ANLASMALAR_VE_ODEMELER\Teknik Envanter Takip Şefliği\IPC\A320\" &D157&"\"& A157 & ".png", "Resim için basınız") -> Resim için basınız
A158: 5A1710 | B158: ANNULUS FILLER | D158: 72 | E158: MECHANIC | F158: 4458 | G158: 86751.75 | I158: =HYPERLINK("\\avrasya\THY_BSK_TEKNIK\MD_TEKNIK_ANLASMALAR_VE_ODEMELER\Teknik Envanter Takip Şefliği\IPC\A320\" &D158&"\"& A158 & ".png", "Resim için basınız") -> Resim için basınız
A159: 35-0F5-1000 | B159: ANNUNCIATOR LIGHT TEST BOARD | D159: 33 | E159: WHEEL | F159: 92 | G159: 95898.93 | I159: =HYPERLINK("\\avrasya\THY_BSK_TEKNIK\MD_TEKNIK_ANLASMALAR_VE_ODEMELER\Teknik Envanter Takip Şefliği\IPC\A320\" &D159&"\"& A159 & ".png", "Resim için basınız") -> Resim için basınız
A160: D23116000 | B160: ANTI SHIMMY VALVE | D160: 32 | E160: INSTRMNT | F160: 183 | G160: 28399.62 | I160: =HYPERLINK("\\avrasya\THY_BSK_TEKNIK\MD_TEKNIK_ANLASMALAR_VE_ODEMELER\Teknik Envanter Takip Şefliği\IPC\A320\" &D160&"\"& A160 & ".png", "Resim için basınız") -> Resim için basınız
A161: 2LA455010-00 | B161: ANTICOLLISION LIGHT | D161: 33 | E161: FUEL | F161: 295 | G161: 68317.5 | I161: =HYPERLINK("\\avrasya\THY_BSK_TEKNIK\MD_TEKNIK_ANLASMALAR_VE_ODEMELER\Teknik Envanter Takip Şefliği\IPC\A320\" &D161&"\"& A161 & ".png", "Resim için basınız") -> Resim için basınız
A162: C16291AB | B162: AOA SENSOR | D162: 34 | E162: INSTRMNT | F162: 738 | G162: 5359342.4 | I162: =HYPERLINK("\\avrasya\THY_BSK_TEKNIK\MD_TEKNIK_ANLASMALAR_VE_ODEMELER\Teknik Envanter Takip Şefliği\IPC\A320\" &D162&"\"& A162 & ".png", "Resim için basınız") -> Resim için basınız
A163: 4500001B | B163: APS3200 | D163: 49 | E163: FUEL | F163: 12 | G163: 10275885 | I163: =HYPERLINK("\\avrasya\THY_BSK_TEKNIK\MD_TEKNIK_ANLASMALAR_VE_ODEMELER\Teknik Envanter Takip Şefliği\IPC\A320\" &D163&"\"& A163 & ".png", "Resim için basınız") -> Resim için basınız
A164: 4500001C | B164: APS3200 | D164: 49 | E164: FUEL | F164: 86 | G164: 13169175 | I164: =HYPERLINK("\\avrasya\THY_BSK_TEKNIK\MD_TEKNIK_ANLASMALAR_VE_ODEMELER\Teknik Envanter Takip Şefliği\IPC\A320\" &D164&"\"& A164 & ".png", "Resim için basınız") -> Resim için basınız
A165: 106-1-1100-02 | B165: APU ACTUATOR-AIR INTAKE | D165: 49 | E165: #N/A | F165: 76 | G165: 768963.8 | I165: =HYPERLINK("\\avrasya\THY_BSK_TEKNIK\MD_TEKNIK_ANLASMALAR_VE_ODEMELER\Teknik Envanter Takip Şefliği\IPC\A320\" &D165&"\"& A165 & ".png", "Resim için basınız") -> Resim için basınız
A166: 106-1-1100-03 | B166: APU ACTUATOR-AIR INTAKE | D166: 49 | E166: #N/A | F166: 203 | G166: 768963.8 | I166: =HYPERLINK("\\avrasya\THY_BSK_TEKNIK\MD_TEKNIK_ANLASMALAR_VE_ODEMELER\Teknik Envanter Takip Şefliği\IPC\A320\" &D166&"\"& A166 & ".png", "Resim için basınız") -> Resim için basınız
A167: 4950014 | B167: APU CIT SENSOR | D167: 49 | E167: FUEL | F167: 1 | G167: 1772.17 | I167: =HYPERLINK("\\avrasya\THY_BSK_TEKNIK\MD_TEKNIK_ANLASMALAR_VE_ODEMELER\Teknik Envanter Takip Şefliği\IPC\A320\" &D167&"\"& A167 & ".png", "Resim için basınız") -> Resim için basınız
A168: 3888394-221204 | B168: APU ECB | D168: 49 | E168: FUEL | F168: 3 | G168: 34778.9 | I168: =HYPERLINK("\\avrasya\THY_BSK_TEKNIK\MD_TEKNIK_ANLASMALAR_VE_ODEMELER\Teknik Envanter Takip Şefliği\IPC\A320\" &D168&"\"& A168 & ".png", "Resim için basınız") -> Resim için basınız
A169: 3888394-221205 | B169: APU ECB | D169: 49 | E169: FUEL | F169: 11 | G169: 1013995.5 | I169: =HYPERLINK("\\avrasya\THY_BSK_TEKNIK\MD_TEKNIK_ANLASMALAR_VE_ODEMELER\Teknik Envanter Takip Şefliği\IPC\A320\" &D169&"\"& A169 & ".png", "Resim için basınız") -> Resim için basınız
A170: 4500003K | B170: APU ECU | D170: 49 | E170: FUEL | F170: 6 | G170: 18285.04 | I170: =HYPERLINK("\\avrasya\THY_BSK_TEKNIK\MD_TEKNIK_ANLASMALAR_VE_ODEMELER\Teknik Envanter Takip Şefliği\IPC\A320\" &D170&"\"& A170 & ".png", "Resim için basınız") -> Resim için basınız
A171: 4500003L | B171: APU ECU | D171: 49 | E171: FUEL | F171: 23 | G171: 18285.04 | I171: =HYPERLINK("\\avrasya\THY_BSK_TEKNIK\MD_TEKNIK_ANLASMALAR_VE_ODEMELER\Teknik Envanter Takip Şefliği\IPC\A320\" &D171&"\"& A171 & ".png", "Resim için basınız") -> Resim için basınız
A172: 4500003M | B172: APU ECU | D172: 49 | E172: FUEL | F172: 78 | G172: 26571.75 | I172: =HYPERLINK("\\avrasya\THY_BSK_TEKNIK\MD_TEKNIK_ANLASMALAR_VE_ODEMELER\Teknik Envanter Takip Şefliği\IPC\A320\" &D172&"\"& A172 & ".png", "Resim için basınız") -> Resim için basınız
A173: 472412-1 | B173: APU FIRE EXTINGUISHER | D173: 26 | E173: FUEL | F173: 17 | G173: 95587.06 | I173: =HYPERLINK("\\avrasya\THY_BSK_TEKNIK\MD_TEKNIK_ANLASMALAR_VE_ODEMELER\Teknik Envanter Takip Şefliği\IPC\A320\" &D173&"\"& A173 & ".png", "Resim için basınız") -> Resim için basınız
A174: FRH100013A | B174: APU FUEL PRESSURE SWITCH | D174: 28 | E174: INSTRMNT | F174: 254 | G174: 15963.61 | I174: =HYPERLINK("\\avrasya\THY_BSK_TEKNIK\MD_TEKNIK_ANLASMALAR_VE_ODEMELER\Teknik Envanter Takip Şefliği\IPC\A320\" &D174&"\"& A174 & ".png", "Resim için basınız") -> Resim için basınız
A175: 20700-300 | B175: APU FUEL VALVE | D175: 28 | E175: INSTRMNT | F175: 204 | G175: 5682.43 | I175: =HYPERLINK("\\avrasya\THY_BSK_TEKNIK\MD_TEKNIK_ANLASMALAR_VE_ODEMELER\Teknik Envanter Takip Şefliği\IPC\A320\" &D175&"\"& A175 & ".png", "Resim için basınız") -> Resim için basınız
A176: BA16501-01 | B176: APU GENERATOR | D176: 24 | E176: INSTRMNT | F176: 177 | G176: 4795170.4 | I176: =HYPERLINK("\\avrasya\THY_BSK_TEKNIK\MD_TEKNIK_ANLASMALAR_VE_ODEMELER\Teknik Envanter Takip Şefliği\IPC\A320\" &D176&"\"& A176 & ".png", "Resim için basınız") -> Resim için basınız
A177: 5913667-4 | B177: APU GENERATOR | D177: 24 | E177: MECHANIC | F177: 13 | G177: 2829729 | I177: =HYPERLINK("\\avrasya\THY_BSK_TEKNIK\MD_TEKNIK_ANLASMALAR_VE_ODEMELER\Teknik Envanter Takip Şefliği\IPC\A320\" &D177&"\"& A177 & ".png", "Resim için basınız") -> Resim için basınız
A178: 4950000 | B178: APU IGNITION EXCITER | D178: 49 | E178: FUEL | F178: 107 | G178: 41501.88 | I178: =HYPERLINK("\\avrasya\THY_BSK_TEKNIK\MD_TEKNIK_ANLASMALAR_VE_ODEMELER\Teknik Envanter Takip Şefliği\IPC\A320\" &D178&"\"& A178 & ".png", "Resim için basınız") -> Resim için basınız
... A221: 177900-103 | B221: AUDIO/VIDEO SERVER | D221: 23 | E221: HYDRAUL | F221: 7 | G221: 306232.05 | I221: =HYPERLINK("\\avrasya\THY_BSK_TEKNIK\MD_TEKNIK_ANLASMALAR_VE_ODEMELER\Teknik Envanter Takip Şefliği\IPC\A320\" &D221&"\"& A221 & ".png", "Resim için basınız") -> Resim için basınız
A222: 01N65900 | B222: AUTOMATIC FIXED ELT | D222: 25 | E222: #N/A | F222: 361 | G222: 70612.24 | I222: =HYPERLINK("\\avrasya\THY_BSK_TEKNIK\MD_TEKNIK_ANLASMALAR_VE_ODEMELER\Teknik Envanter Takip Şefliği\IPC\A320\" &D222&"\"& A222 & ".png", "Resim için basınız") -> Resim için basınız
A223: EVT3454HM01 | B223: AVIONIC FAN | D223: 21 | E223: INSTRMNT | F223: 214 | G223: 271511.8 | I223: =HYPERLINK("\\avrasya\THY_BSK_TEKNIK\MD_TEKNIK_ANLASMALAR_VE_ODEMELER\Teknik Envanter Takip Şefliği\IPC\A320\" &D223&"\"& A223 & ".png", "Resim için basınız") -> Resim için basınız
A224: AE1819B00 | B224: AVIONIC FAN | D224: 21 | E224: GALLEY | F224: 193 | G224: 938443.93 | I224: =HYPERLINK("\\avrasya\THY_BSK_TEKNIK\MD_TEKNIK_ANLASMALAR_VE_ODEMELER\Teknik Envanter Takip Şefliği\IPC\A320\" &D224&"\"& A224 & ".png", "Resim için basınız") -> Resim için basınız
A225: EVT3454HC | B225: AVIONIC FAN | D225: 21 | E225: INSTRMNT | F225: 28 | G225: 211674.09 | I225: =HYPERLINK("\\avrasya\THY_BSK_TEKNIK\MD_TEKNIK_ANLASMALAR_VE_ODEMELER\Teknik Envanter Takip Şefliği\IPC\A320\" &D225&"\"& A225 & ".png", "Resim için basınız") -> Resim için basınız
A226: 8178-1 | B226: BALLAST - LAVATORY LIGHT | D226: 33 | E226: SANITARY | F226: 35 | G226: 13156.36 | I226: =HYPERLINK("\\avrasya\THY_BSK_TEKNIK\MD_TEKNIK_ANLASMALAR_VE_ODEMELER\Teknik Envanter Takip Şefliği\IPC\A320\" &D226&"\"& A226 & ".png", "Resim için basınız") -> Resim için basınız
A227: 3250-70 | B227: BALLAST UNIT | D227: 33 | E227: WHEEL | F227: 30 | G227: 178.17 | I227: =HYPERLINK("\\avrasya\THY_BSK_TEKNIK\MD_TEKNIK_ANLASMALAR_VE_ODEMELER\Teknik Envanter Takip Şefliği\IPC\A320\" &D227&"\"& A227 & ".png", "Resim için basınız") -> Resim için basınız
A228: 3250-81 | B228: BALLAST UNIT | D228: 33 | E228: WHEEL | F228: 209 | G228: 5040.06 | I228: =HYPERLINK("\\avrasya\THY_BSK_TEKNIK\MD_TEKNIK_ANLASMALAR_VE_ODEMELER\Teknik Envanter Takip Şefliği\IPC\A320\" &D228&"\"& A228 & ".png", "Resim için basınız") -> Resim için basınız
A229: 3250-31 | B229: BALLAST UNIT | D229: 33 | E229: WHEEL | F229: 43 | G229: 5040.08 | I229: =HYPERLINK("\\avrasya\THY_BSK_TEKNIK\MD_TEKNIK_ANLASMALAR_VE_ODEMELER\Teknik Envanter Takip Şefliği\IPC\A320\" &D229&"\"& A229 & ".png", "Resim için basınız") -> Resim için basınız
A230: 3250-30 | B230: BALLAST UNIT | D230: 33 | E230: WHEEL | F230: 19 | G230: 3914.79 | I230: =HYPERLINK("\\avrasya\THY_BSK_TEKNIK\MD_TEKNIK_ANLASMALAR_VE_ODEMELER\Teknik Envanter Takip Şefliği\IPC\A320\" &D230&"\"& A230 & ".png", "Resim için basınız") -> Resim için basınız
A231: 3250-80 | B231: BALLAST UNIT | D231: 33 | E231: WHEEL | F231: 20 | G231: 5040.06 | I231: =HYPERLINK("\\avrasya\THY_BSK_TEKNIK\MD_TEKNIK_ANLASMALAR_VE_ODEMELER\Teknik Envanter Takip Şefliği\IPC\A320\" &D231&"\"& A231 & ".png", "Resim için basınız") -> Resim için basınız
A232: 4197-10-02 | B232: BALLAST UNIT (AIBU), 15W | D232: 33 | E232: FUEL | F232: 200 | G232: 21452.9 | I232: =HYPERLINK("\\avrasya\THY_BSK_TEKNIK\MD_TEKNIK_ANLASMALAR_VE_ODEMELER\Teknik Envanter Takip Şefliği\IPC\A320\" &D232&"\"& A232 & ".png", "Resim için basınız") -> Resim için basınız
A233: 4197-10-04 | B233: BALLAST UNIT (AIBU), 15W | D233: 33 | E233: FUEL | F233: 157 | G233: 48830.49 | I233: =HYPERLINK("\\avrasya\THY_BSK_TEKNIK\MD_TEKNIK_ANLASMALAR_VE_ODEMELER\Teknik Envanter Takip Şefliği\IPC\A320\" &D233&"\"& A233 & ".png", "Resim için basınız") -> Resim için basınız
A234: 4197-20-02 | B234: BALLAST UNIT (AIBU), 30W | D234: 33 | E234: FUEL | F234: 398 | G234: 20996.52 | I234: =HYPERLINK("\\avrasya\THY_BSK_TEKNIK\MD_TEKNIK_ANLASMALAR_VE_ODEMELER\Teknik Envanter Takip Şefliği\IPC\A320\" &D234&"\"& A234 & ".png", "Resim için basınız") -> Resim için basınız
A235: 4197-20-04 | B235: BALLAST UNIT (AIBU), 30W | D235: 33 | E235: FUEL | F235: 753 | G235: 15027.52 | I235: =HYPERLINK("\\avrasya\THY_BSK_TEKNIK\MD_TEKNIK_ANLASMALAR_VE_ODEMELER\Teknik Envanter Takip Şefliği\IPC\A320\" &D235&"\"& A235 & ".png", "Resim için basınız") -> Resim için basınız
A236: 121664-8 | B236: BALLSCREW ACTUATOR | D236: 75 | E236: #N/A | F236: 51 | G236: 65840.27 | I236: =HYPERLINK("\\avrasya\THY_BSK_TEKNIK\MD_TEKNIK_ANLASMALAR_VE_ODEMELER\Teknik Envanter Takip Şefliği\IPC\A320\" &D236&"\"& A236 & ".png", "Resim için basınız") -> Resim için basınız
A237: 201661206 | B237: BANANA LINK SUBASSY | D237: 32 | E237: ELECTMEC | F237: 267 | G237: 10119.19 | I237: =HYPERLINK("\\avrasya\THY_BSK_TEKNIK\MD_TEKNIK_ANLASMALAR_VE_ODEMELER\Teknik Envanter Takip Şefliği\IPC\A320\" &D237&"\"& A237 & ".png", "Resim için basınız") -> Resim için basınız
A238: 35-0L5-1005-08 | B238: BATTERY CHARGE LIMITER | D238: 24 | E238: WHEEL | F238: 115 | G238: 358835.92 | I238: =HYPERLINK("\\avrasya\THY_BSK_TEKNIK\MD_TEKNIK_ANLASMALAR_VE_ODEMELER\Teknik Envanter Takip Şefliği\IPC\A320\" &D238&"\"& A238 & ".png", "Resim için basınız") -> Resim için basınız
...

Sheet A320
A1: PID_PN | B1: PN DESC | C1: ilgili | D1: Chapter | E1: Sub Category | F1: QTY | G1: FA Amount | H1: Fonksiyonu | I1: Görsel | J1: Resim notu
A2: 3840160-8 | B2: 1.STG.TURBINE ROTOR ASSY. | D2: 49 | E2: APU | F2: 6 | G2: 143000 | I2: =HYPERLINK("\\avrasya\THY_BSK_TEKNIK\MD_TEKNIK_ANLASMALAR_VE_ODEMELER\Teknik Envanter Takip Şefliği\IPC\A320\" &D2&"\"& A2 & ".png", "Resim için basınız") -> Resim için basınız
A3: 3840310-3 | B3: 1.STG.TURBINE ROTOR ASSY. | D3: 49 | E3: APU | F3: 31 | G3: 1885048.1 | I3: =HYPERLINK("\\avrasya\THY_BSK_TEKNIK\MD_TEKNIK_ANLASMALAR_VE_ODEMELER\Teknik Envanter Takip Şefliği\IPC\A320\" &D3&"\"& A3 & ".png", "Resim için basınız") -> Resim için basınız
A4: 3840310-4 | B4: 1.STG.TURBINE ROTOR ASSY. | D4: 49 | E4: APU | F4: 240 | G4: 1913751.7 | I4: =HYPERLINK("\\avrasya\THY_BSK_TEKNIK\MD_TEKNIK_ANLASMALAR_VE_ODEMELER\Teknik Envanter Takip Şefliği\IPC\A320\" &D4&"\"& A4 & ".png", "Resim için basınız") -> Resim için basınız
A5: 201158007 | B5: 1M ELECT.HARNESS,AXLE-LH | C5: TAHA | D5: 32 | E5: HARNESS | F5: 1 | G5: 0 | H5: İniş Takımı aksı üzerinde elektrik kablolarını taşıyarak sistemin elektriksel bağlantısını sağlar | I5: =HYPERLINK("\\avrasya\THY_BSK_TEKNIK\MD_TEKNIK_ANLASMALAR_VE_ODEMELER\Teknik Envanter Takip Şefliği\IPC\A320\32\"& A5 & ".png", "Resim için basınız") -> Resim için basınız | J5: Resim girildi
A6: 201134016 | B6: 1M ELECT.HARNESS,LEG-R/H | C6: TAHA | D6: 32 | E6: HARNESS | F6: 1 | G6: 0 | H6: İniş takımı bacağı boyunca elektrik sinyallerini sensörlere ve kontrol sistemine ileterek iniş takımı sisteminin çalışmasını sağlar | I6: =HYPERLINK("\\avrasya\THY_BSK_TEKNIK\MD_TEKNIK_ANLASMALAR_VE_ODEMELER\Teknik Envanter Takip Şefliği\IPC\A320\" &D6&"\"& A6 & ".png", "Resim için basınız") -> Resim için basınız | J6: Resim girildi
A7: D23627000 | B7: 1M UPPER ELEC.HARNESS | C7: TAHA | D7: 32 | E7: HARNESS | F7: 82 | G7: 18208.8 | H7: İniş takımı üst kısımdaki sensör, gösterge ve kontrol bileşenlerine elektrik bağlantısı sağlayarak sistemin veri ve güç akışını gerçekleştirir. | I7: =HYPERLINK("\\avrasya\THY_BSK_TEKNIK\MD_TEKNIK_ANLASMALAR_VE_ODEMELER\Teknik Envanter Takip Şefliği\IPC\A320\" &D7&"\"& A7 & ".png", "Resim için basınız") -> Resim için basınız | J7: Resim girildi
A8: D23627000-1 | B8: 1M UPPER ELEC.HARNESS | C8: TAHA | D8: 32 | E8: HARNESS | F8: 8 | G8: 463103.89 | H8: İniş takımı üst kısımdaki sensör, gösterge ve kontrol bileşenlerine elektrik bağlantısı sağlayarak sistemin veri ve güç akışını gerçekleştirir. | I8: =HYPERLINK("\\avrasya\THY_BSK_TEKNIK\MD_TEKNIK_ANLASMALAR_VE_ODEMELER\Teknik Envanter Takip Şefliği\IPC\A320\" &D8&"\"& A8 & ".png", "Resim için basınız") -> Resim için basınız | J8: Resim girildi
A9: 4520563 | B9: 1ST STG TURBINE DISK ASSEMBLY | C9: TAHA | D9: 49 | E9: APU | F9: 7 | G9: 3416407.5 | H9: Yanma odasından gelen sıcak gazı mekanik enerjiye çevirerek APU kompresörünün ve jeneratörünün dönmesini sağlar | I9: =HYPERLINK("\\avrasya\THY_BSK_TEKNIK\MD_TEKNIK_ANLASMALAR_VE_ODEMELER\Teknik Envanter Takip Şefliği\IPC\A320\" &D9&"\"& A9 & ".png", "Resim için basınız") -> Resim için basınız | J9: Resim girildi
A10: 4505475 | B10: 1ST STG TURBINE WHEEL ASY | D10: 49 | E10: APU | F10: 36 | G10: 3129113.3 | I10: =HYPERLINK("\\avrasya\THY_BSK_TEKNIK\MD_TEKNIK_ANLASMALAR_VE_ODEMELER\Teknik Envanter Takip Şefliği\IPC\A320\" &D10&"\"& A10 & ".png", "Resim için basınız") -> Resim için basınız
A11: 2A9002 | B11: 2.STG HPT BLADE | D11: 72 | E11: ENGINE | F11: 471 | G11: 17899.87 | I11: =HYPERLINK("\\avrasya\THY_BSK_TEKNIK\MD_TEKNIK_ANLASMALAR_VE_ODEMELER\Teknik Envanter Takip Şefliği\IPC\A320\" &D11&"\"& A11 & ".png", "Resim için basınız") -> Resim için basınız
A12: 3840165-4 | B12: 2.STG. TURBINE ROTOR ASSY | D12: 49 | E12: APU | F12: 95 | G12: 1177872.9 | I12: =HYPERLINK("\\avrasya\THY_BSK_TEKNIK\MD_TEKNIK_ANLASMALAR_VE_ODEMELER\Teknik Envanter Takip Şefliği\IPC\A320\" &D12&"\"& A12 & ".png", "Resim için basınız") -> Resim için basınız
A13: 3840165-9 | B13: 2.STG. TURBINE WHEEL | D13: 49 | E13: APU | F13: 186 | G13: 1208340.3 | I13: =HYPERLINK("\\avrasya\THY_BSK_TEKNIK\MD_TEKNIK_ANLASMALAR_VE_ODEMELER\Teknik Envanter Takip Şefliği\IPC\A320\" &D13&"\"& A13 & ".png", "Resim için basınız") -> Resim için basınız
A14: 201168021 | B14: 2M ELECT,HARNESS,LEG-L/H | D14: 32 | E14: HARNESS | F14: 1 | G14: 0 | I14: =HYPERLINK("\\avrasya\THY_BSK_TEKNIK\MD_TEKNIK_ANLASMALAR_VE_ODEMELER\Teknik Envanter Takip Şefliği\IPC\A320\" &D14&"\"& A14 & ".png", "Resim için basınız") -> Resim için basınız
A15: D23628000-1 | B15: 2M UPPER ELEC.HARNESS | D15: 32 | E15: HARNESS | F15: 73 | G15: 15393.69 | I15: =HYPERLINK("\\avrasya\THY_BSK_TEKNIK\MD_TEKNIK_ANLASMALAR_VE_ODEMELER\Teknik Envanter Takip Şefliği\IPC\A320\" &D15&"\"& A15 & ".png", "Resim için basınız") -> Resim için basınız
A16: D23628000 | B16: 2M UPPER ELEC.HARNESS | D16: 32 | E16: HARNESS | F16: 6 | G16: 0 | I16: =HYPERLINK("\\avrasya\THY_BSK_TEKNIK\MD_TEKNIK_ANLASMALAR_VE_ODEMELER\Teknik Envanter Takip Şefliği\IPC\A320\" &D16&"\"& A16 & ".png", "Resim için basınız") -> Resim için basınız
A17: 10-375401-001 | B17: 2M UPPER ELEC.HARNESS | D17: 32 | E17: HARNESS | F17: 5 | G17: 294948.58 | I17: =HYPERLINK("\\avrasya\THY_BSK_TEKNIK\MD_TEKNIK_ANLASMALAR_VE_ODEMELER\Teknik Envanter Takip Şefliği\IPC\A320\" &D17&"\"& A17 & ".png", "Resim için basınız") -> Resim için basınız
A18: D23628000-2 | B18: 2M UPPER ELEC.HARNESS | D18: 32 | E18: HARNESS | F18: 8 | G18: 542362.78 | I18: =HYPERLINK("\\avrasya\THY_BSK_TEKNIK\MD_TEKNIK_ANLASMALAR_VE_ODEMELER\Teknik Envanter Takip Şefliği\IPC\A320\" &D18&"\"& A18 & ".png", "Resim için basınız") -> Resim için basınız
A19: 4505477B | B19: 2ND STG TURBINE WHEEL | D19: 49 | E19: APU | F19: 71 | G19: 2587126 | I19: =HYPERLINK("\\avrasya\THY_BSK_TEKNIK\MD_TEKNIK_ANLASMALAR_VE_ODEMELER\Teknik Envanter Takip Şefliği\IPC\A320\" &D19&"\"& A19 & ".png", "Resim için basınız") -> Resim için basınız
A20: 4505477 | B20: 2ND STG TURBINE WHEEL | D20: 49 | E20: APU | F20: 3 | G20: 2810163.6 | I20: =HYPERLINK("\\avrasya\THY_BSK_TEKNIK\MD_TEKNIK_ANLASMALAR_VE_ODEMELER\Teknik Envanter Takip Şefliği\IPC\A320\" &D20&"\"& A20 & ".png", "Resim için basınız") -> Resim için basınız
A21: 4520482 | B21: 2ND STG TURBINE WHEEL | D21: 49 | E21: APU | F21: 32 | G21: 2810163.6 | I21: =HYPERLINK("\\avrasya\THY_BSK_TEKNIK\MD_TEKNIK_ANLASMALAR_VE_ODEMELER\Teknik Envanter Takip Şefliği\IPC\A320\" &D21&"\"& A21 & ".png", "Resim için basınız") -> Resim için basınız
A22: S4-3400950-06 | B22: 3-2 WAY VALVE | D22: 29 | E22: HYDRAUL | F22: 1 | G22: 6324.23 | I22: =HYPERLINK("\\avrasya\THY_BSK_TEKNIK\MD_TEKNIK_ANLASMALAR_VE_ODEMELER\Teknik Envanter Takip Şefliği\IPC\A320\" &D22&"\"& A22 & ".png", "Resim için basınız") -> Resim için basınız
A23: RD-AA8190-01 | B23: 4G ENHANCED CELL MODEM (4G ECM) | D23: 23 | E23: IFE | F23: 247 | G23: 898253.44 | I23: =HYPERLINK("\\avrasya\THY_BSK_TEKNIK\MD_TEKNIK_ANLASMALAR_VE_ODEMELER\Teknik Envanter Takip Şefliği\IPC\A320\" &D23&"\"& A23 & ".png", "Resim için basınız") -> Resim için basınız
A24: AA1051-00 | B24: 7HP COMP.SOLENOID VALVE | D24: 75 | E24: PNEUMATC | F24: 389 | G24: 111512.19 | I24: =HYPERLINK("\\avrasya\THY_BSK_TEKNIK\MD_TEKNIK_ANLASMALAR_VE_ODEMELER\Teknik Envanter Takip Şefliği\IPC\A320\" &D24&"\"& A24 & ".png", "Resim için basınız") -> Resim için basınız
A25: AA1056-00 | B25: 7HP COMP.SOLENOID VALVE | D25: 75 | E25: PNEUMATC | F25: 377 | G25: 54586.77 | I25: =HYPERLINK("\\avrasya\THY_BSK_TEKNIK\MD_TEKNIK_ANLASMALAR_VE_ODEMELER\Teknik Envanter Takip Şefliği\IPC\A320\" &D25&"\"& A25 & ".png", "Resim için basınız") -> Resim için basınız
A26: AC69572 | B26: 7HP COMP.SOLENOID VALVE | D26: 75 | E26: PNEUMATC | F26: 12 | G26: 49938 | I26: =HYPERLINK("\\avrasya\THY_BSK_TEKNIK\MD_TEKNIK_ANLASMALAR_VE_ODEMELER\Teknik Envanter Takip Şefliği\IPC\A320\" &D26&"\"& A26 & ".png", "Resim için basınız") -> Resim için basınız
A27: 617-6231-001 | B27: 8.6? LH LCD RETRACT MON | D27: 23 | E27: IFE | F27: 1 | G27: 4964.7 | I27: =HYPERLINK("\\avrasya\THY_BSK_TEKNIK\MD_TEKNIK_ANLASMALAR_VE_ODEMELER\Teknik Envanter Takip Şefliği\IPC\A320\" &D27&"\"& A27 & ".png", "Resim için basınız") -> Resim için basınız
A28: 617-6231-002 | B28: 8.6? RH LCD RETRACT MON. | D28: 23 | E28: IFE | F28: 1 | G28: 0.01 | I28: =HYPERLINK("\\avrasya\THY_BSK_TEKNIK\MD_TEKNIK_ANLASMALAR_VE_ODEMELER\Teknik Envanter Takip Şefliği\IPC\A320\" &D28&"\"& A28 & ".png", "Resim için basınız") -> Resim için basınız
A29: RD-AV9843-01 | B29: 10.4? LCD COLOR MONITOR | D29: 23 | E29: IFE | F29: 60 | G29: 0 | I29: =HYPERLINK("\\avrasya\THY_BSK_TEKNIK\MD_TEKNIK_ANLASMALAR_VE_ODEMELER\Teknik Envanter Takip Şefliği\IPC\A320\" &D29&"\"& A29 & ".png", "Resim için basınız") -> Resim için basınız
A30: RD-AV9844-01 | B30: 10.4? LCD DISPLAY | D30: 23 | E30: IFE | F30: 60 | G30: 0 | I30: =HYPERLINK("\\avrasya\THY_BSK_TEKNIK\MD_TEKNIK_ANLASMALAR_VE_ODEMELER\Teknik Envanter Takip Şefliği\IPC\A320\" &D30&"\"& A30 & ".png", "Resim için basınız") -> Resim için basınız
A31: TP0311-001 | B31: 10" CREW CONTROL PANEL | D31: 44 | E31: IFE | F31: 58 | G31: 95852.8 | I31: =HYPERLINK("\\avrasya\THY_BSK_TEKNIK\MD_TEKNIK_ANLASMALAR_VE_ODEMELER\Teknik Envanter Takip Şefliği\IPC\A320\" &D31&"\"& A31 & ".png", "Resim için basınız") -> Resim için basınız
A32: AA1064-00 | B32: 10HP COMP.SOLENOID VALVE | D32: 75 | E32: PNEUMATC | F32: 134 | G32: 48121.58 | I32: =HYPERLINK("\\avrasya\THY_BSK_TEKNIK\MD_TEKNIK_ANLASMALAR_VE_ODEMELER\Teknik Envanter Takip Şefliği\IPC\A320\" &D32&"\"& A32 & ".png", "Resim için basınız") -> Resim için basınız
A33: AA1060-00 | B33: 10HP COMP.SOLENOID VALVE | D33: 75 | E33: PNEUMATC | F33: 122 | G33: 240191.39 | I33: =HYPERLINK("\\avrasya\THY_BSK_TEKNIK\MD_TEKNIK_ANLASMALAR_VE_ODEMELER\Teknik Envanter Takip Şefliği\IPC\A320\" &D33&"\"& A33 & ".png", "Resim için basınız") -> Resim için basınız
... A53: 6610-20567-01 | B53: ACTUATOR | D53: 36 | E53: ELECTMEC | F53: 69 | G53: 250489.87 | I53: =HYPERLINK("\\avrasya\THY_BSK_TEKNIK\MD_TEKNIK_ANLASMALAR_VE_ODEMELER\Teknik Envanter Takip Şefliği\IPC\A320\" &D53&"\"& A53 & ".png", "Resim için basınız") -> Resim için basınız
A54: 1809A0000-01 | B54: ACTUATOR - INLET | C54: TAHA | D54: 21 | E54: ELECTMEC | F54: 419 | G54: 493027.36 | H54: Motorun ön kısmındaki hava giriş yapısını hareket ettirerek hava akışını ve buzlanma önlemini kontrol eder | I54: =HYPERLINK("\\avrasya\THY_BSK_TEKNIK\MD_TEKNIK_ANLASMALAR_VE_ODEMELER\Teknik Envanter Takip Şefliği\IPC\A320\" &D54&"\"& A54 & ".png", "Resim için basınız") -> Resim için basınız | J54: Resim girildi
A55: AD8552502-1 | B55: ACTUATOR ARTUS | D55: 25 | E55: ELECTMEC | F55: 9 | G55: 117647.88 | I55: =HYPERLINK("\\avrasya\THY_BSK_TEKNIK\MD_TEKNIK_ANLASMALAR_VE_ODEMELER\Teknik Envanter Takip Şefliği\IPC\A320\" &D55&"\"& A55 & ".png", "Resim için basınız") -> Resim için basınız
A56: 4504086 | B56: ACTUATOR ASSY | D56: 49 | E56: FUEL | F56: 32 | G56: 104212.19 | I56: =HYPERLINK("\\avrasya\THY_BSK_TEKNIK\MD_TEKNIK_ANLASMALAR_VE_ODEMELER\Teknik Envanter Takip Şefliği\IPC\A320\" &D56&"\"& A56 & ".png", "Resim için basınız") -> Resim için basınız
A57: 4510835 | B57: ACTUATOR ASSY | D57: 49 | E57: FUEL | F57: 68 | G57: 101313.75 | I57: =HYPERLINK("\\avrasya\THY_BSK_TEKNIK\MD_TEKNIK_ANLASMALAR_VE_ODEMELER\Teknik Envanter Takip Şefliği\IPC\A320\" &D57&"\"& A57 & ".png", "Resim için basınız") -> Resim için basınız
A58: A05000 | B58: ACTUATOR ASSY | D58: 38 | E58: ELECTMEC | F58: 34 | G58: 18952.28 | I58: =HYPERLINK("\\avrasya\THY_BSK_TEKNIK\MD_TEKNIK_ANLASMALAR_VE_ODEMELER\Teknik Envanter Takip Şefliği\IPC\A320\" &D58&"\"& A58 & ".png", "Resim için basınız") -> Resim için basınız
A59: B27000 | B59: ACTUATOR ASSY | D59: 28 | E59: ELECTMEC | F59: 3 | G59: 6794.88 | I59: =HYPERLINK("\\avrasya\THY_BSK_TEKNIK\MD_TEKNIK_ANLASMALAR_VE_ODEMELER\Teknik Envanter Takip Şefliği\IPC\A320\" &D59&"\"& A59 & ".png", "Resim için basınız") -> Resim için basınız
A60: A05B00 | B60: ACTUATOR ASSY | D60: 38 | E60: ELECTMEC | F60: 103 | G60: 18811.15 | I60: =HYPERLINK("\\avrasya\THY_BSK_TEKNIK\MD_TEKNIK_ANLASMALAR_VE_ODEMELER\Teknik Envanter Takip Şefliği\IPC\A320\" &D60&"\"& A60 & ".png", "Resim için basınız") -> Resim için basınız
A61: 4504086A | B61: ACTUATOR ASSY | D61: 49 | E61: FUEL | F61: 7 | G61: 32757.9 | I61: =HYPERLINK("\\avrasya\THY_BSK_TEKNIK\MD_TEKNIK_ANLASMALAR_VE_ODEMELER\Teknik Envanter Takip Şefliği\IPC\A320\" &D61&"\"& A61 & ".png", "Resim için basınız") -> Resim için basınız
A62: 5329472 | B62: ACTUATOR ASSY-HIGH PRESSURE COMPRESSOR S | D62: 75 | E62: FUEL | F62: 105 | G62: 809094.36 | I62: =HYPERLINK("\\avrasya\THY_BSK_TEKNIK\MD_TEKNIK_ANLASMALAR_VE_ODEMELER\Teknik Envanter Takip Şefliği\IPC\A320\" &D62&"\"& A62 & ".png", "Resim için basınız") -> Resim için basınız
A63: 5315196 | B63: ACTUATOR ASSY-HIGH PRESSURE COMPRESSOR S | D63: 75 | E63: ENGINE | F63: 122 | G63: 606090.98 | I63: =HYPERLINK("\\avrasya\THY_BSK_TEKNIK\MD_TEKNIK_ANLASMALAR_VE_ODEMELER\Teknik Envanter Takip Şefliği\IPC\A320\" &D63&"\"& A63 & ".png", "Resim için basınız") -> Resim için basınız
A64: 6147-6 | B64: ACTUATOR AVIAC | D64: 25 | E64: ELECTMEC | F64: 12 | G64: 117647.88 | I64: =HYPERLINK("\\avrasya\THY_BSK_TEKNIK\MD_TEKNIK_ANLASMALAR_VE_ODEMELER\Teknik Envanter Takip Şefliği\IPC\A320\" &D64&"\"& A64 & ".png", "Resim için basınız") -> Resim için basınız
A65: 6147-5 | B65: ACTUATOR AVIAC | D65: 25 | E65: ELECTMEC | F65: 2 | G65: 21067.54 | I65: =HYPERLINK("\\avrasya\THY_BSK_TEKNIK\MD_TEKNIK_ANLASMALAR_VE_ODEMELER\Teknik Envanter Takip Şefliği\IPC\A320\" &D65&"\"& A65 & ".png", "Resim için basınız") -> Resim için basınız
A66: A06L00 | B66: ACTUATOR ELECTRIC | D66: 29 | E66: ELECTMEC | F66: 63 | G66: 7537.61 | I66: =HYPERLINK("\\avrasya\THY_BSK_TEKNIK\MD_TEKNIK_ANLASMALAR_VE_ODEMELER\Teknik Envanter Takip Şefliği\IPC\A320\" &D66&"\"& A66 & ".png", "Resim için basınız") -> Resim için basınız
A67: 41-2-1100-02 | B67: ACTUATOR EMERGENCY RAM | C67: TAHA | D67: 21 | E67: ELECTMEC | F67: 202 | G67: 17687.02 | H67: Normal hidrolik sistemin çalışmadığı durumda yedek mekanik güç sağlayarak ilgili sistemin devamlılığını sağlar | I67: =HYPERLINK("\\avrasya\THY_BSK_TEKNIK\MD_TEKNIK_ANLASMALAR_VE_ODEMELER\Teknik Envanter Takip Şefliği\IPC\A320\" &D67&"\"& A67 & ".png", "Resim için basınız") -> Resim için basınız | J67: Resim girildi
A68: 321-409-900-0 | B68: ACTUATOR JUNCTION BOX | D68: 78 | E68: HYDRAUL | F68: 2 | G68: 39386.55 | I68: =HYPERLINK("\\avrasya\THY_BSK_TEKNIK\MD_TEKNIK_ANLASMALAR_VE_ODEMELER\Teknik Envanter Takip Şefliği\IPC\A320\" &D68&"\"& A68 & ".png", "Resim için basınız") -> Resim için basınız
A69: 4136290006 | B69: ACTUATOR_LABINAL | D69: 25 | E69: ELECTMEC | F69: 499 | G69: 300126.96 | I69: =HYPERLINK("\\avrasya\THY_BSK_TEKNIK\MD_TEKNIK_ANLASMALAR_VE_ODEMELER\Teknik Envanter Takip Şefliği\IPC\A320\" &D69&"\"& A69 & ".png", "Resim için basınız") -> Resim için basınız
A70: 4136290007 | B70: ACTUATOR_LABINAL | D70: 25 | E70: ELECTMEC | F70: 4 | G70: 35645.16 | I70: =HYPERLINK("\\avrasya\THY_BSK_TEKNIK\MD_TEKNIK_ANLASMALAR_VE_ODEMELER\Teknik Envanter Takip Şefliği\IPC\A320\" &D70&"\"& A70 & ".png", "Resim için basınız") -> Resim için basınız
A71: 321-400-705-0 | B71: ACTUATOR-DOOR OPENING | D71: 78 | E71: HYDRAUL | F71: 5 | G71: 432432.9 | I71: =HYPERLINK("\\avrasya\THY_BSK_TEKNIK\MD_TEKNIK_ANLASMALAR_VE_ODEMELER\Teknik Envanter Takip Şefliği\IPC\A320\" &D71&"\"& A71 & ".png", "Resim için basınız") -> Resim için basınız
A72: 321-400-707-0 | B72: ACTUATOR-DOOR OPENING | D72: 78 | E72: HYDRAUL | F72: 4 | G72: 538782.94 | I72: =HYPERLINK("\\avrasya\THY_BSK_TEKNIK\MD_TEKNIK_ANLASMALAR_VE_ODEMELER\Teknik Envanter Takip Şefliği\IPC\A320\" &D72&"\"& A72 & ".png", "Resim için basınız") -> Resim için basınız
A73: 70654A010001 | B73: ACTUATOR-ELECTROPNEUMATIC | D73: 36 | E73: PNEUMATC | F73: 61 | G73: 291268.44 | I73: =HYPERLINK("\\avrasya\THY_BSK_TEKNIK\MD_TEKNIK_ANLASMALAR_VE_ODEMELER\Teknik Envanter Takip Şefliği\IPC\A320\" &D73&"\"& A73 & ".png", "Resim için basınız") -> Resim için basınız
A74: 70654A020001 | B74: ACTUATOR-ELECTROPNEUMATIC | D74: 36 | E74: PNEUMATC | F74: 138 | G74: 533337.49 | I74: =HYPERLINK("\\avrasya\THY_BSK_TEKNIK\MD_TEKNIK_ANLASMALAR_VE_ODEMELER\Teknik Envanter Takip Şefliği\IPC\A320\" &D74&"\"& A74 & ".png", "Resim için basınız") -> Resim için basınız
A75: 636D0050-565 | B75: ACTUATOR-FEEDBACK LOCKING | D75: 78 | E75: HYDRAUL | F75: 192 | G75: 579196.32 | I75: =HYPERLINK("\\avrasya\THY_BSK_TEKNIK\MD_TEKNIK_ANLASMALAR_VE_ODEMELER\Teknik Envanter Takip Şefliği\IPC\A320\" &D75&"\"& A75 & ".png", "Resim için basınız") -> Resim için basınız
A76: S4-3300520-01 | B76: ACTUATOR-HYDRAULIC | D76: 52 | E76: HYDRAUL | F76: 16 | G76: 5095.35 | I76: =HYPERLINK("\\avrasya\THY_BSK_TEKNIK\MD_TEKNIK_ANLASMALAR_VE_ODEMELER\Teknik Envanter Takip Şefliği\IPC\A320\" &D76&"\"& A76 & ".png", "Resim için basınız") -> Resim için basınız
A77: E20000 | B77: ACTUATOR-HYDRAULIC | D77: 52 | E77: HYDRAUL | F77: 801 | G77: 99641 | I77: =HYPERLINK("\\avrasya\THY_BSK_TEKNIK\MD_TEKNIK_ANLASMALAR_VE_ODEMELER\Teknik Envanter Takip Şefliği\IPC\A320\" &D77&"\"& A77 & ".png", "Resim için basınız") -> Resim için basınız
A78: S4-3300520 | B78: ACTUATOR-HYDRAULIC | D78: 52 | E78: HYDRAUL | F78: 4 | G78: 59727.68 | I78: =HYPERLINK("\\avrasya\THY_BSK_TEKNIK\MD_TEKNIK_ANLASMALAR_VE_ODEMELER\Teknik Envanter Takip Şefliği\IPC\A320\" &D78&"\"& A78 & ".png", "Resim için basınız") -> Resim için basınız
A79: 761B0000-01 | B79: ACTUATOR-RAM AIR INLET | C79: TAHA | D79: 21 | E79: ELECTMEC | F79: 7 | G79: 11871.68 | H79: Hava giriş kısmındaki paneli mekanik olarak hareket ettirir. | I79: =HYPERLINK("\\avrasya\THY_BSK_TEKNIK\MD_TEKNIK_ANLASMALAR_VE_ODEMELER\Teknik Envanter Takip Şefliği\IPC\A320\" &D79&"\"& A79 & ".png", "Resim için basınız") -> Resim için basınız | J79: Resim girildi
A80: 761A0000-04 | B80: ACTUATOR-RAM AIR INLET | C80: TAHA | D80: 21 | E80: ELECTMEC | F80: 2 | G80: 8699.4 | H80: Hava giriş kısmındaki paneli mekanik olarak hareket ettirir. | I80: =HYPERLINK("\\avrasya\THY_BSK_TEKNIK\MD_TEKNIK_ANLASMALAR_VE_ODEMELER\Teknik Envanter Takip Şefliği\IPC\A320\" &D80&"\"& A80 & ".png", "Resim için basınız") -> Resim için basınız | J80: Resim girildi
A81: 829C0000-01 | B81: ACTUATOR-ROTARY,SLAT | D81: 27 | E81: MECHANIC | F81: 280 | G81: 9011.98 | I81: =HYPERLINK("\\avrasya\THY_BSK_TEKNIK\MD_TEKNIK_ANLASMALAR_VE_ODEMELER\Teknik Envanter Takip Şefliği\IPC\A320\" &D81&"\"& A81 & ".png", "Resim için basınız") -> Resim için basınız
A82: 829D0000-02 | B82: ACTUATOR-ROTARY,SLAT | D82: 27 | E82: MECHANIC | F82: 330 | G82: 9011.98 | I82: =HYPERLINK("\\avrasya\THY_BSK_TEKNIK\MD_TEKNIK_ANLASMALAR_VE_ODEMELER\Teknik Envanter Takip Şefliği\IPC\A320\" &D82&"\"& A82 & ".png", "Resim için basınız") -> Resim için basınız
A83: 830C0000-01 | B83: ACTUATOR-ROTARY,SLAT | D83: 27 | E83: MECHANIC | F83: 1111 | G83: 6234.47 | I83: =HYPERLINK("\\avrasya\THY_BSK_TEKNIK\MD_TEKNIK_ANLASMALAR_VE_ODEMELER\Teknik Envanter Takip Şefliği\IPC\A320\" &D83&"\"& A83 & ".png", "Resim için basınız") -> Resim için basınız
A84: 830D0000-02 | B84: ACTUATOR-ROTARY,SLAT | D84: 27 | E84: MECHANIC | F84: 1036 | G84: 258933.5 | I84: =HYPERLINK("\\avrasya\THY_BSK_TEKNIK\MD_TEKNIK_ANLASMALAR_VE_ODEMELER\Teknik Envanter Takip Şefliği\IPC\A320\" &D84&"\"& A84 & ".png", "Resim için basınız") -> Resim için basınız
A85: 830E0000-01 | B85: ACTUATOR-ROTARY,SLAT | D85: 27 | E85: MECHANIC | F85: 353 | G85: 1881.62 | I85: =HYPERLINK("\\avrasya\THY_BSK_TEKNIK\MD_TEKNIK_ANLASMALAR_VE_ODEMELER\Teknik Envanter Takip Şefliği\IPC\A320\" &D85&"\"& A85 & ".png", "Resim için basınız") -> Resim için basınız
A86: 636D0050-567 | B86: ACTUATOR-TRAS LOCKING | D86: 78 | E86: HYDRAUL | F86: 190 | G86: 546428.65 | I86: =HYPERLINK("\\avrasya\THY_BSK_TEKNIK\MD_TEKNIK_ANLASMALAR_VE_ODEMELER\Teknik Envanter Takip Şefliği\IPC\A320\" &D86&"\"& A86 & ".png", "Resim için basınız") -> Resim için basınız
A87: 1020926-1 | B87: ACTUATOR, HPC STATOR VANE | D87: 75 | E87: FUEL | F87: 70 | G87: 2809472 | I87: =HYPERLINK("\\avrasya\THY_BSK_TEKNIK\MD_TEKNIK_ANLASMALAR_VE_ODEMELER\Teknik Envanter Takip Şefliği\IPC\A320\" &D87&"\"& A87 & ".png", "Resim için basınız") -> Resim için basınız
A88: 1020927-1 | B88: ACTUATOR, HPC STATOR VANE, SECONDARY UNIT | D88: 75 | E88: ENGINE | F88: 108 | G88: 297874.99 | I88: =HYPERLINK("\\avrasya\THY_BSK_TEKNIK\MD_TEKNIK_ANLASMALAR_VE_ODEMELER\Teknik Envanter Takip Şefliği\IPC\A320\" &D88&"\"& A88 & ".png", "Resim için basınız") -> Resim için basınız
A89: 1020929-1 | B89: ACTUATOR, LPC 2.5 BLEED VALVE | D89: 75 | E89: FUEL | F89: 70 | G89: 1664734.4 | I89: =HYPERLINK("\\avrasya\THY_BSK_TEKNIK\MD_TEKNIK_ANLASMALAR_VE_ODEMELER\Teknik Envanter Takip Şefliği\IPC\A320\" &D89&"\"& A89 & ".png", "Resim için basınız") -> Resim için basınız
A90: 1020928-1 | B90: ACTUATOR, LPC STATOR VANE | D90: 75 | E90: ENGINE | F90: 73 | G90: 3653772.6 | I90: =HYPERLINK("\\avrasya\THY_BSK_TEKNIK\MD_TEKNIK_ANLASMALAR_VE_ODEMELER\Teknik Envanter Takip Şefliği\IPC\A320\" &D90&"\"& A90 & ".png", "Resim için basınız") -> Resim için basınız
A91: 6610-20560-01 | B91: ACTUATOR, ROTARY | C91: TAHA | D91: 21 | E91: ELECTMEC | F91: 239 | G91: 48451.5 | H91: Lineer actuatorların aksine bir parçanın belirli açıda dönmesini sağlar | I91: =HYPERLINK("\\avrasya\THY_BSK_TEKNIK\MD_TEKNIK_ANLASMALAR_VE_ODEMELER\Teknik Envanter Takip Şefliği\IPC\A320\" &D91&"\"& A91 & ".png", "Resim için basınız") -> Resim için basınız | J91: Resim girildi
A92: 6610-19878-1 | B92: ACTUATOR, ROTARY | D92: 21 | E92: ELECTMEC | F92: 1 | G92: 2435.78 | I92: =HYPERLINK("\\avrasya\THY_BSK_TEKNIK\MD_TEKNIK_ANLASMALAR_VE_ODEMELER\Teknik Envanter Takip Şefliği\IPC\A320\" &D92&"\"& A92 & ".png", "Resim için basınız") -> Resim için basınız
A93: 6610-19878-2 | B93: ACTUATOR, ROTARY | D93: 21 | E93: ELECTMEC | F93: 447 | G93: 55820.7 | I93: =HYPERLINK("\\avrasya\THY_BSK_TEKNIK\MD_TEKNIK_ANLASMALAR_VE_ODEMELER\Teknik Envanter Takip Şefliği\IPC\A320\" &D93&"\"& A93 & ".png", "Resim için basınız") -> Resim için basınız
A94: 6610-18520 | B94: ACTUATOR, ROTARY | D94: 21 | E94: ELECTMEC | F94: 10 | G94: 55759.5 | I94: =HYPERLINK("\\avrasya\THY_BSK_TEKNIK\MD_TEKNIK_ANLASMALAR_VE_ODEMELER\Teknik Envanter Takip Şefliği\IPC\A320\" &D94&"\"& A94 & ".png", "Resim için basınız") -> Resim için basınız
A95: A08000 | B95: ACTUATOR,APU LP FUEL SOV | D95: 28 | E95: ELECTMEC | F95: 269 | G95: 22855.2 | I95: =HYPERLINK("\\avrasya\THY_BSK_TEKNIK\MD_TEKNIK_ANLASMALAR_VE_ODEMELER\Teknik Envanter Takip Şefliği\IPC\A320\" &D95&"\"& A95 & ".png", "Resim için basınız") -> Resim için basınız
A96: 521A0200-01 | B96: ADAPTER | D96: 27 | E96: MECHANIC | F96: 25 | G96: 682.33 | I96: =HYPERLINK("\\avrasya\THY_BSK_TEKNIK\MD_TEKNIK_ANLASMALAR_VE_ODEMELER\Teknik Envanter Takip Şefliği\IPC\A320\" &D96&"\"& A96 & ".png", "Resim için basınız") -> Resim için basınız
A97: 521B0200-01 | B97: ADAPTER | D97: 27 | E97: MECHANIC | F97: 500 | G97: 23412.97 | I97: =HYPERLINK("\\avrasya\THY_BSK_TEKNIK\MD_TEKNIK_ANLASMALAR_VE_ODEMELER\Teknik Envanter Takip Şefliği\IPC\A320\" &D97&"\"& A97 & ".png", "Resim için basınız") -> Resim için basınız
A98: 615-2630-102 | B98: ADF ANTENNA | D98: 34 | E98: RADIO | F98: 210 | G98: 483360.4 | I98: =HYPERLINK("\\avrasya\THY_BSK_TEKNIK\MD_TEKNIK_ANLASMALAR_VE_ODEMELER\Teknik Envanter Takip Şefliği\IPC\A320\" &D98&"\"& A98 & ".png", "Resim için basınız") -> Resim için basınız
A99: S72-1712-8 | B99: ADF ANTENNA | D99: 34 | E99: RADIO | F99: 6 | G99: 478670.59 | I99: =HYPERLINK("\\avrasya\THY_BSK_TEKNIK\MD_TEKNIK_ANLASMALAR_VE_ODEMELER\Teknik Envanter Takip Şefliği\IPC\A320\" &D99&"\"& A99 & ".png", "Resim için basınız") -> Resim için basınız
A100: 066-50014-0202 | B100: ADF RECEIVER | D100: 34 | E100: RADIO | F100: 106 | G100: 12840.07 | I100: =HYPERLINK("\\avrasya\THY_BSK_TEKNIK\MD_TEKNIK_ANLASMALAR_VE_ODEMELER\Teknik Envanter Takip Şefliği\IPC\A320\" &D100&"\"& A100 & ".png", "Resim için basınız") -> Resim için basınız
A101: 822-0299-020 | B101: ADF RECEIVER | D101: 34 | E101: RADIO | F101: 234 | G101: 12840.07 | I101: =HYPERLINK("\\avrasya\THY_BSK_TEKNIK\MD_TEKNIK_ANLASMALAR_VE_ODEMELER\Teknik Envanter Takip Şefliği\IPC\A320\" &D101&"\"& A101 & ".png", "Resim için basınız") -> Resim için basınız
A102: 465010-0300-0300 | B102: ADIRS CDU | D102: 34 | E102: ATE | F102: 1 | G102: 35697.31 | I102: =HYPERLINK("\\avrasya\THY_BSK_TEKNIK\MD_TEKNIK_ANLASMALAR_VE_ODEMELER\Teknik Envanter Takip Şefliği\IPC\A320\" &D102&"\"& A102 & ".png", "Resim için basınız") -> Resim için basınız
A103: CG1151AC03 | B103: ADIRS CDU | D103: 34 | E103: ATE | F103: 26 | G103: 122761.5 | I103: =HYPERLINK("\\avrasya\THY_BSK_TEKNIK\MD_TEKNIK_ANLASMALAR_VE_ODEMELER\Teknik Envanter Takip Şefliği\IPC\A320\" &D103&"\"& A103 & ".png", "Resim için basınız") -> Resim için basınız
... A322: 176900-00 | B322: BOTTLE,OXYGEN,MEDICAL | D322: 35 | E322: OXYGEN | F322: 180 | G322: 28138.8 | I322: =HYPERLINK("\\avrasya\THY_BSK_TEKNIK\MD_TEKNIK_ANLASMALAR_VE_ODEMELER\Teknik Envanter Takip Şefliği\IPC\A320\" &D322&"\"& A322 & ".png", "Resim için basınız") -> Resim için basınız
A323: 176900 | B323: BOTTLE,OXYGEN,MEDICAL | D323: 35 | E323: OXYGEN | F323: 77 | G323: 26114.7 | I323: =HYPERLINK("\\avrasya\THY_BSK_TEKNIK\MD_TEKNIK_ANLASMALAR_VE_ODEMELER\Teknik Envanter Takip Şefliği\IPC\A320\" &D323&"\"& A323 & ".png", "Resim için basınız") -> Resim için basınız
A324: 70895-1 | B324: BOX ASSY | D324: 38 | E324: HYDRAUL | F324: 324 | G324: 331935.93 | I324: =HYPERLINK("\\avrasya\THY_BSK_TEKNIK\MD_TEKNIK_ANLASMALAR_VE_ODEMELER\Teknik Envanter Takip Şefliği\IPC\A320\" &D324&"\"& A324 & ".png", "Resim için basınız") -> Resim için basınız
A325: 600629-10-500 | B325: BOX-CONTROL | D325: 25 | E325: ATE | F325: 28 | G325: 8409.31 | I325: =HYPERLINK("\\avrasya\THY_BSK_TEKNIK\MD_TEKNIK_ANLASMALAR_VE_ODEMELER\Teknik Envanter Takip Şefliği\IPC\A320\" &D325&"\"& A325 & ".png", "Resim için basınız") -> Resim için basınız
A326: 088256-04644 | B326: BRAKE ACCUMULATOR | D326: 32 | E326: HYDRAUL | F326: 378 | G326: 249441.61 | I326: =HYPERLINK("\\avrasya\THY_BSK_TEKNIK\MD_TEKNIK_ANLASMALAR_VE_ODEMELER\Teknik Envanter Takip Şefliği\IPC\A320\" &D326&"\"& A326 & ".png", "Resim için basınız") -> Resim için basınız
A327: C20374000-2 | B327: BRAKE SERVOVALVE | D327: 32 | E327: HYDRAUL | F327: 338 | G327: 199951.52 | I327: =HYPERLINK("\\avrasya\THY_BSK_TEKNIK\MD_TEKNIK_ANLASMALAR_VE_ODEMELER\Teknik Envanter Takip Şefliği\IPC\A320\" &D327&"\"& A327 & ".png", "Resim için basınız") -> Resim için basınız
A328: 2-1684 | B328: BRAKE ASSY CARBON | D328: 32 | E328: BRAKE | F328: 24 | G328: 2054857.7 | I328: =HYPERLINK("\\avrasya\THY_BSK_TEKNIK\MD_TEKNIK_ANLASMALAR_VE_ODEMELER\Teknik Envanter Takip Şefliği\IPC\A320\" &D328&"\"& A328 & ".png", "Resim için basınız") -> Resim için basınız
A329: C20225510 | B329: BRAKE ASSY., CARBON | D329: 32 | E329: BRAKE | F329: 162 | G329: 1435125.2 | I329: =HYPERLINK("\\avrasya\THY_BSK_TEKNIK\MD_TEKNIK_ANLASMALAR_VE_ODEMELER\Teknik Envanter Takip Şefliği\IPC\A320\" &D329&"\"& A329 & ".png", "Resim için basınız") -> Resim için basınız
A330: C20225508 | B330: BRAKE ASSY., CARBON | D330: 32 | E330: BRAKE | F330: 15 | G330: 1435125.2 | I330: =HYPERLINK("\\avrasya\THY_BSK_TEKNIK\MD_TEKNIK_ANLASMALAR_VE_ODEMELER\Teknik Envanter Takip Şefliği\IPC\A320\" &D330&"\"& A330 & ".png", "Resim için basınız") -> Resim için basınız
A331: C20225509 | B331: BRAKE ASSY., CARBON | D331: 32 | E331: BRAKE | F331: 9 | G331: 1465364.3 | I331: =HYPERLINK("\\avrasya\THY_BSK_TEKNIK\MD_TEKNIK_ANLASMALAR_VE_ODEMELER\Teknik Envanter Takip Şefliği\IPC\A320\" &D331&"\"& A331 & ".png", "Resim için basınız") -> Resim için basınız
A332: C20215000 | B332: BRAKE PEDAL TRANSMITTER | D332: 32 | E332: INSTRMNT | F332: 48 | G332: 15340 | I332: =HYPERLINK("\\avrasya\THY_BSK_TEKNIK\MD_TEKNIK_ANLASMALAR_VE_ODEMELER\Teknik Envanter Takip Şefliği\IPC\A320\" &D332&"\"& A332 & ".png", "Resim için basınız") -> Resim için basınız
A333: 727-1600-01 | B333: BRAKE PRESSURE INDICATOR | D333: 32 | E333: INSTRMNT | F333: 117 | G333: 576994.71 | I333: =HYPERLINK("\\avrasya\THY_BSK_TEKNIK\MD_TEKNIK_ANLASMALAR_VE_ODEMELER\Teknik Envanter Takip Şefliği\IPC\A320\" &D333&"\"& A333 & ".png", "Resim için basınız") -> Resim için basınız
A334: 64882-206-1 | B334: BRAKE PRESSURE INDICATOR | D334: 32 | E334: INSTRMNT | F334: 90 | G334: 611747.76 | I334: =HYPERLINK("\\avrasya\THY_BSK_TEKNIK\MD_TEKNIK_ANLASMALAR_VE_ODEMELER\Teknik Envanter Takip Şefliği\IPC\A320\" &D334&"\"& A334 & ".png", "Resim için basınız") -> Resim için basınız
A335: A25313002 | B335: BRAKE SELECTOR VALVE | D335: 32 | E335: HYDRAUL | F335: 2 | G335: 0 | I335: =HYPERLINK("\\avrasya\THY_BSK_TEKNIK\MD_TEKNIK_ANLASMALAR_VE_ODEMELER\Teknik Envanter Takip Şefliği\IPC\A320\" &D335&"\"& A335 & ".png", "Resim için basınız") -> Resim için basınız
... A3331: 114079017 | B3331: LG SELECTOR VALVE | D3331: 32 | E3331: HYDRAUL | F3331: 1 | G3331: 0 | I3331: =HYPERLINK("\\avrasya\THY_BSK_TEKNIK\MD_TEKNIK_ANLASMALAR_VE_ODEMELER\Teknik Envanter Takip Şefliği\IPC\A320\" &D3331&"\"& A3331 & ".png", "Resim için basınız") -> Resim için basınız
A3332: 326373 | B3332: CHECK VALVE | D3332: 29 | E3332: HYDRAUL | F3332: 2 | G3332: 0 | I3332: =HYPERLINK("\\avrasya\THY_BSK_TEKNIK\MD_TEKNIK_ANLASMALAR_VE_ODEMELER\Teknik Envanter Takip Şefliği\IPC\A320\" &D3332&"\"& A3332 & ".png", "Resim için basınız") -> Resim için basınız
...

Sheet A321
A1: PN | B1: PN DESC | C1: ilgili | D1: Chapter | E1: Sub Category | F1: QTY | G1: FA Amount | H1: Fonksiyonu | I1: Görsel | J1: Resim Notu
A2: PW1133GA-JM | B2: PW1100GA-JM ENGINE | D2: 72 | E2: ENGINE | F2: 226 | G2: 4.168259e+08 | I2: =HYPERLINK("\\avrasya\THY_BSK_TEKNIK\MD_TEKNIK_ANLASMALAR_VE_ODEMELER\Teknik Envanter Takip Şefliği\IPC\A321\" &D2&"\"& A2 & ".png", "Resim için basınız") -> Resim için basınız
A3: 10-454301-002 | B3: LEG ASSY AND DRESSINGS, MLG (LH) | D3: 32 | E3: LDG | F3: 14 | G3: 38114000 | I3: =HYPERLINK("\\avrasya\THY_BSK_TEKNIK\MD_TEKNIK_ANLASMALAR_VE_ODEMELER\Teknik Envanter Takip Şefliği\IPC\A321\" &D3&"\"& A3 & ".png", "Resim için basınız") -> Resim için basınız
A4: V2533-A5 | B4: V2500 ENGINE | D4: 72 | E4: ENGINE | F4: 157 | G4: 32875390 | I4: =HYPERLINK("\\avrasya\THY_BSK_TEKNIK\MD_TEKNIK_ANLASMALAR_VE_ODEMELER\Teknik Envanter Takip Şefliği\IPC\A321\" &D4&"\"& A4 & ".png", "Resim için basınız") -> Resim için basınız
A5: 10-375902-005 | B5: NLG LEG ASSY | D5: 32 | E5: LDG | F5: 19 | G5: 15553175 | I5: =HYPERLINK("\\avrasya\THY_BSK_TEKNIK\MD_TEKNIK_ANLASMALAR_VE_ODEMELER\Teknik Envanter Takip Şefliği\IPC\A321\" &D5&"\"& A5 & ".png", "Resim için basınız") -> Resim için basınız
A6: RD-NB2112-02 | B6: SINGLE PANEL GCS ANTENNA (SPA-02) | D6: 23 | E6: IFE | F6: 133 | G6: 14274280 | I6: =HYPERLINK("\\avrasya\THY_BSK_TEKNIK\MD_TEKNIK_ANLASMALAR_VE_ODEMELER\Teknik Envanter Takip Şefliği\IPC\A321\" &D6&"\"& A6 & ".png", "Resim için basınız") -> Resim için basınız
A7: 1020420-3-121 | B7: CONTROL-ELECTRONIC ENGINE | D7: 73 | E7: ATE | F7: 37 | G7: 13753738 | I7: =HYPERLINK("\\avrasya\THY_BSK_TEKNIK\MD_TEKNIK_ANLASMALAR_VE_ODEMELER\Teknik Envanter Takip Şefliği\IPC\A321\" &D7&"\"& A7 & ".png", "Resim için basınız") -> Resim için basınız
A8: 636-2051-519 | B8: RH FAN COWL, ENG 1 | D8: 71 | E8: COMPOSIT | F8: 66 | G8: 13501348 | I8: =HYPERLINK("\\avrasya\THY_BSK_TEKNIK\MD_TEKNIK_ANLASMALAR_VE_ODEMELER\Teknik Envanter Takip Şefliği\IPC\A321\" &D8&"\"& A8 & ".png", "Resim için basınız") -> Resim için basınız
A9: 4500001C | B9: APS3200 | D9: 49 | E9: APU | F9: 86 | G9: 13169175 | I9: =HYPERLINK("\\avrasya\THY_BSK_TEKNIK\MD_TEKNIK_ANLASMALAR_VE_ODEMELER\Teknik Envanter Takip Şefliği\IPC\A321\" &D9&"\"& A9 & ".png", "Resim için basınız") -> Resim için basınız
A10: 1015200-6 | B10: INTEGRATED FUEL CONTROL&PUMP-MAIN | D10: 73 | E10: FUEL | F10: 141 | G10: 12975067 | I10: =HYPERLINK("\\avrasya\THY_BSK_TEKNIK\MD_TEKNIK_ANLASMALAR_VE_ODEMELER\Teknik Envanter Takip Şefliği\IPC\A321\" &D10&"\"& A10 & ".png", "Resim için basınız") -> Resim için basınız
A11: HG2030BE04 | B11: ADIRU | D11: 34 | E11: ATE | F11: 543 | G11: 11803404 | I11: =HYPERLINK("\\avrasya\THY_BSK_TEKNIK\MD_TEKNIK_ANLASMALAR_VE_ODEMELER\Teknik Envanter Takip Şefliği\IPC\A321\" &D11&"\"& A11 & ".png", "Resim için basınız") -> Resim için basınız
A12: HG2030BE03 | B12: ADIRU | D12: 34 | E12: ATE | F12: 125 | G12: 11561484 | I12: =HYPERLINK("\\avrasya\THY_BSK_TEKNIK\MD_TEKNIK_ANLASMALAR_VE_ODEMELER\Teknik Envanter Takip Şefliği\IPC\A321\" &D12&"\"& A12 & ".png", "Resim için basınız") -> Resim için basınız
A13: 9005000-11203 | B13: T3CAS COMPUTER | D13: 34 | E13: RADIO | F13: 21 | G13: 11447780 | I13: =HYPERLINK("\\avrasya\THY_BSK_TEKNIK\MD_TEKNIK_ANLASMALAR_VE_ODEMELER\Teknik Envanter Takip Şefliği\IPC\A321\" &D13&"\"& A13 & ".png", "Resim için basınız") -> Resim için basınız
... A18: 201522281 | B18: SLIDING TUBE SUBASSY | D18: 32 | E18: LDG | F18: 14 | G18: 8794246 | I18: =HYPERLINK("\\avrasya\THY_BSK_TEKNIK\MD_TEKNIK_ANLASMALAR_VE_ODEMELER\Teknik Envanter Takip Şefliği\IPC\A321\" &D18&"\"& A18 & ".png", "Resim için basınız") -> Resim için basınız
A19: 745-3000-515 | B19: INLET COWL | C19: TAHA | D19: 71 | E19: COMPOSIT | F19: 41 | G19: 8417130 | H19: Motorun ön kısmından gelen havayı düzgün şekilde içeri yönlendirerek motorun verimli çalışmasını sağlar ve Fan bölgesini dış etkilerden korur. | I19: =HYPERLINK("\\avrasya\THY_BSK_TEKNIK\MD_TEKNIK_ANLASMALAR_VE_ODEMELER\Teknik Envanter Takip Şefliği\IPC\A321\" &D19&"\"& A19 & ".png", "Resim için basınız") -> Resim için basınız | J19: Resim girildi
A20: RD-KA1003-05 | B20: FILE SERVER | C20: TAHA | D20: 23 | E20: IFE | F20: 39 | G20: 8160765.9 | H20: Dosyaların güvenli bir ortamda saklanmasını sağlayarak kullanıcıların dosyalara güvenli ve sağlıklı bir şekilde ulaşmalarını sağlar | I20: =HYPERLINK("\\avrasya\THY_BSK_TEKNIK\MD_TEKNIK_ANLASMALAR_VE_ODEMELER\Teknik Envanter Takip Şefliği\IPC\A321\" &D20&"\"& A20 & ".png", "Resim için basınız") -> Resim için basınız | J20: Resim girildi
A21: 745-3400-507 | B21: INLET COWL | D21: 71 | E21: COMPOSIT | F21: 143 | G21: 8073740.4 | I21: =HYPERLINK("\\avrasya\THY_BSK_TEKNIK\MD_TEKNIK_ANLASMALAR_VE_ODEMELER\Teknik Envanter Takip Şefliği\IPC\A321\" &D21&"\"& A21 & ".png", "Resim için basınız") -> Resim için basınız
A22: 636-1101-513 | B22: AIR INTAKE ASSY | D22: 71 | E22: COMPOSIT | F22: 36 | G22: 7536488.2 | I22: =HYPERLINK("\\avrasya\THY_BSK_TEKNIK\MD_TEKNIK_ANLASMALAR_VE_ODEMELER\Teknik Envanter Takip Şefliği\IPC\A321\" &D22&"\"& A22 & ".png", "Resim için basınız") -> Resim için basınız
A23: 5322862 | B23: ANGLE GEARBOX MODULE | D23: 72 | E23: ENGINE | F23: 158 | G23: 7363723.8 | I23: =HYPERLINK("\\avrasya\THY_BSK_TEKNIK\MD_TEKNIK_ANLASMALAR_VE_ODEMELER\Teknik Envanter Takip Şefliği\IPC\A321\" &D23&"\"& A23 & ".png", "Resim için basınız") -> Resim için basınız
A24: 5327092 | B24: STARTER-ENGINE,AIR | D24: 80 | E24: PNEUMATC | F24: 113 | G24: 6390849.1 | I24: =HYPERLINK("\\avrasya\THY_BSK_TEKNIK\MD_TEKNIK_ANLASMALAR_VE_ODEMELER\Teknik Envanter Takip Şefliği\IPC\A321\" &D24&"\"& A24 & ".png", "Resim için basınız") -> Resim için basınız
A25: 745-1101-507 | B25: COMMON NOZZLE ASSY (CNA) | D25: 78 | E25: COMPOSIT | F25: 143 | G25: 5782543.8 | I25: =HYPERLINK("\\avrasya\THY_BSK_TEKNIK\MD_TEKNIK_ANLASMALAR_VE_ODEMELER\Teknik Envanter Takip Şefliği\IPC\A321\" &D25&"\"& A25 & ".png", "Resim için basınız") -> Resim için basınız
A26: C12850BC03 | B26: FLIGHT CONTROL UNIT | D26: 22 | E26: ATE | F26: 10 | G26: 5598603 | I26: =HYPERLINK("\\avrasya\THY_BSK_TEKNIK\MD_TEKNIK_ANLASMALAR_VE_ODEMELER\Teknik Envanter Takip Şefliği\IPC\A321\" &D26&"\"& A26 & ".png", "Resim için basınız") -> Resim için basınız
A27: C19755BA01 | B27: ENHANCED LIQ.CRYS.DISP.UN | D27: 31 | E27: ATE | F27: 1088 | G27: 5483816 | I27: =HYPERLINK("\\avrasya\THY_BSK_TEKNIK\MD_TEKNIK_ANLASMALAR_VE_ODEMELER\Teknik Envanter Takip Şefliği\IPC\A321\" &D27&"\"& A27 & ".png", "Resim için basınız") -> Resim için basınız
A28: 201522267 | B28: SLIDING TUBE SUBASSEMBLY | D28: 32 | E28: LDG | F28: 92 | G28: 5388285.6 | I28: =HYPERLINK("\\avrasya\THY_BSK_TEKNIK\MD_TEKNIK_ANLASMALAR_VE_ODEMELER\Teknik Envanter Takip Şefliği\IPC\A321\" &D28&"\"& A28 & ".png", "Resim için basınız") -> Resim için basınız
A29: D2755605501300 | B29: FLAP TRACK N 4 CARRIAGE RH | D29: 27 | E29: STRCTURE | F29: 58 | G29: 5361060.4 | I29: =HYPERLINK("\\avrasya\THY_BSK_TEKNIK\MD_TEKNIK_ANLASMALAR_VE_ODEMELER\Teknik Envanter Takip Şefliği\IPC\A321\" &D29&"\"& A29 & ".png", "Resim için basınız") -> Resim için basınız
A30: C16291AB | B30: AOA SENSOR | C30: TAHA | D30: 34 | E30: INSTRMNT | F30: 738 | G30: 5359342.4 | H30: Angle Of Attack Sensor kanadın hava akışına göre açısını ölçerek stall riskini önlemek için uçuş kontrol sistemine veri sağlar | I30: =HYPERLINK("\\avrasya\THY_BSK_TEKNIK\MD_TEKNIK_ANLASMALAR_VE_ODEMELER\Teknik Envanter Takip Şefliği\IPC\A321\" &D30&"\"& A30 & ".png", "Resim için basınız") -> Resim için basınız | J30: Resim girildi
A31: 47145-247 | B31: THS ACTUATOR | D31: 27 | E31: MECHANIC | F31: 27 | G31: 5354604.3 | I31: =HYPERLINK("\\avrasya\THY_BSK_TEKNIK\MD_TEKNIK_ANLASMALAR_VE_ODEMELER\Teknik Envanter Takip Şefliği\IPC\A321\" &D31&"\"& A31 & ".png", "Resim için basınız") -> Resim için basınız
A32: 5323305 | B32: COOLER-AIR, #4 BEARING | D32: 75 | E32: MECHANIC | F32: 119 | G32: 5104343.2 | I32: =HYPERLINK("\\avrasya\THY_BSK_TEKNIK\MD_TEKNIK_ANLASMALAR_VE_ODEMELER\Teknik Envanter Takip Şefliği\IPC\A321\" &D32&"\"& A32 & ".png", "Resim için basınız") -> Resim için basınız
A33: BA03604 | B33: AC GENERATOR | D33: 24 | E33: IDG/GEN | F33: 46 | G33: 4965131.4 | I33: =HYPERLINK("\\avrasya\THY_BSK_TEKNIK\MD_TEKNIK_ANLASMALAR_VE_ODEMELER\Teknik Envanter Takip Şefliği\IPC\A321\" &D33&"\"& A33 & ".png", "Resim için basınız") -> Resim için basınız
A34: D5757390001051 | B34: LH INBOARD FLAP | D34: 27 | E34: COMPOSIT | F34: 1 | G34: 4937434.9 | I34: =HYPERLINK("\\avrasya\THY_BSK_TEKNIK\MD_TEKNIK_ANLASMALAR_VE_ODEMELER\Teknik Envanter Takip Şefliği\IPC\A321\" &D34&"\"& A34 & ".png", "Resim için basınız") -> Resim için basınız
A35: D5757390001151 | B35: RH INBOARD FLAP | D35: 27 | E35: COMPOSIT | F35: 1 | G35: 4937434.9 | I35: =HYPERLINK("\\avrasya\THY_BSK_TEKNIK\MD_TEKNIK_ANLASMALAR_VE_ODEMELER\Teknik Envanter Takip Şefliği\IPC\A321\" &D35&"\"& A35 & ".png", "Resim için basınız") -> Resim için basınız
A36: B372BAM0515 | B36: SPOILER ELEVATOR COMPUTER | D36: 27 | E36: ATE | F36: 127 | G36: 4874212 | I36: =HYPERLINK("\\avrasya\THY_BSK_TEKNIK\MD_TEKNIK_ANLASMALAR_VE_ODEMELER\Teknik Envanter Takip Şefliği\IPC\A321\" &D36&"\"& A36 & ".png", "Resim için basınız") -> Resim için basınız
A37: B372BBM0104 | B37: SPOILER ELEVATOR COMPUTER | D37: 27 | E37: ATE | F37: 84 | G37: 4874212 | I37: =HYPERLINK("\\avrasya\THY_BSK_TEKNIK\MD_TEKNIK_ANLASMALAR_VE_ODEMELER\Teknik Envanter Takip Şefliği\IPC\A321\" &D37&"\"& A37 & ".png", "Resim için basınız") -> Resim için basınız
A38: BA16501-01 | B38: APU GENERATOR | D38: 24 | E38: IDG/GEN | F38: 176 | G38: 4795170.4 | I38: =HYPERLINK("\\avrasya\THY_BSK_TEKNIK\MD_TEKNIK_ANLASMALAR_VE_ODEMELER\Teknik Envanter Takip Şefliği\IPC\A321\" &D38&"\"& A38 & ".png", "Resim için basınız") -> Resim için basınız
A39: 745-3400-503 | B39: INLET COWL | D39: 71 | E39: COMPOSIT | F39: 37 | G39: 4772940.9 | I39: =HYPERLINK("\\avrasya\THY_BSK_TEKNIK\MD_TEKNIK_ANLASMALAR_VE_ODEMELER\Teknik Envanter Takip Şefliği\IPC\A321\" &D39&"\"& A39 & ".png", "Resim için basınız") -> Resim için basınız
A40: 745-0006-501 | B40: SLEEVE ASSY. LH | D40: 78 | E40: COMPOSIT | F40: 215 | G40: 4757446 | I40: =HYPERLINK("\\avrasya\THY_BSK_TEKNIK\MD_TEKNIK_ANLASMALAR_VE_ODEMELER\Teknik Envanter Takip Şefliği\IPC\A321\" &D40&"\"& A40 & ".png", "Resim için basınız") -> Resim için basınız
A41: RWA11-0008-00 | B41: GLOBAL SATELLITE ANTENNA ASSEMBLY (GSAA) | D41: 44 | E41: IFE | F41: 111 | G41: 4708414.4 | I41: =HYPERLINK("\\avrasya\THY_BSK_TEKNIK\MD_TEKNIK_ANLASMALAR_VE_ODEMELER\Teknik Envanter Takip Şefliği\IPC\A321\" &D41&"\"& A41 & ".png", "Resim için basınız") -> Resim için basınız
A42: Z014H010035C | B42: CIDS DIRECTOR | D42: 23 | E42: IFE | F42: 52 | G42: 4661174 | I42: =HYPERLINK("\\avrasya\THY_BSK_TEKNIK\MD_TEKNIK_ANLASMALAR_VE_ODEMELER\Teknik Envanter Takip Şefliği\IPC\A321\" &D42&"\"& A42 & ".png", "Resim için basınız") -> Resim için basınız
... A3060: 177778-901 | B3060: IN ARMREST VDU | D3060: 23 | E3060: IFE | F3060: 14 | G3060: 0 | I3060: =HYPERLINK("\\avrasya\THY_BSK_TEKNIK\MD_TEKNIK_ANLASMALAR_VE_ODEMELER\Teknik Envanter Takip Şefliği\IPC\A321\" &D3060&"\"& A3060 & ".png", "Resim için basınız") -> Resim için basınız
A3061: 201660002-025 | B3061: MLG SIDESTAY ASSY-R/H | C3061: ENİS | D3061: 32 | E3061: LDG | F3061: 15 | G3061: 0 | I3061: =HYPERLINK("\\avrasya\THY_BSK_TEKNIK\MD_TEKNIK_ANLASMALAR_VE_ODEMELER\Teknik Envanter Takip Şefliği\IPC\A321\" &D3061&"\"& A3061 & ".png", "Resim için basınız") -> Resim için basınız | J3061: resim girildi
A3062: D23589520-14 | B3062: NLG LEG | D3062: 32 | E3062: LDG | F3062: 2 | G3062: 0 | I3062: =HYPERLINK("\\avrasya\THY_BSK_TEKNIK\MD_TEKNIK_ANLASMALAR_VE_ODEMELER\Teknik Envanter Takip Şefliği\IPC\A321\" &D3062&"\"& A3062 & ".png", "Resim için basınız") -> Resim için basınız
A3063: D65628-1 | B3063: CROSS PIN | D3063: 32 | E3063: LDG | F3063: 4 | G3063: 0 | I3063: =HYPERLINK("\\avrasya\THY_BSK_TEKNIK\MD_TEKNIK_ANLASMALAR_VE_ODEMELER\Teknik Envanter Takip Şefliği\IPC\A321\" &D3063&"\"& A3063 & ".png", "Resim için basınız") -> Resim için basınız
A3064: D57259192000 | B3064: LH MLG FWD PINTLE FITTING ASSY | D3064: 57 | E3064: STRCTURE | F3064: 24 | G3064: 0 | I3064: =HYPERLINK("\\avrasya\THY_BSK_TEKNIK\MD_TEKNIK_ANLASMALAR_VE_ODEMELER\Teknik Envanter Takip Şefliği\IPC\A321\" &D3064&"\"& A3064 & ".png", "Resim için basınız") -> Resim için basınız
A3065: D57259192002A | B3065: LH MLG FWD PINTLE FITTING | D3065: 57 | E3065: STRCTURE | F3065: 17 | G3065: 0 | I3065: =HYPERLINK("\\avrasya\THY_BSK_TEKNIK\MD_TEKNIK_ANLASMALAR_VE_ODEMELER\Teknik Envanter Takip Şefliği\IPC\A321\" &D3065&"\"& A3065 & ".png", "Resim için basınız") -> Resim için basınız
A3066: D57259192001 | B3066: RH MLG FWD PINTLE FITTING ASSY | D3066: 57 | E3066: STRCTURE | F3066: 25 | G3066: 0 | I3066: =HYPERLINK("\\avrasya\THY_BSK_TEKNIK\MD_TEKNIK_ANLASMALAR_VE_ODEMELER\Teknik Envanter Takip Şefliği\IPC\A321\" &D3066&"\"& A3066 & ".png", "Resim için basınız") -> Resim için basınız
A3067: D57259192003A | B3067: RH MLG FWD PINTLE FITTING | D3067: 57 | E3067: STRCTURE | F3067: 18 | G3067: 0 | I3067: =HYPERLINK("\\avrasya\THY_BSK_TEKNIK\MD_TEKNIK_ANLASMALAR_VE_ODEMELER\Teknik Envanter Takip Şefliği\IPC\A321\" &D3067&"\"& A3067 & ".png", "Resim için basınız") -> Resim için basınız
A3068: D57255530000 | B3068: LH MLG SIDESTAY FITTING ASSY | D3068: 57 | E3068: STRCTURE | F3068: 17 | G3068: 0 | I3068: =HYPERLINK("\\avrasya\THY_BSK_TEKNIK\MD_TEKNIK_ANLASMALAR_VE_ODEMELER\Teknik Envanter Takip Şefliği\IPC\A321\" &D3068&"\"& A3068 & ".png", "Resim için basınız") -> Resim için basınız
A3069: D57259172004 | B3069: LH MLG SIDESTAY FITTING | D3069: 57 | E3069: STRCTURE | F3069: 17 | G3069: 0 | I3069: =HYPERLINK("\\avrasya\THY_BSK_TEKNIK\MD_TEKNIK_ANLASMALAR_VE_ODEMELER\Teknik Envanter Takip Şefliği\IPC\A321\" &D3069&"\"& A3069 & ".png", "Resim için basınız") -> Resim için basınız
A3070: D57255530001 | B3070: RH MLG SIDESTAY FITTING ASSY | D3070: 57 | E3070: STRCTURE | F3070: 17 | G3070: 0 | I3070: =HYPERLINK("\\avrasya\THY_BSK_TEKNIK\MD_TEKNIK_ANLASMALAR_VE_ODEMELER\Teknik Envanter Takip Şefliği\IPC\A321\" &D3070&"\"& A3070 & ".png", "Resim için basınız") -> Resim için basınız
A3071: D57259172005 | B3071: RH MLG SIDESTAY FITTING | D3071: 57 | E3071: STRCTURE | F3071: 17 | G3071: 0 | I3071: =HYPERLINK("\\avrasya\THY_BSK_TEKNIK\MD_TEKNIK_ANLASMALAR_VE_ODEMELER\Teknik Envanter Takip Şefliği\IPC\A321\" &D3071&"\"& A3071 & ".png", "Resim için basınız") -> Resim için basınız
A3072: D9255003200400 | B3072: REFEUEL/DEFUEL PANEL | D3072: 28 | E3072: INSTRMNT | F3072: 5 | G3072: 0 | I3072: =HYPERLINK("\\avrasya\THY_BSK_TEKNIK\MD_TEKNIK_ANLASMALAR_VE_ODEMELER\Teknik Envanter Takip Şefliği\IPC\A321\" &D3072&"\"& A3072 & ".png", "Resim için basınız") -> Resim için basınız
A3073: SLN41194 | B3073: REAR PINTLE PIN NUT | D3073: 32 | E3073: LDG | F3073: 295 | G3073: 0 | I3073: =HYPERLINK("\\avrasya\THY_BSK_TEKNIK\MD_TEKNIK_ANLASMALAR_VE_ODEMELER\Teknik Envanter Takip Şefliği\IPC\A321\" &D3073&"\"& A3073 & ".png", "Resim için basınız") -> Resim için basınız
... A3098: H3841-14 | B3098: LATCH ASSY-ARM/DISARM RH | D3098: 52 | E3098: MECHANIC | F3098: 1 | G3098: 0 | I3098: =HYPERLINK("\\avrasya\THY_BSK_TEKNIK\MD_TEKNIK_ANLASMALAR_VE_ODEMELER\Teknik Envanter Takip Şefliği\IPC\A321\" &D3098&"\"& A3098 & ".png", "Resim için basınız") -> Resim için basınız
A3099: 201660001-025 | B3099: MLG SIDESTAY ASSY-L/H | C3099: ENİS | D3099: 32 | E3099: LDG | F3099: 15 | G3099: 0 | I3099: =HYPERLINK("\\avrasya\THY_BSK_TEKNIK\MD_TEKNIK_ANLASMALAR_VE_ODEMELER\Teknik Envanter Takip Şefliği\IPC\A321\" &D3099&"\"& A3099 & ".png", "Resim için basınız") -> Resim için basınız | J3099: resim girildi
A3100: C12850BC02 | B3100: FLIGHT CONTROL UNIT | D3100: 22 | E3100: ATE | F3100: 3 | G3100: 0 | I3100: =HYPERLINK("\\avrasya\THY_BSK_TEKNIK\MD_TEKNIK_ANLASMALAR_VE_ODEMELER\Teknik Envanter Takip Şefliği\IPC\A321\" &D3100&"\"& A3100 & ".png", "Resim için basınız") -> Resim için basınız
A3101: A35778 | B3101: AXLE SLEEVE | D3101: 32 | E3101: LDG | F3101: 36 | G3101: 0 | I3101: =HYPERLINK("\\avrasya\THY_BSK_TEKNIK\MD_TEKNIK_ANLASMALAR_VE_ODEMELER\Teknik Envanter Takip Şefliği\IPC\A321\" &D3101&"\"& A3101 & ".png", "Resim için basınız") -> Resim için basınız
A3102: 201585003-030 | B3102: MLG UNIT (LEG&DRESS.)-L/H | D3102: 32 | E3102: LDG | F3102: 8 | G3102: 0 | I3102: =HYPERLINK("\\avrasya\THY_BSK_TEKNIK\MD_TEKNIK_ANLASMALAR_VE_ODEMELER\Teknik Envanter Takip Şefliği\IPC\A321\" &D3102&"\"& A3102 & ".png", "Resim için basınız") -> Resim için basınız
A3103: D5757305006400 | B3103: LH INBOARD FLAP | D3103: 27 | E3103: COMPOSIT | F3103: 37 | G3103: 0 | I3103: =HYPERLINK("\\avrasya\THY_BSK_TEKNIK\MD_TEKNIK_ANLASMALAR_VE_ODEMELER\Teknik Envanter Takip Şefliği\IPC\A321\" &D3103&"\"& A3103 & ".png", "Resim için basınız") -> Resim için basınız
A3104: 745-5967-517 | B3104: CORE SERV. HARNESS ASSY | D3104: 71 | E3104: ENGINE | F3104: 19 | G3104: 0 | I3104: =HYPERLINK("\\avrasya\THY_BSK_TEKNIK\MD_TEKNIK_ANLASMALAR_VE_ODEMELER\Teknik Envanter Takip Şefliği\IPC\A321\" &D3104&"\"& A3104 & ".png", "Resim için basınız") -> Resim için basınız
A3105: 114079016 | B3105: LG DOOR SELECTOR VALVE | D3105: 32 | E3105: HYDRAUL | F3105: 1 | G3105: 0 | I3105: =HYPERLINK("\\avrasya\THY_BSK_TEKNIK\MD_TEKNIK_ANLASMALAR_VE_ODEMELER\Teknik Envanter Takip Şefliği\IPC\A321\" &D3105&"\"& A3105 & ".png", "Resim için basınız") -> Resim için basınız
A3106: 114079017 | B3106: LG SELECTOR VALVE | D3106: 32 | E3106: HYDRAUL | F3106: 1 | G3106: 0 | I3106: =HYPERLINK("\\avrasya\THY_BSK_TEKNIK\MD_TEKNIK_ANLASMALAR_VE_ODEMELER\Teknik Envanter Takip Şefliği\IPC\A321\" &D3106&"\"& A3106 & ".png", "Resim için basınız") -> Resim için basınız
A3107: D5758620011700 | B3107: RH OUTBOARD FLAP TAB | D3107: 57 | E3107: COMPOSIT | F3107: 1 | G3107: 0 | I3107: =HYPERLINK("\\avrasya\THY_BSK_TEKNIK\MD_TEKNIK_ANLASMALAR_VE_ODEMELER\Teknik Envanter Takip Şefliği\IPC\A321\" &D3107&"\"& A3107 & ".png", "Resim için basınız") -> Resim için basınız
A3108: 326373 | B3108: CHECK VALVE | D3108: 29 | E3108: HYDRAUL | F3108: 2 | G3108: 0 | I3108: =HYPERLINK("\\avrasya\THY_BSK_TEKNIK\MD_TEKNIK_ANLASMALAR_VE_ODEMELER\Teknik Envanter Takip Şefliği\IPC\A321\" &D3108&"\"& A3108 & ".png", "Resim için basınız") -> Resim için basınız
A3109: 201587207 | B3109: FW.PINT.PIN STUBBOLT ASSY | D3109: 32 | E3109: LDG | F3109: 15 | G3109: 0 | I3109: =HYPERLINK("\\avrasya\THY_BSK_TEKNIK\MD_TEKNIK_ANLASMALAR_VE_ODEMELER\Teknik Envanter Takip Şefliği\IPC\A321\" &D3109&"\"& A3109 & ".png", "Resim için basınız") -> Resim için basınız
A3110: 55-4537018-00 | B3110: SIDE STAY PIVOT PIN | D3110: 32 | E3110: LDG | F3110: 189 | G3110: 0 | I3110: =HYPERLINK("\\avrasya\THY_BSK_TEKNIK\MD_TEKNIK_ANLASMALAR_VE_ODEMELER\Teknik Envanter Takip Şefliği\IPC\A321\" &D3110&"\"& A3110 & ".png", "Resim için basınız") -> Resim için basınız
A3111: 55-4537009-00 | B3111: SIDESTAY UPPER CARDAN PIN | D3111: 32 | E3111: LDG | F3111: 189 | G3111: 0 | I3111: =HYPERLINK("\\avrasya\THY_BSK_TEKNIK\MD_TEKNIK_ANLASMALAR_VE_ODEMELER\Teknik Envanter Takip Şefliği\IPC\A321\" &D3111&"\"& A3111 & ".png", "Resim için basınız") -> Resim için basınız
... A3607: 50-3757007-00 | B3607: UNIVERSAL JOINT | D3607: 32 | E3607: LDG | F3607: 64 | G3607: 0 | I3607: =HYPERLINK("\\avrasya\THY_BSK_TEKNIK\MD_TEKNIK_ANLASMALAR_VE_ODEMELER\Teknik Envanter Takip Şefliği\IPC\A321\" &D3607&"\"& A3607 & ".png", "Resim için basınız") -> Resim için basınız
A3608: 10-375902-000 | B3608: NLG LEG ASSY | C3608: ENİS | D3608: 32 | E3608: LDG | F3608: 21 | G3608: 0 | I3608: =HYPERLINK("\\avrasya\THY_BSK_TEKNIK\MD_TEKNIK_ANLASMALAR_VE_ODEMELER\Teknik Envanter Takip Şefliği\IPC\A321\" &D3608&"\"& A3608 & ".png", "Resim için basınız") -> Resim için basınız | J3608: Resim girildi
A3609: 10-375002-000 | B3609: LEG STRUCTURE | C3609: ENİS | D3609: 32 | E3609: LDG | F3609: 55 | G3609: 0 | I3609: =HYPERLINK("\\avrasya\THY_BSK_TEKNIK\MD_TEKNIK_ANLASMALAR_VE_ODEMELER\Teknik Envanter Takip Şefliği\IPC\A321\" &D3609&"\"& A3609 & ".png", "Resim için basınız") -> Resim için basınız | J3609: Resim girildi
A3610: D5757380001400W | B3610: LH INBOARD FLAP TAB | D3610: 27 | E3610: COMPOSIT | F3610: 1 | G3610: 0 | I3610: =HYPERLINK("\\avrasya\THY_BSK_TEKNIK\MD_TEKNIK_ANLASMALAR_VE_ODEMELER\Teknik Envanter Takip Şefliği\IPC\A321\" &D3610&"\"& A3610 & ".png", "Resim için basınız") -> Resim için basınız
A3611: 4W6515 | B3611: HP COMPRESSOR ASSY | D3611: 72 | E3611: ENGINE | F3611: 1 | G3611: 0 | I3611: =HYPERLINK("\\avrasya\THY_BSK_TEKNIK\MD_TEKNIK_ANLASMALAR_VE_ODEMELER\Teknik Envanter Takip Şefliği\IPC\A321\" &D3611&"\"& A3611 & ".png", "Resim için basınız") -> Resim için basınız
A3612: D5312000800900 | B3612: WINDOW ASSY SLIDING - RH | D3612: 56 | E3612: MECHANIC | F3612: 1 | G3612: 0 | I3612: =HYPERLINK("\\avrasya\THY_BSK_TEKNIK\MD_TEKNIK_ANLASMALAR_VE_ODEMELER\Teknik Envanter Takip Şefliği\IPC\A321\" &D3612&"\"& A3612 & ".png", "Resim için basınız") -> Resim için basınız
A3613: D5765000000838A | B3613: AILERON - LH | C3613: ENİS | D3613: 57 | E3613: COMPOSIT | F3613: 42 | G3613: 0 | I3613: =HYPERLINK("\\avrasya\THY_BSK_TEKNIK\MD_TEKNIK_ANLASMALAR_VE_ODEMELER\Teknik Envanter Takip Şefliği\IPC\A321\" &D3613&"\"& A3613 & ".png", "Resim için basınız") -> Resim için basınız | J3613: Resim girildi
A3614: 5W0155 | B3614: LPC INTERMEDIATE MM | D3614: 72 | E3614: ENGINE | F3614: 5 | G3614: 0 | I3614: =HYPERLINK("\\avrasya\THY_BSK_TEKNIK\MD_TEKNIK_ANLASMALAR_VE_ODEMELER\Teknik Envanter Takip Şefliği\IPC\A321\" &D3614&"\"& A3614 & ".png", "Resim için basınız") -> Resim için basınız
A3615: 43-1-1100 | B3615: APU ACTUATOR-AIR INTAKE | D3615: 49 | E3615: ELECTMEC | F3615: 1 | G3615: 0 | I3615: =HYPERLINK("\\avrasya\THY_BSK_TEKNIK\MD_TEKNIK_ANLASMALAR_VE_ODEMELER\Teknik Envanter Takip Şefliği\IPC\A321\" &D3615&"\"& A3615 & ".png", "Resim için basınız") -> Resim için basınız
A3616: 745M0007-507 | B3616: R/H NAC. L/H T/R | D3616: 78 | E3616: COMPOSIT | F3616: 1 | G3616: 0 | I3616: =HYPERLINK("\\avrasya\THY_BSK_TEKNIK\MD_TEKNIK_ANLASMALAR_VE_ODEMELER\Teknik Envanter Takip Şefliği\IPC\A321\" &D3616&"\"& A3616 & ".png", "Resim için basınız") -> Resim için basınız
A3617: 01R757259A | B3617: HOUSING SET, GEARBOX-MATCHED | D3617: 49 | E3617: APU | F3617: 2 | G3617: 0 | I3617: =HYPERLINK("\\avrasya\THY_BSK_TEKNIK\MD_TEKNIK_ANLASMALAR_VE_ODEMELER\Teknik Envanter Takip Şefliği\IPC\A321\" &D3617&"\"& A3617 & ".png", "Resim için basınız") -> Resim için basınız
A3618: H3841-13 | B3618: LATCH ASSY-ARM/DISARM LH | D3618: 52 | E3618: MECHANIC | F3618: 1 | G3618: 0 | I3618: =HYPERLINK("\\avrasya\THY_BSK_TEKNIK\MD_TEKNIK_ANLASMALAR_VE_ODEMELER\Teknik Envanter Takip Şefliği\IPC\A321\" &D3618&"\"& A3618 & ".png", "Resim için basınız") -> Resim için basınız
A3619: 2A3344-004 | B3619: INNER COMBUSTION CHAMBER | D3619: 72 | E3619: ENGINE | F3619: 2 | G3619: 0 | I3619: =HYPERLINK("\\avrasya\THY_BSK_TEKNIK\MD_TEKNIK_ANLASMALAR_VE_ODEMELER\Teknik Envanter Takip Şefliği\IPC\A321\" &D3619&"\"& A3619 & ".png", "Resim için basınız") -> Resim için basınız
A3620: 2040081-101 | B3620: OXYGEN SENSOR | D3620: 47 | E3620: INSTRMNT | F3620: 2 | G3620: 0 | I3620: =HYPERLINK("\\avrasya\THY_BSK_TEKNIK\MD_TEKNIK_ANLASMALAR_VE_ODEMELER\Teknik Envanter Takip Şefliği\IPC\A321\" &D3620&"\"& A3620 & ".png", "Resim için basınız") -> Resim için basınız
A3621: 473873-8 | B3621: CORE FIRE DETECTOR ASSY | D3621: 26 | E3621: INSTRMNT | F3621: 1 | G3621: 0 | I3621: =HYPERLINK("\\avrasya\THY_BSK_TEKNIK\MD_TEKNIK_ANLASMALAR_VE_ODEMELER\Teknik Envanter Takip Şefliği\IPC\A321\" &D3621&"\"& A3621 & ".png", "Resim için basınız") -> Resim için basınız
A3622: 14402-001 | B3622: DRAIN VALVE | D3622: 38 | E3622: SANITARY | F3622: 2 | G3622: 0 | I3622: =HYPERLINK("\\avrasya\THY_BSK_TEKNIK\MD_TEKNIK_ANLASMALAR_VE_ODEMELER\Teknik Envanter Takip Şefliği\IPC\A321\" &D3622&"\"& A3622 & ".png", "Resim için basınız") -> Resim için basınız
A3623: D5312000800300 | B3623: WINDOW ASSY SLIDING - RH | D3623: 56 | E3623: MECHANIC | F3623: 2 | G3623: 0 | I3623: =HYPERLINK("\\avrasya\THY_BSK_TEKNIK\MD_TEKNIK_ANLASMALAR_VE_ODEMELER\Teknik Envanter Takip Şefliği\IPC\A321\" &D3623&"\"& A3623 & ".png", "Resim için basınız") -> Resim için basınız
A3624: D5312000800200 | B3624: WINDOW ASSY SLIDING - LH | D3624: 56 | E3624: MECHANIC | F3624: 1 | G3624: 0 | I3624: =HYPERLINK("\\avrasya\THY_BSK_TEKNIK\MD_TEKNIK_ANLASMALAR_VE_ODEMELER\Teknik Envanter Takip Şefliği\IPC\A321\" &D3624&"\"& A3624 & ".png", "Resim için basınız") -> Resim için basınız
A3625: D5758550102100 | B3625: OUTER FLAP RH | D3625: 27 | E3625: COMPOSIT | F3625: 5 | G3625: 0 | I3625: =HYPERLINK("\\avrasya\THY_BSK_TEKNIK\MD_TEKNIK_ANLASMALAR_VE_ODEMELER\Teknik Envanter Takip Şefliği\IPC\A321\" &D3625&"\"& A3625 & ".png", "Resim için basınız") -> Resim için basınız
... A4830: 2A3106CL01 | B4830: DATA ENTRY PLUG | D4830: 75 | E4830: ELECTRIC | F4830: 2 | G4830: 0 | I4830: =HYPERLINK("\\avrasya\THY_BSK_TEKNIK\MD_TEKNIK_ANLASMALAR_VE_ODEMELER\Teknik Envanter Takip Şefliği\IPC\A321\" &D4830&"\"& A4830 & ".png", "Resim için basınız") -> Resim için basınız

Sheet A330
A1: PN | B1: PN DESC | C1: ilgili | D1: CHAPTER | E1: SUB CATEGORY | F1: QTY | G1: FA AMOUNT | H1: Fonksiyonu | I1: Görsel | J1: Resim Notu
A2: F5777210000600 | B2: 1 SPOILER LH | D2: 27 | E2: COMPOSIT | F2: 46 | G2: 0 | I2: =HYPERLINK("\\avrasya\THY_BSK_TEKNIK\MD_TEKNIK_ANLASMALAR_VE_ODEMELER\Teknik Envanter Takip Şefliği\IPC\A330\" &D2&"\"& A2 & ".png", "Resim için basınız") -> Resim için basınız
A3: F5777210000700 | B3: 1 SPOILER RH | D3: 27 | E3: COMPOSIT | F3: 46 | G3: 0 | I3: =HYPERLINK("\\avrasya\THY_BSK_TEKNIK\MD_TEKNIK_ANLASMALAR_VE_ODEMELER\Teknik Envanter Takip Şefliği\IPC\A330\" &D3&"\"& A3 & ".png", "Resim için basınız") -> Resim için basınız
A4: F5777100002900 | B4: 1 SPOILER RH | D4: 27 | E4: COMPOSIT | F4: 3 | G4: 18533.25 | I4: =HYPERLINK("\\avrasya\THY_BSK_TEKNIK\MD_TEKNIK_ANLASMALAR_VE_ODEMELER\Teknik Envanter Takip Şefliği\IPC\A330\" &D4&"\"& A4 & ".png", "Resim için basınız") -> Resim için basınız
A5: D23446200 | B5: LOOM, UPPER ELECTRICAL 1M | D5: 32 | E5: HARNESS | F5: 2 | G5: 0 | I5: =HYPERLINK("\\avrasya\THY_BSK_TEKNIK\MD_TEKNIK_ANLASMALAR_VE_ODEMELER\Teknik Envanter Takip Şefliği\IPC\A330\" &D5&"\"& A5 & ".png", "Resim için basınız") -> Resim için basınız
A6: F5777100103600 | B6: 2 SPOILER LH | D6: 27 | E6: COMPOSIT | F6: 3 | G6: 0 | I6: =HYPERLINK("\\avrasya\THY_BSK_TEKNIK\MD_TEKNIK_ANLASMALAR_VE_ODEMELER\Teknik Envanter Takip Şefliği\IPC\A330\" &D6&"\"& A6 & ".png", "Resim için basınız") -> Resim için basınız
A7: F5777220000600 | B7: 2 SPOILER LH | D7: 27 | E7: COMPOSIT | F7: 46 | G7: 0 | I7: =HYPERLINK("\\avrasya\THY_BSK_TEKNIK\MD_TEKNIK_ANLASMALAR_VE_ODEMELER\Teknik Envanter Takip Şefliği\IPC\A330\" &D7&"\"& A7 & ".png", "Resim için basınız") -> Resim için basınız
A8: F5777100103700 | B8: 2 SPOILER RH | D8: 27 | E8: COMPOSIT | F8: 4 | G8: 18667.5 | I8: =HYPERLINK("\\avrasya\THY_BSK_TEKNIK\MD_TEKNIK_ANLASMALAR_VE_ODEMELER\Teknik Envanter Takip Şefliği\IPC\A330\" &D8&"\"& A8 & ".png", "Resim için basınız") -> Resim için basınız
A9: F5777220000700 | B9: 2 SPOILER RH | D9: 27 | E9: COMPOSIT | F9: 46 | G9: 0 | I9: =HYPERLINK("\\avrasya\THY_BSK_TEKNIK\MD_TEKNIK_ANLASMALAR_VE_ODEMELER\Teknik Envanter Takip Şefliği\IPC\A330\" &D9&"\"& A9 & ".png", "Resim için basınız") -> Resim için basınız
A10: 86053-10 | B10: 2" WIDE CARGO LOCK ASSY | D10: 25 | E10: MECHANIC | F10: 17 | G10: 2274.47 | I10: =HYPERLINK("\\avrasya\THY_BSK_TEKNIK\MD_TEKNIK_ANLASMALAR_VE_ODEMELER\Teknik Envanter Takip Şefliği\IPC\A330\" &D10&"\"& A10 & ".png", "Resim için basınız") -> Resim için basınız
A11: 86053-11 | B11: 2" WIDE CARGO LOCK ASSY | D11: 25 | E11: MECHANIC | F11: 19 | G11: 75860 | I11: =HYPERLINK("\\avrasya\THY_BSK_TEKNIK\MD_TEKNIK_ANLASMALAR_VE_ODEMELER\Teknik Envanter Takip Şefliği\IPC\A330\" &D11&"\"& A11 & ".png", "Resim için basınız") -> Resim için basınız
A12: G5777230001200 | B12: 3 SPOILER LH | D12: 27 | E12: COMPOSIT | F12: 28 | G12: 0 | I12: =HYPERLINK("\\avrasya\THY_BSK_TEKNIK\MD_TEKNIK_ANLASMALAR_VE_ODEMELER\Teknik Envanter Takip Şefliği\IPC\A330\" &D12&"\"& A12 & ".png", "Resim için basınız") -> Resim için basınız
A13: F5777000001000 | B13: 3 SPOILER LH | D13: 27 | E13: COMPOSIT | F13: 3 | G13: 18533.25 | I13: =HYPERLINK("\\avrasya\THY_BSK_TEKNIK\MD_TEKNIK_ANLASMALAR_VE_ODEMELER\Teknik Envanter Takip Şefliği\IPC\A330\" &D13&"\"& A13 & ".png", "Resim için basınız") -> Resim için basınız
... A24: G5777240001100 | B24: 4 SPOILER RH | D24: 27 | E24: COMPOSIT | F24: 17 | G24: 0 | I24: =HYPERLINK("\\avrasya\THY_BSK_TEKNIK\MD_TEKNIK_ANLASMALAR_VE_ODEMELER\Teknik Envanter Takip Şefliği\IPC\A330\" &D24&"\"& A24 & ".png", "Resim için basınız") -> Resim için basınız
A25: RD-AA8110-02 | B25: 4G CELL MODEM | C25: TAHA | D25: 23 | E25: IFE | F25: 21 | G25: 106722.11 | H25: 4G mobil şebeke üzerinden veri iletişimi sağlayarak sistemin internet ile gerçek zamanlı bağlantı kurmasını sağlar | I25: =HYPERLINK("\\avrasya\THY_BSK_TEKNIK\MD_TEKNIK_ANLASMALAR_VE_ODEMELER\Teknik Envanter Takip Şefliği\IPC\A330\" &D25&"\"& A25 & ".png", "Resim için basınız") -> Resim için basınız | J25: Resim Girildi
A26: RD-AA8190-01 | B26: 4G ENHANCED CELL MODEM (4G ECM) | D26: 23 | E26: IFE | F26: 247 | G26: 898253.44 | I26: =HYPERLINK("\\avrasya\THY_BSK_TEKNIK\MD_TEKNIK_ANLASMALAR_VE_ODEMELER\Teknik Envanter Takip Şefliği\IPC\A330\" &D26&"\"& A26 & ".png", "Resim için basınız") -> Resim için basınız
A27: G5777250001200 | B27: 5 SPOILER LH | D27: 27 | E27: COMPOSIT | F27: 29 | G27: 0 | I27: =HYPERLINK("\\avrasya\THY_BSK_TEKNIK\MD_TEKNIK_ANLASMALAR_VE_ODEMELER\Teknik Envanter Takip Şefliği\IPC\A330\" &D27&"\"& A27 & ".png", "Resim için basınız") -> Resim için basınız
A28: F5777000201000 | B28: 5 SPOILER LH | D28: 27 | E28: COMPOSIT | F28: 3 | G28: 18533.25 | I28: =HYPERLINK("\\avrasya\THY_BSK_TEKNIK\MD_TEKNIK_ANLASMALAR_VE_ODEMELER\Teknik Envanter Takip Şefliği\IPC\A330\" &D28&"\"& A28 & ".png", "Resim için basınız") -> Resim için basınız
A29: G5777250001000 | B29: 5 SPOILER LH | D29: 27 | E29: COMPOSIT | F29: 17 | G29: 0 | I29: =HYPERLINK("\\avrasya\THY_BSK_TEKNIK\MD_TEKNIK_ANLASMALAR_VE_ODEMELER\Teknik Envanter Takip Şefliği\IPC\A330\" &D29&"\"& A29 & ".png", "Resim için basınız") -> Resim için basınız
A30: F5777000201100 | B30: 5 SPOILER RH | D30: 27 | E30: COMPOSIT | F30: 3 | G30: 18533.25 | I30: =HYPERLINK("\\avrasya\THY_BSK_TEKNIK\MD_TEKNIK_ANLASMALAR_VE_ODEMELER\Teknik Envanter Takip Şefliği\IPC\A330\" &D30&"\"& A30 & ".png", "Resim için basınız") -> Resim için basınız
A31: G5777250001100 | B31: 5 SPOILER RH | D31: 27 | E31: COMPOSIT | F31: 17 | G31: 0 | I31: =HYPERLINK("\\avrasya\THY_BSK_TEKNIK\MD_TEKNIK_ANLASMALAR_VE_ODEMELER\Teknik Envanter Takip Şefliği\IPC\A330\" &D31&"\"& A31 & ".png", "Resim için basınız") -> Resim için basınız
A32: F5777100203600 | B32: 6 SPOILER LH | D32: 27 | E32: COMPOSIT | F32: 3 | G32: 18533.25 | I32: =HYPERLINK("\\avrasya\THY_BSK_TEKNIK\MD_TEKNIK_ANLASMALAR_VE_ODEMELER\Teknik Envanter Takip Şefliği\IPC\A330\" &D32&"\"& A32 & ".png", "Resim için basınız") -> Resim için basınız
A33: F5777260000600 | B33: 6 SPOILER LH | D33: 27 | E33: COMPOSIT | F33: 45 | G33: 0 | I33: =HYPERLINK("\\avrasya\THY_BSK_TEKNIK\MD_TEKNIK_ANLASMALAR_VE_ODEMELER\Teknik Envanter Takip Şefliği\IPC\A330\" &D33&"\"& A33 & ".png", "Resim için basınız") -> Resim için basınız
A34: F5777260000700 | B34: 6 SPOILER RH | D34: 27 | E34: COMPOSIT | F34: 46 | G34: 0 | I34: =HYPERLINK("\\avrasya\THY_BSK_TEKNIK\MD_TEKNIK_ANLASMALAR_VE_ODEMELER\Teknik Envanter Takip Şefliği\IPC\A330\" &D34&"\"& A34 & ".png", "Resim için basınız") -> Resim için basınız
A35: F5777100203700 | B35: 6 SPOILER RH | D35: 27 | E35: COMPOSIT | F35: 3 | G35: 18533.25 | I35: =HYPERLINK("\\avrasya\THY_BSK_TEKNIK\MD_TEKNIK_ANLASMALAR_VE_ODEMELER\Teknik Envanter Takip Şefliği\IPC\A330\" &D35&"\"& A35 & ".png", "Resim için basınız") -> Resim için basınız
A36: 180770-201T1 | B36: 8.9" IN-ARM SVDU | D36: 23 | E36: IFE | F36: 5 | G36: 77042.31 | I36: =HYPERLINK("\\avrasya\THY_BSK_TEKNIK\MD_TEKNIK_ANLASMALAR_VE_ODEMELER\Teknik Envanter Takip Şefliği\IPC\A330\" &D36&"\"& A36 & ".png", "Resim için basınız") -> Resim için basınız
A37: 180771-201T1 | B37: 8.9" SEATBACK SVDU | D37: 23 | E37: IFE | F37: 13 | G37: 67453.69 | I37: =HYPERLINK("\\avrasya\THY_BSK_TEKNIK\MD_TEKNIK_ANLASMALAR_VE_ODEMELER\Teknik Envanter Takip Şefliği\IPC\A330\" &D37&"\"& A37 & ".png", "Resim için basınız") -> Resim için basınız
... A1023: 70N106-801 | B1023: ENGINE INLET COWL | D1023: 71 | E1023: COMPOSIT | F1023: 19 | G1023: 1506120 | I1023: =HYPERLINK("\\avrasya\THY_BSK_TEKNIK\MD_TEKNIK_ANLASMALAR_VE_ODEMELER\Teknik Envanter Takip Şefliği\IPC\A330\" &D1023&"\"& A1023 & ".png", "Resim için basınız") -> Resim için basınız
A1024: 4295121 | B1024: ENGINE SCAN LIGHT | C1024: TAHA | D1024: 33 | E1024: ELECTRIC | F1024: 1 | G1024: 3889.8 | H1024: Motorla ilgili belirli bilgileri tarayan veya gösterge değişimlerini işaret eden uyarı ışığıdır. | I1024: =HYPERLINK("\\avrasya\THY_BSK_TEKNIK\MD_TEKNIK_ANLASMALAR_VE_ODEMELER\Teknik Envanter Takip Şefliği\IPC\A330\" &D1024&"\"& A1024 & ".png", "Resim için basınız") -> Resim için basınız | J1024: Resim Girildi
A1025: 30-2671-7 | B1025: ENGINE SCAN LIGHT ASSY LH | D1025: 33 | E1025: ELECTRIC | F1025: 54 | G1025: 129935.82 | I1025: =HYPERLINK("\\avrasya\THY_BSK_TEKNIK\MD_TEKNIK_ANLASMALAR_VE_ODEMELER\Teknik Envanter Takip Şefliği\IPC\A330\" &D1025&"\"& A1025 & ".png", "Resim için basınız") -> Resim için basınız
A1026: 30-2671-8 | B1026: ENGINE SCAN LIGHT ASSY RH | D1026: 33 | E1026: ELECTRIC | F1026: 57 | G1026: 55379.78 | I1026: =HYPERLINK("\\avrasya\THY_BSK_TEKNIK\MD_TEKNIK_ANLASMALAR_VE_ODEMELER\Teknik Envanter Takip Şefliği\IPC\A330\" &D1026&"\"& A1026 & ".png", "Resim için basınız") -> Resim için basınız
A1027: 271-200-025-207 | B1027: ENGINE VIBRATION UNIT | D1027: 73 | E1027: ATE | F1027: 17 | G1027: 107623.9 | I1027: =HYPERLINK("\\avrasya\THY_BSK_TEKNIK\MD_TEKNIK_ANLASMALAR_VE_ODEMELER\Teknik Envanter Takip Şefliği\IPC\A330\" &D1027&"\"& A1027 & ".png", "Resim için basınız") -> Resim için basınız
A1028: 974976 | B1028: ENGINE_DRIVEN PUMP | D1028: 29 | E1028: HYDRAUL | F1028: 28 | G1028: 892782 | I1028: =HYPERLINK("\\avrasya\THY_BSK_TEKNIK\MD_TEKNIK_ANLASMALAR_VE_ODEMELER\Teknik Envanter Takip Şefliği\IPC\A330\" &D1028&"\"& A1028 & ".png", "Resim için basınız") -> Resim için basınız
A1029: 3022053-001 | B1029: ENGINE_DRIVEN PUMP | D1029: 29 | E1029: HYDRAUL | F1029: 241 | G1029: 892782 | I1029: =HYPERLINK("\\avrasya\THY_BSK_TEKNIK\MD_TEKNIK_ANLASMALAR_VE_ODEMELER\Teknik Envanter Takip Şefliği\IPC\A330\" &D1029&"\"& A1029 & ".png", "Resim için basınız") -> Resim için basınız
A1030: 974800 | B1030: ENGINE_DRIVEN PUMP | D1030: 29 | E1030: HYDRAUL | F1030: 11 | G1030: 300916.82 | I1030: =HYPERLINK("\\avrasya\THY_BSK_TEKNIK\MD_TEKNIK_ANLASMALAR_VE_ODEMELER\Teknik Envanter Takip Şefliği\IPC\A330\" &D1030&"\"& A1030 & ".png", "Resim için basınız") -> Resim için basınız
A1031: 3022151-000 | B1031: ENGINE_DRIVEN PUMP | D1031: 29 | E1031: HYDRAUL | F1031: 9 | G1031: 810298.96 | I1031: =HYPERLINK("\\avrasya\THY_BSK_TEKNIK\MD_TEKNIK_ANLASMALAR_VE_ODEMELER\Teknik Envanter Takip Şefliği\IPC\A330\" &D1031&"\"& A1031 & ".png", "Resim için basınız") -> Resim için basınız
A1032: RD-AA5007-13 | B1032: ENH. VIDEO SYS CONTR UNIT | D1032: 23 | E1032: IFE | F1032: 5 | G1032: 17279.03 | I1032: =HYPERLINK("\\avrasya\THY_BSK_TEKNIK\MD_TEKNIK_ANLASMALAR_VE_ODEMELER\Teknik Envanter Takip Şefliği\IPC\A330\" &D1032&"\"& A1032 & ".png", "Resim için basınız") -> Resim için basınız
A1033: RD-AA1008-01 | B1033: ENHAN. PES CONTROLLER II | D1033: 23 | E1033: IFE | F1033: 7 | G1033: 42474.05 | I1033: =HYPERLINK("\\avrasya\THY_BSK_TEKNIK\MD_TEKNIK_ANLASMALAR_VE_ODEMELER\Teknik Envanter Takip Şefliği\IPC\A330\" &D1033&"\"& A1033 & ".png", "Resim için basınız") -> Resim için basınız
A1034: 69000942-151 | B1034: ENHANCED EGPWC | D1034: 34 | E1034: ATE | F1034: 82 | G1034: 89874.3 | I1034: =HYPERLINK("\\avrasya\THY_BSK_TEKNIK\MD_TEKNIK_ANLASMALAR_VE_ODEMELER\Teknik Envanter Takip Şefliği\IPC\A330\" &D1034&"\"& A1034 & ".png", "Resim için basınız") -> Resim için basınız
A1035: C19755BA01 | B1035: ENHANCED LIQ.CRYS.DISP.UN | D1035: 31 | E1035: ATE | F1035: 1088 | G1035: 5483816 | I1035: =HYPERLINK("\\avrasya\THY_BSK_TEKNIK\MD_TEKNIK_ANLASMALAR_VE_ODEMELER\Teknik Envanter Takip Şefliği\IPC\A330\" &D1035&"\"& A1035 & ".png", "Resim için basınız") -> Resim için basınız
A1036: HFE95-20D | B1036: ESPRESSO COFFE MAKER | D1036: 25 | E1036: GALLEY | F1036: 147 | G1036: 87685.2 | I1036: =HYPERLINK("\\avrasya\THY_BSK_TEKNIK\MD_TEKNIK_ANLASMALAR_VE_ODEMELER\Teknik Envanter Takip Şefliği\IPC\A330\" &D1036&"\"& A1036 & ".png", "Resim için basınız") -> Resim için basınız
... A5094: D68052-1 | B5094: ROD | D5094: 32 | E5094: LDG | F5094: 1 | G5094: 0 | I5094: =HYPERLINK("\\avrasya\THY_BSK_TEKNIK\MD_TEKNIK_ANLASMALAR_VE_ODEMELER\Teknik Envanter Takip Şefliği\IPC\A330\" &D5094&"\"& A5094 & ".png", "Resim için basınız") -> Resim için basınız

Sheet A350
A1: PN | B1: PN DESC | C1: ilgili | D1: CHAPTER | E1: SUB CATEGORY | F1: QTY | G1: FA AMOUNT | H1: Fonksiyonu | I1: Görsel | J1: Resim Notu
A2: RD-NB4312-01 | B2: 3G EXPHONE SIEMENS NETWORK CONTROLLER UNIT | D2: 23 | E2: IFE | F2: 26 | G2: 8310376 | I2: =HYPERLINK("\\avrasya\THY_BSK_TEKNIK\MD_TEKNIK_ANLASMALAR_VE_ODEMELER\Teknik Envanter Takip Şefliği\IPC\A350\" &D2&"\"& A2 & ".png", "Resim için basınız") -> Resim için basınız
A3: RD-AA8190-01 | B3: 4G ENHANCED CELL MODEM (4G ECM) | D3: 23 | E3: IFE | F3: 247 | G3: 898253.44 | I3: =HYPERLINK("\\avrasya\THY_BSK_TEKNIK\MD_TEKNIK_ANLASMALAR_VE_ODEMELER\Teknik Envanter Takip Şefliği\IPC\A350\" &D3&"\"& A3 & ".png", "Resim için basınız") -> Resim için basınız
A4: RD-FD6795-01 | B4: 9" SMART MONITOR | D4: 44 | E4: IFE | F4: 278 | G4: 63746.53 | I4: =HYPERLINK("\\avrasya\THY_BSK_TEKNIK\MD_TEKNIK_ANLASMALAR_VE_ODEMELER\Teknik Envanter Takip Şefliği\IPC\A350\" &D4&"\"& A4 & ".png", "Resim için basınız") -> Resim için basınız
A5: RD-FE9816-01 | B5: 16" WALL MOUNTED MONITOR | D5: 23 | E5: IFE | F5: 262 | G5: 91048.72 | I5: =HYPERLINK("\\avrasya\THY_BSK_TEKNIK\MD_TEKNIK_ANLASMALAR_VE_ODEMELER\Teknik Envanter Takip Şefliği\IPC\A350\" &D5&"\"& A5 & ".png", "Resim için basınız") -> Resim için basınız
A6: 33900052-13 | B6: 378 CUBIC INCH FIRE EXTINGUISHER | D6: 26 | E6: OXYGEN | F6: 31 | G6: 604156.37 | I6: =HYPERLINK("\\avrasya\THY_BSK_TEKNIK\MD_TEKNIK_ANLASMALAR_VE_ODEMELER\Teknik Envanter Takip Şefliği\IPC\A350\" &D6&"\"& A6 & ".png", "Resim için basınız") -> Resim için basınız
A7: F5746268800400 | B7: A330 SLAT NO 6(LH) | D7: 27 | E7: COMPOSIT | F7: 23 | G7: 0 | I7: =HYPERLINK("\\avrasya\THY_BSK_TEKNIK\MD_TEKNIK_ANLASMALAR_VE_ODEMELER\Teknik Envanter Takip Şefliği\IPC\A350\" &D7&"\"& A7 & ".png", "Resim için basınız") -> Resim için basınız
A8: F5746268800500 | B8: A330 SLAT NO 6(RH) | D8: 27 | E8: COMPOSIT | F8: 24 | G8: 0 | I8: =HYPERLINK("\\avrasya\THY_BSK_TEKNIK\MD_TEKNIK_ANLASMALAR_VE_ODEMELER\Teknik Envanter Takip Şefliği\IPC\A350\" &D8&"\"& A8 & ".png", "Resim için basınız") -> Resim için basınız
A9: LA6L00306H2110B | B9: ABPM-AVIONICS BARE PROCESSOR MODULE | D9: 46 | E9: ATE | F9: 3 | G9: 100556.19 | I9: =HYPERLINK("\\avrasya\THY_BSK_TEKNIK\MD_TEKNIK_ANLASMALAR_VE_ODEMELER\Teknik Envanter Takip Şefliği\IPC\A350\" &D9&"\"& A9 & ".png", "Resim için basınız") -> Resim için basınız
A10: 3952991-01 | B10: ACCUMULATOR-SUCTION,HYDRAULIC | D10: 29 | E10: HYDRAUL | F10: 120 | G10: 350205.88 | I10: =HYPERLINK("\\avrasya\THY_BSK_TEKNIK\MD_TEKNIK_ANLASMALAR_VE_ODEMELER\Teknik Envanter Takip Şefliği\IPC\A350\" &D10&"\"& A10 & ".png", "Resim için basınız") -> Resim için basınız
A11: RD-FA3951-01 | B11: ACTIVE USB HUB | D11: 23 | E11: IFE | F11: 562 | G11: 70033.79 | I11: =HYPERLINK("\\avrasya\THY_BSK_TEKNIK\MD_TEKNIK_ANLASMALAR_VE_ODEMELER\Teknik Envanter Takip Şefliği\IPC\A350\" &D11&"\"& A11 & ".png", "Resim için basınız") -> Resim için basınız
A12: P35502M010 | B12: ACTUATOR | D12: 25 | E12: SEAT | F12: 94 | G12: 291874.83 | I12: =HYPERLINK("\\avrasya\THY_BSK_TEKNIK\MD_TEKNIK_ANLASMALAR_VE_ODEMELER\Teknik Envanter Takip Şefliği\IPC\A350\" &D12&"\"& A12 & ".png", "Resim için basınız") -> Resim için basınız
A13: 5090007-104 | B13: ACTUATOR, TCC VALVE-HP/IP | D13: 75 | E13: FUEL | F13: 136 | G13: 843730.61 | I13: =HYPERLINK("\\avrasya\THY_BSK_TEKNIK\MD_TEKNIK_ANLASMALAR_VE_ODEMELER\Teknik Envanter Takip Şefliği\IPC\A350\" &D13&"\"& A13 & ".png", "Resim için basınız") -> Resim için basınız
... A36: 4808-0008 | B36: BOLT-CROSS,NLG DRAGSTAY | D36: 32 | E36: LDG | F36: 61 | G36: 19213.21 | I36: =HYPERLINK("\\avrasya\THY_BSK_TEKNIK\MD_TEKNIK_ANLASMALAR_VE_ODEMELER\Teknik Envanter Takip Şefliği\IPC\A350\" &D36&"\"& A36 & ".png", "Resim için basınız") -> Resim için basınız
A37: AR4923-3 | B37: BOLTING SYSTEM-DOOR | C37: TAHA | D37: 52 | E37: MECHANIC | F37: 31 | G37: 86449.35 | H37: Kapının gövdeye güvenli şekilde kilitlenmesini ve uçuş sırasında sabit durmasını sağlayan parçadır | I37: =HYPERLINK("\\avrasya\THY_BSK_TEKNIK\MD_TEKNIK_ANLASMALAR_VE_ODEMELER\Teknik Envanter Takip Şefliği\IPC\A350\" &D37&"\"& A37 & ".png", "Resim için basınız") -> Resim için basınız | J37: Resim Girildi
A38: 34800027-1 | B38: BOTTLE ASSY-FIRE EXTINGUISHER | D38: 26 | E38: OXYGEN | F38: 31 | G38: 436195 | I38: =HYPERLINK("\\avrasya\THY_BSK_TEKNIK\MD_TEKNIK_ANLASMALAR_VE_ODEMELER\Teknik Envanter Takip Şefliği\IPC\A350\" &D38&"\"& A38 & ".png", "Resim için basınız") -> Resim için basınız
A39: 34800028-1 | B39: BOTTLE ASSY-FIRE EXTINGUISHER | D39: 26 | E39: OXYGEN | F39: 32 | G39: 558910.71 | I39: =HYPERLINK("\\avrasya\THY_BSK_TEKNIK\MD_TEKNIK_ANLASMALAR_VE_ODEMELER\Teknik Envanter Takip Şefliği\IPC\A350\" &D39&"\"& A39 & ".png", "Resim için basınız") -> Resim için basınız
A40: 176900-00 | B40: BOTTLE,OXYGEN,MEDICAL | D40: 35 | E40: OXYGEN | F40: 180 | G40: 28138.8 | I40: =HYPERLINK("\\avrasya\THY_BSK_TEKNIK\MD_TEKNIK_ANLASMALAR_VE_ODEMELER\Teknik Envanter Takip Şefliği\IPC\A350\" &D40&"\"& A40 & ".png", "Resim için basınız") -> Resim için basınız
A41: 176900 | B41: BOTTLE,OXYGEN,MEDICAL | D41: 35 | E41: OXYGEN | F41: 77 | G41: 26114.7 | I41: =HYPERLINK("\\avrasya\THY_BSK_TEKNIK\MD_TEKNIK_ANLASMALAR_VE_ODEMELER\Teknik Envanter Takip Şefliği\IPC\A350\" &D41&"\"& A41 & ".png", "Resim için basınız") -> Resim için basınız
A42: CH92107-5 | B42: BOX, EXCITER NO.1 LOWER | D42: 74 | E42: ELECTRIC | F42: 141 | G42: 489366.64 | I42: =HYPERLINK("\\avrasya\THY_BSK_TEKNIK\MD_TEKNIK_ANLASMALAR_VE_ODEMELER\Teknik Envanter Takip Şefliği\IPC\A350\" &D42&"\"& A42 & ".png", "Resim için basınız") -> Resim için basınız
A43: KH17504 | B43: BRACKET, ASSY FRONT ENGINE MOUNT | D43: 71 | E43: ENGINE | F43: 64 | G43: 1449345.4 | I43: =HYPERLINK("\\avrasya\THY_BSK_TEKNIK\MD_TEKNIK_ANLASMALAR_VE_ODEMELER\Teknik Envanter Takip Şefliği\IPC\A350\" &D43&"\"& A43 & ".png", "Resim için basınız") -> Resim için basınız
A44: KH34690 | B44: BRACKET, ASSY LINK SUPPORT-REAR ENGINE MOUNT | D44: 71 | E44: ENGINE | F44: 61 | G44: 6488301.1 | I44: =HYPERLINK("\\avrasya\THY_BSK_TEKNIK\MD_TEKNIK_ANLASMALAR_VE_ODEMELER\Teknik Envanter Takip Şefliği\IPC\A350\" &D44&"\"& A44 & ".png", "Resim için basınız") -> Resim için basınız
A45: C20288000-2 | B45: BRAKE ACCUMULATOR | D45: 32 | E45: HYDRAUL | F45: 274 | G45: 355773.45 | I45: =HYPERLINK("\\avrasya\THY_BSK_TEKNIK\MD_TEKNIK_ANLASMALAR_VE_ODEMELER\Teknik Envanter Takip Şefliği\IPC\A350\" &D45&"\"& A45 & ".png", "Resim için basınız") -> Resim için basınız
A46: C20677202 | B46: BRAKE ASSY-CARBON | D46: 32 | E46: BRAKE | F46: 206 | G46: 4072558 | I46: =HYPERLINK("\\avrasya\THY_BSK_TEKNIK\MD_TEKNIK_ANLASMALAR_VE_ODEMELER\Teknik Envanter Takip Şefliği\IPC\A350\" &D46&"\"& A46 & ".png", "Resim için basınız") -> Resim için basınız
A47: RD-NB2504-01 | B47: BROADBAND CONTROLLER(BC-03) | D47: 44 | E47: IFE | F47: 217 | G47: 3392248.5 | I47: =HYPERLINK("\\avrasya\THY_BSK_TEKNIK\MD_TEKNIK_ANLASMALAR_VE_ODEMELER\Teknik Envanter Takip Şefliği\IPC\A350\" &D47&"\"& A47 & ".png", "Resim için basınız") -> Resim için basınız
A48: 4313700-01-6600 | B48: BUN WARMER | D48: 25 | E48: GALLEY | F48: 10 | G48: 222250.71 | I48: =HYPERLINK("\\avrasya\THY_BSK_TEKNIK\MD_TEKNIK_ANLASMALAR_VE_ODEMELER\Teknik Envanter Takip Şefliği\IPC\A350\" &D48&"\"& A48 & ".png", "Resim için basınız") -> Resim için basınız
A49: 5080072-101 | B49: BY-PASS THERMAL,VFG | D49: 24 | E49: ELECTMEC | F49: 135 | G49: 63990.07 | I49: =HYPERLINK("\\avrasya\THY_BSK_TEKNIK\MD_TEKNIK_ANLASMALAR_VE_ODEMELER\Teknik Envanter Takip Şefliği\IPC\A350\" &D49&"\"& A49 & ".png", "Resim için basınız") -> Resim için basınız
... A54: 5090012-104 | B54: CABLE, CONTROL IP ZONE 3 TCC | D54: 75 | E54: ENGINE | F54: 69 | G54: 75143.03 | I54: =HYPERLINK("\\avrasya\THY_BSK_TEKNIK\MD_TEKNIK_ANLASMALAR_VE_ODEMELER\Teknik Envanter Takip Şefliği\IPC\A350\" &D54&"\"& A54 & ".png", "Resim için basınız") -> Resim için basınız
A55: 30903898 | B55: CARTRIDGE | C55: TAHA | D55: 26 | E55: OXYGEN | F55: 781 | G55: 52563.41 | H55: Acil tahliye kaydıraklarının aniden şişmesini sağlayan içinde CO2 veya nitrojen bulunan tüptür. | I55: =HYPERLINK("\\avrasya\THY_BSK_TEKNIK\MD_TEKNIK_ANLASMALAR_VE_ODEMELER\Teknik Envanter Takip Şefliği\IPC\A350\" &D55&"\"& A55 & ".png", "Resim için basınız") -> Resim için basınız | J55: Resim Girildi
A56: Z017H000075A | B56: CIDS DIRECTOR | D56: 44 | E56: IFE | F56: 22 | G56: 2715461.6 | I56: =HYPERLINK("\\avrasya\THY_BSK_TEKNIK\MD_TEKNIK_ANLASMALAR_VE_ODEMELER\Teknik Envanter Takip Şefliği\IPC\A350\" &D56&"\"& A56 & ".png", "Resim için basınız") -> Resim için basınız
A57: Z017H0001A10 | B57: CIDS DIRECTOR | D57: 23 | E57: IFE | F57: 40 | G57: 1198892.5 | I57: =HYPERLINK("\\avrasya\THY_BSK_TEKNIK\MD_TEKNIK_ANLASMALAR_VE_ODEMELER\Teknik Envanter Takip Şefliği\IPC\A350\" &D57&"\"& A57 & ".png", "Resim için basınız") -> Resim için basınız
A58: N40-2A10301-103 | B58: CIDS HANDSET WITH SUPPORT BRAC | D58: 23 | E58: RADIO | F58: 30 | G58: 25215.98 | I58: =HYPERLINK("\\avrasya\THY_BSK_TEKNIK\MD_TEKNIK_ANLASMALAR_VE_ODEMELER\Teknik Envanter Takip Şefliği\IPC\A350\" &D58&"\"& A58 & ".png", "Resim için basınız") -> Resim için basınız
A59: N40-2A50402-104 | B59: CIDS HANDSET WITH SUPPORT BRAC | D59: 23 | E59: RADIO | F59: 304 | G59: 73748.83 | I59: =HYPERLINK("\\avrasya\THY_BSK_TEKNIK\MD_TEKNIK_ANLASMALAR_VE_ODEMELER\Teknik Envanter Takip Şefliği\IPC\A350\" &D59&"\"& A59 & ".png", "Resim için basınız") -> Resim için basınız
A60: 8430K1-3 | B60: CMV-CONCENTRATOR MULTIPLEXOR VIDEO | D60: 31 | E60: ATE | F60: 59 | G60: 3484025.9 | I60: =HYPERLINK("\\avrasya\THY_BSK_TEKNIK\MD_TEKNIK_ANLASMALAR_VE_ODEMELER\Teknik Envanter Takip Şefliği\IPC\A350\" &D60&"\"& A60 & ".png", "Resim için basınız") -> Resim için basınız
A61: 805984-11 | B61: COMPOSITE OXYGEN CYLINDER | D61: 35 | E61: OXYGEN | F61: 2328 | G61: 78209.99 | I61: =HYPERLINK("\\avrasya\THY_BSK_TEKNIK\MD_TEKNIK_ANLASMALAR_VE_ODEMELER\Teknik Envanter Takip Şefliği\IPC\A350\" &D61&"\"& A61 & ".png", "Resim için basınız") -> Resim için basınız
A62: FW84895 | B62: CONE | D62: 71 | E62: ENGINE | F62: 69 | G62: 5329611.3 | I62: =HYPERLINK("\\avrasya\THY_BSK_TEKNIK\MD_TEKNIK_ANLASMALAR_VE_ODEMELER\Teknik Envanter Takip Şefliği\IPC\A350\" &D62&"\"& A62 & ".png", "Resim için basınız") -> Resim için basınız
A63: 564CA04A11Y00 | B63: CONTACTOR-THREE POLE | D63: 24 | E63: ELECTRIC | F63: 3 | G63: 1746.34 | I63: =HYPERLINK("\\avrasya\THY_BSK_TEKNIK\MD_TEKNIK_ANLASMALAR_VE_ODEMELER\Teknik Envanter Takip Şefliği\IPC\A350\" &D63&"\"& A63 & ".png", "Resim için basınız") -> Resim için basınız
A64: RD-FA1074-01 | B64: CONTENT SERVER ( 6.4 TB) | D64: 23 | E64: IFE | F64: 137 | G64: 9779800 | I64: =HYPERLINK("\\avrasya\THY_BSK_TEKNIK\MD_TEKNIK_ANLASMALAR_VE_ODEMELER\Teknik Envanter Takip Şefliği\IPC\A350\" &D64&"\"& A64 & ".png", "Resim için basınız") -> Resim için basınız
A65: 965-1695-002 | B65: CONTROL PANEL-AESU | D65: 34 | E65: RADIO | F65: 31 | G65: 125772.85 | I65: =HYPERLINK("\\avrasya\THY_BSK_TEKNIK\MD_TEKNIK_ANLASMALAR_VE_ODEMELER\Teknik Envanter Takip Şefliği\IPC\A350\" &D65&"\"& A65 & ".png", "Resim için basınız") -> Resim için basınız
A66: 2119332-01 | B66: CONTROL UNIT-OUTFLOW VALVE | D66: 21 | E66: PNEUMATC | F66: 59 | G66: 434624.43 | I66: =HYPERLINK("\\avrasya\THY_BSK_TEKNIK\MD_TEKNIK_ANLASMALAR_VE_ODEMELER\Teknik Envanter Takip Şefliği\IPC\A350\" &D66&"\"& A66 & ".png", "Resim için basınız") -> Resim için basınız
A67: 38201-370 | B67: CONTROL UNIT-THERMOSTAT,DEVICE | D67: 38 | E67: ELECTRIC | F67: 59 | G67: 684642.2 | I67: =HYPERLINK("\\avrasya\THY_BSK_TEKNIK\MD_TEKNIK_ANLASMALAR_VE_ODEMELER\Teknik Envanter Takip Şefliği\IPC\A350\" &D67&"\"& A67 & ".png", "Resim için basınız") -> Resim için basınız
... A84: 9390A-501 | B84: DEFIBRILLATOR | D84: 25 | E84: INSTRMNT | F84: 1 | G84: 32631.42 | I84: =HYPERLINK("\\avrasya\THY_BSK_TEKNIK\MD_TEKNIK_ANLASMALAR_VE_ODEMELER\Teknik Envanter Takip Şefliği\IPC\A350\" &D84&"\"& A84 & ".png", "Resim için basınız") -> Resim için basınız
A85: 9300E-1001-TS0 | B85: DEFIBRILLATOR | C85: TAHA | D85: 25 | E85: INSTRMNT | F85: 63 | G85: 102074.09 | H85: Kalp ritmi bozukluklarında ve ciddi kalp durmalarında kullanılan kalp ritmini düzenleyen cihazdır. | I85: =HYPERLINK("\\avrasya\THY_BSK_TEKNIK\MD_TEKNIK_ANLASMALAR_VE_ODEMELER\Teknik Envanter Takip Şefliği\IPC\A350\" &D85&"\"& A85 & ".png", "Resim için basınız") -> Resim için basınız | J85: Resim Girildi
A86: 9300E-1001 | B86: DEFIBRILLATOR | D86: 25 | E86: INSTRMNT | F86: 13 | G86: 102074.09 | I86: =HYPERLINK("\\avrasya\THY_BSK_TEKNIK\MD_TEKNIK_ANLASMALAR_VE_ODEMELER\Teknik Envanter Takip Şefliği\IPC\A350\" &D86&"\"& A86 & ".png", "Resim için basınız") -> Resim için basınız
A87: 9390E-501 | B87: DEFIBRILLATOR | D87: 25 | E87: INSTRMNT | F87: 2 | G87: 43098.18 | I87: =HYPERLINK("\\avrasya\THY_BSK_TEKNIK\MD_TEKNIK_ANLASMALAR_VE_ODEMELER\Teknik Envanter Takip Şefliği\IPC\A350\" &D87&"\"& A87 & ".png", "Resim için basınız") -> Resim için basınız
A88: G5S-04P1 | B88: DEFIBRILLATOR | D88: 25 | E88: INSTRMNT | F88: 1 | G88: 63705.1 | I88: =HYPERLINK("\\avrasya\THY_BSK_TEKNIK\MD_TEKNIK_ANLASMALAR_VE_ODEMELER\Teknik Envanter Takip Şefliği\IPC\A350\" &D88&"\"& A88 & ".png", "Resim için basınız") -> Resim için basınız
A89: 8918-03 | B89: DETECTOR | D89: 26 | E89: INSTRMNT | F89: 61 | G89: 111501.33 | I89: =HYPERLINK("\\avrasya\THY_BSK_TEKNIK\MD_TEKNIK_ANLASMALAR_VE_ODEMELER\Teknik Envanter Takip Şefliği\IPC\A350\" &D89&"\"& A89 & ".png", "Resim için basınız") -> Resim için basınız
A90: 909030-01 | B90: DETECTOR, ASSY,FIRE ZONE 2-CENTRE | D90: 26 | E90: INSTRMNT | F90: 68 | G90: 29851.2 | I90: =HYPERLINK("\\avrasya\THY_BSK_TEKNIK\MD_TEKNIK_ANLASMALAR_VE_ODEMELER\Teknik Envanter Takip Şefliği\IPC\A350\" &D90&"\"& A90 & ".png", "Resim için basınız") -> Resim için basınız
A91: 909028-01 | B91: DETECTOR, ASSY,FIRE ZONE 2-UPPER | D91: 26 | E91: INSTRMNT | F91: 68 | G91: 29870.1 | I91: =HYPERLINK("\\avrasya\THY_BSK_TEKNIK\MD_TEKNIK_ANLASMALAR_VE_ODEMELER\Teknik Envanter Takip Şefliği\IPC\A350\" &D91&"\"& A91 & ".png", "Resim için basınız") -> Resim için basınız
A92: 907822-02 | B92: DETECTOR, FIRE,ZONE 1 AFT | D92: 26 | E92: INSTRMNT | F92: 68 | G92: 69500.93 | I92: =HYPERLINK("\\avrasya\THY_BSK_TEKNIK\MD_TEKNIK_ANLASMALAR_VE_ODEMELER\Teknik Envanter Takip Şefliği\IPC\A350\" &D92&"\"& A92 & ".png", "Resim için basınız") -> Resim için basınız
A93: 8917-19 | B93: DETECTOR, FIRE,ZONE 3 | D93: 26 | E93: INSTRMNT | F93: 142 | G93: 232816.6 | I93: =HYPERLINK("\\avrasya\THY_BSK_TEKNIK\MD_TEKNIK_ANLASMALAR_VE_ODEMELER\Teknik Envanter Takip Şefliği\IPC\A350\" &D93&"\"& A93 & ".png", "Resim için basınız") -> Resim için basınız
A94: 907820-02 | B94: DETECTOR, ZONE 1 FWD | D94: 26 | E94: INSTRMNT | F94: 68 | G94: 93727.56 | I94: =HYPERLINK("\\avrasya\THY_BSK_TEKNIK\MD_TEKNIK_ANLASMALAR_VE_ODEMELER\Teknik Envanter Takip Şefliği\IPC\A350\" &D94&"\"& A94 & ".png", "Resim için basınız") -> Resim için basınız
A95: VA3508 | B95: DETECTOR,CHIP TBH | D95: 79 | E95: HYDRAUL | F95: 14 | G95: 101095.09 | I95: =HYPERLINK("\\avrasya\THY_BSK_TEKNIK\MD_TEKNIK_ANLASMALAR_VE_ODEMELER\Teknik Envanter Takip Şefliği\IPC\A350\" &D95&"\"& A95 & ".png", "Resim için basınız") -> Resim için basınız
A96: Z037H0001110 | B96: DEU - DECODER ENCODER UNIT A | D96: 44 | E96: IFE | F96: 846 | G96: 0 | I96: =HYPERLINK("\\avrasya\THY_BSK_TEKNIK\MD_TEKNIK_ANLASMALAR_VE_ODEMELER\Teknik Envanter Takip Şefliği\IPC\A350\" &D96&"\"& A96 & ".png", "Resim için basınız") -> Resim için basınız
A97: Z037H0000110 | B97: DEU-DECODER ENCODER UNIT A | D97: 44 | E97: RADIO | F97: 417 | G97: 0 | I97: =HYPERLINK("\\avrasya\THY_BSK_TEKNIK\MD_TEKNIK_ANLASMALAR_VE_ODEMELER\Teknik Envanter Takip Şefliği\IPC\A350\" &D97&"\"& A97 & ".png", "Resim için basınız") -> Resim için basınız
... A1890: LV15257 | B1890: OIL TANK ASSY | D1890: 79 | E1890: MECHANIC | F1890: 3 | G1890: 0 | I1890: =HYPERLINK("\\avrasya\THY_BSK_TEKNIK\MD_TEKNIK_ANLASMALAR_VE_ODEMELER\Teknik Envanter Takip Şefliği\IPC\A350\" &D1890&"\"& A1890 & ".png", "Resim için basınız") -> Resim için basınız

Sheet B737
A1: PID_PN | B1: PN DESC | C1: ilgili | D1: Chapter | E1: Sub Category | F1: QTY | G1: Fa Aomunt | H1: Fonksiyonu | I1: Görsel | J1: Resim Notu
A2: 113A4100-9 | B2: 1 SPOILER ASSY LH,GROUND | C2: TAHA | D2: 27 | E2: COMPOSIT | F2: 6 | G2: 25579.2 | H2: Uçak yerdeyken spoiler panelinin açılarak hava akışını kesmesini ve frenlemeyi desteklemesini sağlar | I2: =HYPERLINK("\\avrasya\THY_BSK_TEKNIK\MD_TEKNIK_ANLASMALAR_VE_ODEMELER\Teknik Envanter Takip Şefliği\IPC\B737\" &D2&"\"& A2 & ".png", "Resim için basınız") -> Resim için basınız | J2: Resim girildi
A3: 113A4100-13 | B3: 1 SPOILER ASSY LH,GROUND | C3: TAHA | D3: 27 | E3: COMPOSIT | F3: 89 | G3: 0 | H3: Uçak yerdeyken spoiler panelinin açılarak hava akışını kesmesini ve frenlemeyi desteklemesini sağlar | I3: =HYPERLINK("\\avrasya\THY_BSK_TEKNIK\MD_TEKNIK_ANLASMALAR_VE_ODEMELER\Teknik Envanter Takip Şefliği\IPC\B737\" &D3&"\"& A3 & ".png", "Resim için basınız") -> Resim için basınız | J3: Resim girildi
A4: 113A4100-1 | B4: 1 SPOILER ASSY LH,GROUND | C4: TAHA | D4: 27 | E4: COMPOSIT | F4: 20 | G4: 992.91 | H4: Uçak yerdeyken spoiler panelinin açılarak hava akışını kesmesini ve frenlemeyi desteklemesini sağlar | I4: =HYPERLINK("\\avrasya\THY_BSK_TEKNIK\MD_TEKNIK_ANLASMALAR_VE_ODEMELER\Teknik Envanter Takip Şefliği\IPC\B737\" &D4&"\"& A4 & ".png", "Resim için basınız") -> Resim için basınız | J4: Resim girildi
A5: 3840160-8 | B5: 1.STG.TURBINE ROTOR ASSY. | D5: 49 | E5: APU | F5: 6 | G5: 143000 | I5: =HYPERLINK("\\avrasya\THY_BSK_TEKNIK\MD_TEKNIK_ANLASMALAR_VE_ODEMELER\Teknik Envanter Takip Şefliği\IPC\B737\" &D5&"\"& A5 & ".png", "Resim için basınız") -> Resim için basınız
A6: 3840310-3 | B6: 1.STG.TURBINE ROTOR ASSY. | D6: 49 | E6: APU | F6: 31 | G6: 1885048.1 | I6: =HYPERLINK("\\avrasya\THY_BSK_TEKNIK\MD_TEKNIK_ANLASMALAR_VE_ODEMELER\Teknik Envanter Takip Şefliği\IPC\B737\" &D6&"\"& A6 & ".png", "Resim için basınız") -> Resim için basınız
A7: 3840310-4 | B7: 1.STG.TURBINE ROTOR ASSY. | D7: 49 | E7: APU | F7: 242 | G7: 1913751.7 | I7: =HYPERLINK("\\avrasya\THY_BSK_TEKNIK\MD_TEKNIK_ANLASMALAR_VE_ODEMELER\Teknik Envanter Takip Şefliği\IPC\B737\" &D7&"\"& A7 & ".png", "Resim için basınız") -> Resim için basınız
A8: 113A4200-3 | B8: 2 SPOILER ASSY LH,FLIGHT | D8: 27 | E8: COMPOSIT | F8: 107 | G8: 992.91 | I8: =HYPERLINK("\\avrasya\THY_BSK_TEKNIK\MD_TEKNIK_ANLASMALAR_VE_ODEMELER\Teknik Envanter Takip Şefliği\IPC\B737\" &D8&"\"& A8 & ".png", "Resim için basınız") -> Resim için basınız
A9: 113A4200-1 | B9: 2 SPOILER ASSY LH,FLIGHT | D9: 27 | E9: COMPOSIT | F9: 10 | G9: 0 | I9: =HYPERLINK("\\avrasya\THY_BSK_TEKNIK\MD_TEKNIK_ANLASMALAR_VE_ODEMELER\Teknik Envanter Takip Şefliği\IPC\B737\" &D9&"\"& A9 & ".png", "Resim için basınız") -> Resim için basınız
A10: 3840165-4 | B10: 2.STG. TURBINE ROTOR ASSY | D10: 49 | E10: APU | F10: 95 | G10: 1177872.9 | I10: =HYPERLINK("\\avrasya\THY_BSK_TEKNIK\MD_TEKNIK_ANLASMALAR_VE_ODEMELER\Teknik Envanter Takip Şefliği\IPC\B737\" &D10&"\"& A10 & ".png", "Resim için basınız") -> Resim için basınız
A11: 3840165-9 | B11: 2.STG. TURBINE WHEEL | D11: 49 | E11: APU | F11: 188 | G11: 1208340.3 | I11: =HYPERLINK("\\avrasya\THY_BSK_TEKNIK\MD_TEKNIK_ANLASMALAR_VE_ODEMELER\Teknik Envanter Takip Şefliği\IPC\B737\" &D11&"\"& A11 & ".png", "Resim için basınız") -> Resim için basınız
A12: 113A4300-5 | B12: 3 SPOILER ASSY LH,FLIGHT | D12: 27 | E12: COMPOSIT | F12: 69 | G12: 25579.2 | I12: =HYPERLINK("\\avrasya\THY_BSK_TEKNIK\MD_TEKNIK_ANLASMALAR_VE_ODEMELER\Teknik Envanter Takip Şefliği\IPC\B737\" &D12&"\"& A12 & ".png", "Resim için basınız") -> Resim için basınız
A13: 113A4300-3 | B13: 3 SPOILER ASSY LH,FLIGHT | D13: 27 | E13: COMPOSIT | F13: 3 | G13: 992.91 | I13: =HYPERLINK("\\avrasya\THY_BSK_TEKNIK\MD_TEKNIK_ANLASMALAR_VE_ODEMELER\Teknik Envanter Takip Şefliği\IPC\B737\" &D13&"\"& A13 & ".png", "Resim için basınız") -> Resim için basınız
A14: 113A4300-601 | B14: 3 SPOILER ASSY LH,FLIGHT | D14: 27 | E14: COMPOSIT | F14: 37 | G14: 199587.8 | I14: =HYPERLINK("\\avrasya\THY_BSK_TEKNIK\MD_TEKNIK_ANLASMALAR_VE_ODEMELER\Teknik Envanter Takip Şefliği\IPC\B737\" &D14&"\"& A14 & ".png", "Resim için basınız") -> Resim için basınız
A15: 320362-2-1 | B15: 3-WAY SOLENOID VALVE | C15: TAHA | D15: 49 | E15: PNEUMATC | F15: 6 | G15: 712.83 | H15: Elektrik sinyaliyle açılıp kapanarak akışın üç farklı hat arasında yönlendirilmesini veya kesilmesini sağlar | I15: =HYPERLINK("\\avrasya\THY_BSK_TEKNIK\MD_TEKNIK_ANLASMALAR_VE_ODEMELER\Teknik Envanter Takip Şefliği\IPC\B737\" &D15&"\"& A15 & ".png", "Resim için basınız") -> Resim için basınız | J15: Resim girildi
A16: 113A1160-1103 | B16: 4 FLAP-INB TRACK ASSY | C16: TAHA | D16: 27 | E16: MECHANIC | F16: 9 | G16: 0 | H16: Flap panelinin iç kanat kısmında düzgün şekilde hareket etmesini sağlayarak kalkış ve inişte kaldırmayı artırır | I16: =HYPERLINK("\\avrasya\THY_BSK_TEKNIK\MD_TEKNIK_ANLASMALAR_VE_ODEMELER\Teknik Envanter Takip Şefliği\IPC\B737\" &D16&"\"& A16 & ".png", "Resim için basınız") -> Resim için basınız | J16: Resim girildi
A17: 113A4400-601 | B17: 4 SPOILER ASSY LH, FLIGHT | D17: 27 | E17: COMPOSIT | F17: 37 | G17: 199587.8 | I17: =HYPERLINK("\\avrasya\THY_BSK_TEKNIK\MD_TEKNIK_ANLASMALAR_VE_ODEMELER\Teknik Envanter Takip Şefliği\IPC\B737\" &D17&"\"& A17 & ".png", "Resim için basınız") -> Resim için basınız
A18: 113A4400-1 | B18: 4 SPOILER ASSY LH,FLIGHT | D18: 27 | E18: COMPOSIT | F18: 14 | G18: 25579.2 | I18: =HYPERLINK("\\avrasya\THY_BSK_TEKNIK\MD_TEKNIK_ANLASMALAR_VE_ODEMELER\Teknik Envanter Takip Şefliği\IPC\B737\" &D18&"\"& A18 & ".png", "Resim için basınız") -> Resim için basınız
A19: 113A4400-5 | B19: 4 SPOILER ASSY LH,FLIGHT | D19: 27 | E19: COMPOSIT | F19: 69 | G19: 0 | I19: =HYPERLINK("\\avrasya\THY_BSK_TEKNIK\MD_TEKNIK_ANLASMALAR_VE_ODEMELER\Teknik Envanter Takip Şefliği\IPC\B737\" &D19&"\"& A19 & ".png", "Resim için basınız") -> Resim için basınız
A20: 113A4400-3 | B20: 4 SPOILER ASSY LH,FLIGHT | D20: 57 | E20: COMPOSIT | F20: 5 | G20: 992.91 | I20: =HYPERLINK("\\avrasya\THY_BSK_TEKNIK\MD_TEKNIK_ANLASMALAR_VE_ODEMELER\Teknik Envanter Takip Şefliği\IPC\B737\" &D20&"\"& A20 & ".png", "Resim için basınız") -> Resim için basınız
A21: RD-AA8190-01 | B21: 4G ENHANCED CELL MODEM (4G ECM) | D21: 23 | E21: IFE | F21: 247 | G21: 898253.44 | I21: =HYPERLINK("\\avrasya\THY_BSK_TEKNIK\MD_TEKNIK_ANLASMALAR_VE_ODEMELER\Teknik Envanter Takip Şefliği\IPC\B737\" &D21&"\"& A21 & ".png", "Resim için basınız") -> Resim için basınız
A22: 113A1160-1104 | B22: 5 FLAP-INB TRACK ASSY | D22: 27 | E22: MECHANIC | F22: 10 | G22: 173029.86 | I22: =HYPERLINK("\\avrasya\THY_BSK_TEKNIK\MD_TEKNIK_ANLASMALAR_VE_ODEMELER\Teknik Envanter Takip Şefliği\IPC\B737\" &D22&"\"& A22 & ".png", "Resim için basınız") -> Resim için basınız
A23: 113A4500-1 | B23: 5 SPOILER ASSY LH,FLIGHT | D23: 27 | E23: COMPOSIT | F23: 15 | G23: 33352.85 | I23: =HYPERLINK("\\avrasya\THY_BSK_TEKNIK\MD_TEKNIK_ANLASMALAR_VE_ODEMELER\Teknik Envanter Takip Şefliği\IPC\B737\" &D23&"\"& A23 & ".png", "Resim için basınız") -> Resim için basınız
A24: 113A4500-5 | B24: 5 SPOILER ASSY LH,FLIGHT | D24: 27 | E24: COMPOSIT | F24: 69 | G24: 0 | I24: =HYPERLINK("\\avrasya\THY_BSK_TEKNIK\MD_TEKNIK_ANLASMALAR_VE_ODEMELER\Teknik Envanter Takip Şefliği\IPC\B737\" &D24&"\"& A24 & ".png", "Resim için basınız") -> Resim için basınız
A25: 113A4600-7 | B25: 6 SPOILER ASSY LH,GROUND | D25: 27 | E25: COMPOSIT | F25: 41 | G25: 113593.35 | I25: =HYPERLINK("\\avrasya\THY_BSK_TEKNIK\MD_TEKNIK_ANLASMALAR_VE_ODEMELER\Teknik Envanter Takip Şefliği\IPC\B737\" &D25&"\"& A25 & ".png", "Resim için basınız") -> Resim için basınız
A26: 113A4600-1 | B26: 6 SPOILER ASSY LH,GROUND | D26: 27 | E26: COMPOSIT | F26: 23 | G26: 64382.9 | I26: =HYPERLINK("\\avrasya\THY_BSK_TEKNIK\MD_TEKNIK_ANLASMALAR_VE_ODEMELER\Teknik Envanter Takip Şefliği\IPC\B737\" &D26&"\"& A26 & ".png", "Resim için basınız") -> Resim için basınız
A27: 113A4600-5 | B27: 6 SPOILER ASSY LH,GROUND | D27: 27 | E27: COMPOSIT | F27: 30 | G27: 222951.69 | I27: =HYPERLINK("\\avrasya\THY_BSK_TEKNIK\MD_TEKNIK_ANLASMALAR_VE_ODEMELER\Teknik Envanter Takip Şefliği\IPC\B737\" &D27&"\"& A27 & ".png", "Resim için basınız") -> Resim için basınız
A28: 113A4600-601 | B28: 6 SPOILER ASSY LH,GROUND | D28: 27 | E28: COMPOSIT | F28: 37 | G28: 2876740.5 | I28: =HYPERLINK("\\avrasya\THY_BSK_TEKNIK\MD_TEKNIK_ANLASMALAR_VE_ODEMELER\Teknik Envanter Takip Şefliği\IPC\B737\" &D28&"\"& A28 & ".png", "Resim için basınız") -> Resim için basınız
... A1158: 314D2260-509 | B1158: HOLD-OPEN ROD | D1158: 71 | E1158: MECHANIC | F1158: 10 | G1158: 217443.98 | I1158: =HYPERLINK("\\avrasya\THY_BSK_TEKNIK\MD_TEKNIK_ANLASMALAR_VE_ODEMELER\Teknik Envanter Takip Şefliği\IPC\B737\" &D1158&"\"& A1158 & ".png", "Resim için basınız") -> Resim için basınız
A1159: 186A1000-41 | B1159: HORIZONTAL STABILIZER LH | C1159: Enis | D1159: 55 | E1159: STRCTURE | F1159: 17 | G1159: 1037.18 | I1159: =HYPERLINK("\\avrasya\THY_BSK_TEKNIK\MD_TEKNIK_ANLASMALAR_VE_ODEMELER\Teknik Envanter Takip Şefliği\IPC\B737\" &D1159&"\"& A1159 & ".png", "Resim için basınız") -> Resim için basınız
A1160: 186A2000-41 | B1160: HORIZONTAL STABILIZER RH | C1160: Enis | D1160: 55 | E1160: STRCTURE | F1160: 17 | G1160: 1037.18 | I1160: =HYPERLINK("\\avrasya\THY_BSK_TEKNIK\MD_TEKNIK_ANLASMALAR_VE_ODEMELER\Teknik Envanter Takip Şefliği\IPC\B737\" &D1160&"\"& A1160 & ".png", "Resim için basınız") -> Resim için basınız
A1161: 30283-0201 | B1161: HOT SHORT PROTECTOR | D1161: 28 | E1161: INSTRMNT | F1161: 1 | G1161: 19074.09 | I1161: =HYPERLINK("\\avrasya\THY_BSK_TEKNIK\MD_TEKNIK_ANLASMALAR_VE_ODEMELER\Teknik Envanter Takip Şefliği\IPC\B737\" &D1161&"\"& A1161 & ".png", "Resim için basınız") -> Resim için basınız
A1162: 115A5240-1 | B1162: MLG FWD TRUN HOUSING ASSY | D1162: 32 | E1162: LDG | F1162: 33 | G1162: 1079469.1 | I1162: =HYPERLINK("\\avrasya\THY_BSK_TEKNIK\MD_TEKNIK_ANLASMALAR_VE_ODEMELER\Teknik Envanter Takip Şefliği\IPC\B737\" &D1162&"\"& A1162 & ".png", "Resim için basınız") -> Resim için basınız
A1163: 60-75502 | B1163: HOUSING ASSY | D1163: 28 | E1163: FUEL | F1163: 1 | G1163: 0 | I1163: =HYPERLINK("\\avrasya\THY_BSK_TEKNIK\MD_TEKNIK_ANLASMALAR_VE_ODEMELER\Teknik Envanter Takip Şefliği\IPC\B737\" &D1163&"\"& A1163 & ".png", "Resim için basınız") -> Resim için basınız
A1164: 60-98907 | B1164: HOUSING ASSY | D1164: 28 | E1164: FUEL | F1164: 2 | G1164: 0 | I1164: =HYPERLINK("\\avrasya\THY_BSK_TEKNIK\MD_TEKNIK_ANLASMALAR_VE_ODEMELER\Teknik Envanter Takip Şefliği\IPC\B737\" &D1164&"\"& A1164 & ".png", "Resim için basınız") -> Resim için basınız
A1165: 60B89004-7 | B1165: HOUSING ASSY | D1165: 28 | E1165: FUEL | F1165: 42 | G1165: 0 | I1165: =HYPERLINK("\\avrasya\THY_BSK_TEKNIK\MD_TEKNIK_ANLASMALAR_VE_ODEMELER\Teknik Envanter Takip Şefliği\IPC\B737\" &D1165&"\"& A1165 & ".png", "Resim için basınız") -> Resim için basınız
A1166: 9514M54G05 | B1166: HPC AIR DUCT | D1166: 72 | E1166: ENGINE | F1166: 187 | G1166: 49085.35 | I1166: =HYPERLINK("\\avrasya\THY_BSK_TEKNIK\MD_TEKNIK_ANLASMALAR_VE_ODEMELER\Teknik Envanter Takip Şefliği\IPC\B737\" &D1166&"\"& A1166 & ".png", "Resim için basınız") -> Resim için basınız
A1167: 1559M30G10 | B1167: HPC FRONT STATOR CASE | D1167: 72 | E1167: ENGINE | F1167: 36 | G1167: 318408 | I1167: =HYPERLINK("\\avrasya\THY_BSK_TEKNIK\MD_TEKNIK_ANLASMALAR_VE_ODEMELER\Teknik Envanter Takip Şefliği\IPC\B737\" &D1167&"\"& A1167 & ".png", "Resim için basınız") -> Resim için basınız
A1168: 1386M56P03 | B1168: HPCR - FRONT SHAFT | D1168: 72 | E1168: ENGINE | F1168: 255 | G1168: 0 | I1168: =HYPERLINK("\\avrasya\THY_BSK_TEKNIK\MD_TEKNIK_ANLASMALAR_VE_ODEMELER\Teknik Envanter Takip Şefliği\IPC\B737\" &D1168&"\"& A1168 & ".png", "Resim için basınız") -> Resim için basınız
A1169: 1558M31G07 | B1169: HPCR - STG 1-2 SPOOL | D1169: 72 | E1169: ENGINE | F1169: 232 | G1169: 0 | I1169: =HYPERLINK("\\avrasya\THY_BSK_TEKNIK\MD_TEKNIK_ANLASMALAR_VE_ODEMELER\Teknik Envanter Takip Şefliği\IPC\B737\" &D1169&"\"& A1169 & ".png", "Resim için basınız") -> Resim için basınız
A1170: 2116M23P01 | B1170: HPCR - STG 3 DISK | D1170: 72 | E1170: ENGINE | F1170: 228 | G1170: 0 | I1170: =HYPERLINK("\\avrasya\THY_BSK_TEKNIK\MD_TEKNIK_ANLASMALAR_VE_ODEMELER\Teknik Envanter Takip Şefliği\IPC\B737\" &D1170&"\"& A1170 & ".png", "Resim için basınız") -> Resim için basınız
A1171: 2048M20G04 | B1171: HPCR - STG 4-9 SPOOL | D1171: 72 | E1171: ENGINE | F1171: 134 | G1171: 0 | I1171: =HYPERLINK("\\avrasya\THY_BSK_TEKNIK\MD_TEKNIK_ANLASMALAR_VE_ODEMELER\Teknik Envanter Takip Şefliği\IPC\B737\" &D1171&"\"& A1171 & ".png", "Resim için basınız") -> Resim için basınız
A1172: 2048M20G03 | B1172: HPCR - STG 4-9 SPOOL | D1172: 72 | E1172: ENGINE | F1172: 17 | G1172: 0 | I1172: =HYPERLINK("\\avrasya\THY_BSK_TEKNIK\MD_TEKNIK_ANLASMALAR_VE_ODEMELER\Teknik Envanter Takip Şefliği\IPC\B737\" &D1172&"\"& A1172 & ".png", "Resim için basınız") -> Resim için basınız
... A3311: 902014 | B3311: FIRE DETECTOR ASSY, APU | D3311: 26 | E3311: INSTRMNT | F3311: 20 | G3311: 0 | I3311: =HYPERLINK("\\avrasya\THY_BSK_TEKNIK\MD_TEKNIK_ANLASMALAR_VE_ODEMELER\Teknik Envanter Takip Şefliği\IPC\B737\" &D3311&"\"& A3311 & ".png", "Resim için basınız") -> Resim için basınız
A3312: 183A0103-7 | B3312: LH ELEVATOR ASSY | C3312: Enis | D3312: 55 | E3312: COMPOSIT | F3312: 1 | G3312: 0 | I3312: =HYPERLINK("\\avrasya\THY_BSK_TEKNIK\MD_TEKNIK_ANLASMALAR_VE_ODEMELER\Teknik Envanter Takip Şefliği\IPC\B737\" &D3312&"\"& A3312 & ".png", "Resim için basınız") -> Resim için basınız
A3313: 113A9350-201 | B3313: FAIRING ASSY | D3313: 27 | E3313: STRCTURE | F3313: 5 | G3313: 0 | I3313: =HYPERLINK("\\avrasya\THY_BSK_TEKNIK\MD_TEKNIK_ANLASMALAR_VE_ODEMELER\Teknik Envanter Takip Şefliği\IPC\B737\" &D3313&"\"& A3313 & ".png", "Resim için basınız") -> Resim için basınız
A3314: 141A6710-13 | B3314: DOOR ASSY-EQPT ACCESS | D3314: 52 | E3314: STRCTURE | F3314: 7 | G3314: 0 | I3314: =HYPERLINK("\\avrasya\THY_BSK_TEKNIK\MD_TEKNIK_ANLASMALAR_VE_ODEMELER\Teknik Envanter Takip Şefliği\IPC\B737\" &D3314&"\"& A3314 & ".png", "Resim için basınız") -> Resim için basınız
A3315: 024807-002 | B3315: RUDDER TRIM CONT SW ASSY | D3315: 27 | E3315: ELECTRIC | F3315: 19 | G3315: 0 | I3315: =HYPERLINK("\\avrasya\THY_BSK_TEKNIK\MD_TEKNIK_ANLASMALAR_VE_ODEMELER\Teknik Envanter Takip Şefliği\IPC\B737\" &D3315&"\"& A3315 & ".png", "Resim için basınız") -> Resim için basınız
A3316: 15800-348 | B3316: RINSE VALVE | D3316: 38 | E3316: SANITARY | F3316: 2 | G3316: 0 | I3316: =HYPERLINK("\\avrasya\THY_BSK_TEKNIK\MD_TEKNIK_ANLASMALAR_VE_ODEMELER\Teknik Envanter Takip Şefliği\IPC\B737\" &D3316&"\"& A3316 & ".png", "Resim için basınız") -> Resim için basınız
A3317: DMN23-1C | B3317: ANTENNA-VOR/ILS | D3317: 34 | E3317: RADIO | F3317: 41 | G3317: 0 | I3317: =HYPERLINK("\\avrasya\THY_BSK_TEKNIK\MD_TEKNIK_ANLASMALAR_VE_ODEMELER\Teknik Envanter Takip Şefliği\IPC\B737\" &D3317&"\"& A3317 & ".png", "Resim için basınız") -> Resim için basınız
A3318: 2740028-6 | B3318: ROTARY ELECTRO MECHANICAL ACTUATOR | D3318: 21 | E3318: ELECTMEC | F3318: 212 | G3318: 0 | I3318: =HYPERLINK("\\avrasya\THY_BSK_TEKNIK\MD_TEKNIK_ANLASMALAR_VE_ODEMELER\Teknik Envanter Takip Şefliği\IPC\B737\" &D3318&"\"& A3318 & ".png", "Resim için basınız") -> Resim için basınız
A3319: 233145 | B3319: VALVE ASSY | D3319: 29 | E3319: HYDRAUL | F3319: 11 | G3319: 0 | I3319: =HYPERLINK("\\avrasya\THY_BSK_TEKNIK\MD_TEKNIK_ANLASMALAR_VE_ODEMELER\Teknik Envanter Takip Şefliği\IPC\B737\" &D3319&"\"& A3319 & ".png", "Resim için basınız") -> Resim için basınız
A3320: 1697EA1 | B3320: SPEED BRAKE CONTROL VALVE | D3320: 27 | E3320: HYDRAUL | F3320: 19 | G3320: 0 | I3320: =HYPERLINK("\\avrasya\THY_BSK_TEKNIK\MD_TEKNIK_ANLASMALAR_VE_ODEMELER\Teknik Envanter Takip Şefliği\IPC\B737\" &D3320&"\"& A3320 & ".png", "Resim için basınız") -> Resim için basınız
A3321: 8870-13-1175-850-650 | B3321: FIRE DET. LEFT CORE | D3321: 26 | E3321: INSTRMNT | F3321: 123 | G3321: 0 | I3321: =HYPERLINK("\\avrasya\THY_BSK_TEKNIK\MD_TEKNIK_ANLASMALAR_VE_ODEMELER\Teknik Envanter Takip Şefliği\IPC\B737\" &D3321&"\"& A3321 & ".png", "Resim için basınız") -> Resim için basınız
A3322: S332A210-11 | B3322: SUPPLY HOSE | D3322: 29 | E3322: HYDRAUL | F3322: 5 | G3322: 0 | I3322: =HYPERLINK("\\avrasya\THY_BSK_TEKNIK\MD_TEKNIK_ANLASMALAR_VE_ODEMELER\Teknik Envanter Takip Şefliği\IPC\B737\" &D3322&"\"& A3322 & ".png", "Resim için basınız") -> Resim için basınız
A3323: 8870-11-1000-530-345 | B3323: FIRE DET. UPPER FAN | D3323: 26 | E3323: INSTRMNT | F3323: 28 | G3323: 0 | I3323: =HYPERLINK("\\avrasya\THY_BSK_TEKNIK\MD_TEKNIK_ANLASMALAR_VE_ODEMELER\Teknik Envanter Takip Şefliği\IPC\B737\" &D3323&"\"& A3323 & ".png", "Resim için basınız") -> Resim için basınız
A3324: 8870-14-1175-850-650 | B3324: FIRE DET. RIGHT CORE | D3324: 26 | E3324: INSTRMNT | F3324: 47 | G3324: 0 | I3324: =HYPERLINK("\\avrasya\THY_BSK_TEKNIK\MD_TEKNIK_ANLASMALAR_VE_ODEMELER\Teknik Envanter Takip Şefliği\IPC\B737\" &D3324&"\"& A3324 & ".png", "Resim için basınız") -> Resim için basınız
... A3398: R082121 | B3398: K082121'IN HAYALI MASKI | D3398: 29 | E3398: HYDRAUL | F3398: 108 | G3398: 0 | I3398: =HYPERLINK("\\avrasya\THY_BSK_TEKNIK\MD_TEKNIK_ANLASMALAR_VE_ODEMELER\Teknik Envanter Takip Şefliği\IPC\B737\" &D3398&"\"& A3398 & ".png", "Resim için basınız") -> Resim için basınız
A3399: 002A0016-32 | B3399: RH ELEVATOR ASSY | C3399: Enis | D3399: 55 | E3399: COMPOSIT | F3399: 17 | G3399: 0 | I3399: =HYPERLINK("\\avrasya\THY_BSK_TEKNIK\MD_TEKNIK_ANLASMALAR_VE_ODEMELER\Teknik Envanter Takip Şefliği\IPC\B737\" &D3399&"\"& A3399 & ".png", "Resim için basınız") -> Resim için basınız
A3400: 325-026-101-0 | B3400: J6 HARNESS | D3400: 73 | E3400: HARNESS | F3400: 34 | G3400: 0 | I3400: =HYPERLINK("\\avrasya\THY_BSK_TEKNIK\MD_TEKNIK_ANLASMALAR_VE_ODEMELER\Teknik Envanter Takip Şefliği\IPC\B737\" &D3400&"\"& A3400 & ".png", "Resim için basınız") -> Resim için basınız
A3401: 81000-37703 | B3401: LH WING T.ILLUM.LGH. ASSY | D3401: 33 | E3401: ELECTRIC | F3401: 4 | G3401: 0 | I3401: =HYPERLINK("\\avrasya\THY_BSK_TEKNIK\MD_TEKNIK_ANLASMALAR_VE_ODEMELER\Teknik Envanter Takip Şefliği\IPC\B737\" &D3401&"\"& A3401 & ".png", "Resim için basınız") -> Resim için basınız
A3402: 81000-38204 | B3402: EXTERIOR EMERGENCY OFFWING LIGHT ASSY (LH) | D3402: 33 | E3402: ELECTRIC | F3402: 3 | G3402: 0 | I3402: =HYPERLINK("\\avrasya\THY_BSK_TEKNIK\MD_TEKNIK_ANLASMALAR_VE_ODEMELER\Teknik Envanter Takip Şefliği\IPC\B737\" &D3402&"\"& A3402 & ".png", "Resim için basınız") -> Resim için basınız
A3403: 114A5010-204 | B3403: SLAT ASSY/SUB ASSY-BOX, RH, NO 8 | D3403: 27 | E3403: COMPOSIT | F3403: 1 | G3403: 0 | I3403: =HYPERLINK("\\avrasya\THY_BSK_TEKNIK\MD_TEKNIK_ANLASMALAR_VE_ODEMELER\Teknik Envanter Takip Şefliği\IPC\B737\" &D3403&"\"& A3403 & ".png", "Resim için basınız") -> Resim için basınız
A3404: 161A1126-1 | B3404: INNER CYLINDER ASSEMBLY | D3404: 32 | E3404: LDG | F3404: 9 | G3404: 0 | I3404: =HYPERLINK("\\avrasya\THY_BSK_TEKNIK\MD_TEKNIK_ANLASMALAR_VE_ODEMELER\Teknik Envanter Takip Şefliği\IPC\B737\" &D3404&"\"& A3404 & ".png", "Resim için basınız") -> Resim için basınız
A3405: 10-60581-3 | B3405: MOTOR OPRTD SELECTOR VLV | D3405: 29 | E3405: HYDRAUL | F3405: 18 | G3405: 0 | I3405: =HYPERLINK("\\avrasya\THY_BSK_TEKNIK\MD_TEKNIK_ANLASMALAR_VE_ODEMELER\Teknik Envanter Takip Şefliği\IPC\B737\" &D3405&"\"& A3405 & ".png", "Resim için basınız") -> Resim için basınız
A3406: 162A1100-5 | B3406: NOSE LANDING GEAR | D3406: 32 | E3406: LDG | F3406: 26 | G3406: 0 | I3406: =HYPERLINK("\\avrasya\THY_BSK_TEKNIK\MD_TEKNIK_ANLASMALAR_VE_ODEMELER\Teknik Envanter Takip Şefliği\IPC\B737\" &D3406&"\"& A3406 & ".png", "Resim için basınız") -> Resim için basınız
A3407: 183A0103-8 | B3407: RH ELEVATOR ASSY | C3407: Enis | D3407: 55 | E3407: COMPOSIT | F3407: 1 | G3407: 0 | I3407: =HYPERLINK("\\avrasya\THY_BSK_TEKNIK\MD_TEKNIK_ANLASMALAR_VE_ODEMELER\Teknik Envanter Takip Şefliği\IPC\B737\" &D3407&"\"& A3407 & ".png", "Resim için basınız") -> Resim için basınız
A3408: 315A2521-20 | B3408: T/R SLEEVE ASSY (RH) | D3408: 78 | E3408: COMPOSIT | F3408: 32 | G3408: 0 | I3408: =HYPERLINK("\\avrasya\THY_BSK_TEKNIK\MD_TEKNIK_ANLASMALAR_VE_ODEMELER\Teknik Envanter Takip Şefliği\IPC\B737\" &D3408&"\"& A3408 & ".png", "Resim için basınız") -> Resim için basınız
A3409: 315A2500-21 | B3409: T/R SLEEVE ASSY(LH) | D3409: 78 | E3409: COMPOSIT | F3409: 3 | G3409: 0 | I3409: =HYPERLINK("\\avrasya\THY_BSK_TEKNIK\MD_TEKNIK_ANLASMALAR_VE_ODEMELER\Teknik Envanter Takip Şefliği\IPC\B737\" &D3409&"\"& A3409 & ".png", "Resim için basınız") -> Resim için basınız
A3410: 340-046-603-0 | B3410: AGB HOUSING ASSY. | D3410: 72 | E3410: ENGINE | F3410: 40 | G3410: 0 | I3410: =HYPERLINK("\\avrasya\THY_BSK_TEKNIK\MD_TEKNIK_ANLASMALAR_VE_ODEMELER\Teknik Envanter Takip Şefliği\IPC\B737\" &D3410&"\"& A3410 & ".png", "Resim için basınız") -> Resim için basınız
A3411: 340-059-925-0 | B3411: FAN FRAME SHROUD | D3411: 72 | E3411: ENGINE | F3411: 32 | G3411: 0 | I3411: =HYPERLINK("\\avrasya\THY_BSK_TEKNIK\MD_TEKNIK_ANLASMALAR_VE_ODEMELER\Teknik Envanter Takip Şefliği\IPC\B737\" &D3411&"\"& A3411 & ".png", "Resim için basınız") -> Resim için basınız
A3412: 340-050-101-0 | B3412: SHAFT-RADIAL DRIVE | D3412: 72 | E3412: ENGINE | F3412: 13 | G3412: 0 | I3412: =HYPERLINK("\\avrasya\THY_BSK_TEKNIK\MD_TEKNIK_ANLASMALAR_VE_ODEMELER\Teknik Envanter Takip Şefliği\IPC\B737\" &D3412&"\"& A3412 & ".png", "Resim için basınız") -> Resim için basınız
A3413: 340-055-202-0 | B3413: GEARSHAFT 61X31 TOOTH | D3413: 72 | E3413: ENGINE | F3413: 46 | G3413: 0 | I3413: =HYPERLINK("\\avrasya\THY_BSK_TEKNIK\MD_TEKNIK_ANLASMALAR_VE_ODEMELER\Teknik Envanter Takip Şefliği\IPC\B737\" &D3413&"\"& A3413 & ".png", "Resim için basınız") -> Resim için basınız
A3414: 305-115-201-0 | B3414: BRG BALL | D3414: 72 | E3414: ENGINE | F3414: 9 | G3414: 0 | I3414: =HYPERLINK("\\avrasya\THY_BSK_TEKNIK\MD_TEKNIK_ANLASMALAR_VE_ODEMELER\Teknik Envanter Takip Şefliği\IPC\B737\" &D3414&"\"& A3414 & ".png", "Resim için basınız") -> Resim için basınız
A3415: E01-3L004-005 | B3415: SEAT TPL, LH, STD | D3415: 25 | E3415: SEAT | F3415: 209 | G3415: 0 | I3415: =HYPERLINK("\\avrasya\THY_BSK_TEKNIK\MD_TEKNIK_ANLASMALAR_VE_ODEMELER\Teknik Envanter Takip Şefliği\IPC\B737\" &D3415&"\"& A3415 & ".png", "Resim için basınız") -> Resim için basınız
A3416: E01-3R006-002 | B3416: SEAT TPL, RH, NR WIDTH, STRETCHER PROVISIONS | D3416: 25 | E3416: SEAT | F3416: 19 | G3416: 0 | I3416: =HYPERLINK("\\avrasya\THY_BSK_TEKNIK\MD_TEKNIK_ANLASMALAR_VE_ODEMELER\Teknik Envanter Takip Şefliği\IPC\B737\" &D3416&"\"& A3416 & ".png", "Resim için basınız") -> Resim için basınız
A3417: E01-3R004-005 | B3417: SEAT TPL, RH, STD | D3417: 25 | E3417: SEAT | F3417: 228 | G3417: 0 | I3417: =HYPERLINK("\\avrasya\THY_BSK_TEKNIK\MD_TEKNIK_ANLASMALAR_VE_ODEMELER\Teknik Envanter Takip Şefliği\IPC\B737\" &D3417&"\"& A3417 & ".png", "Resim için basınız") -> Resim için basınız
A3418: E01-3L005-002 | B3418: SEAT TPL, LH, STD WIDTH, STRETCHER PROVISIONS | D3418: 25 | E3418: SEAT | F3418: 38 | G3418: 0 | I3418: =HYPERLINK("\\avrasya\THY_BSK_TEKNIK\MD_TEKNIK_ANLASMALAR_VE_ODEMELER\Teknik Envanter Takip Şefliği\IPC\B737\" &D3418&"\"& A3418 & ".png", "Resim için basınız") -> Resim için basınız
A3419: E01-3L003-002 | B3419: SEAT TPL, LH, STD WIDTH, NO OUTBD ARM | D3419: 25 | E3419: SEAT | F3419: 19 | G3419: 0 | I3419: =HYPERLINK("\\avrasya\THY_BSK_TEKNIK\MD_TEKNIK_ANLASMALAR_VE_ODEMELER\Teknik Envanter Takip Şefliği\IPC\B737\" &D3419&"\"& A3419 & ".png", "Resim için basınız") -> Resim için basınız
... A3458: 147A6116-5 | B3458: DOOR ASSY- AFT ENTRY | D3458: 52 | E3458: STRCTURE | F3458: 1 | G3458: 0 | I3458: =HYPERLINK("\\avrasya\THY_BSK_TEKNIK\MD_TEKNIK_ANLASMALAR_VE_ODEMELER\Teknik Envanter Takip Şefliği\IPC\B737\" &D3458&"\"& A3458 & ".png", "Resim için basınız") -> Resim için basınız
A3459: 002A0016-31 | B3459: LH ELEVATOR ASSY | C3459: Enis | D3459: 55 | E3459: COMPOSIT | F3459: 17 | G3459: 0 | I3459: =HYPERLINK("\\avrasya\THY_BSK_TEKNIK\MD_TEKNIK_ANLASMALAR_VE_ODEMELER\Teknik Envanter Takip Şefliği\IPC\B737\" &D3459&"\"& A3459 & ".png", "Resim için basınız") -> Resim için basınız
A3460: 338-092-401-0 | B3460: LPT STG 1/MOD 12 | D3460: 72 | E3460: ENGINE | F3460: 2 | G3460: 0 | I3460: =HYPERLINK("\\avrasya\THY_BSK_TEKNIK\MD_TEKNIK_ANLASMALAR_VE_ODEMELER\Teknik Envanter Takip Şefliği\IPC\B737\" &D3460&"\"& A3460 & ".png", "Resim için basınız") -> Resim için basınız
A3461: 146A6110-28 | B3461: DOOR ASSY-AFT CARGO | D3461: 52 | E3461: STRCTURE | F3461: 2 | G3461: 0 | I3461: =HYPERLINK("\\avrasya\THY_BSK_TEKNIK\MD_TEKNIK_ANLASMALAR_VE_ODEMELER\Teknik Envanter Takip Şefliği\IPC\B737\" &D3461&"\"& A3461 & ".png", "Resim için basınız") -> Resim için basınız
A3462: 10-62220-2 | B3462: RUDDER TRIM CONT SW ASSY | D3462: 27 | E3462: ELECTRIC | F3462: 1 | G3462: 0 | I3462: =HYPERLINK("\\avrasya\THY_BSK_TEKNIK\MD_TEKNIK_ANLASMALAR_VE_ODEMELER\Teknik Envanter Takip Şefliği\IPC\B737\" &D3462&"\"& A3462 & ".png", "Resim için basınız") -> Resim için basınız
A3463: B55968-004 | B3463: INLET GUIDE VANE ACTUATOR | D3463: 49 | E3463: FUEL | F3463: 1 | G3463: 0 | I3463: =HYPERLINK("\\avrasya\THY_BSK_TEKNIK\MD_TEKNIK_ANLASMALAR_VE_ODEMELER\Teknik Envanter Takip Şefliği\IPC\B737\" &D3463&"\"& A3463 & ".png", "Resim için basınız") -> Resim için basınız
A3464: S281A001-501 | B3464: INTEGRATED DRIVE GEN. QAD | D3464: 71 | E3464: MECHANIC | F3464: 11 | G3464: 0 | I3464: =HYPERLINK("\\avrasya\THY_BSK_TEKNIK\MD_TEKNIK_ANLASMALAR_VE_ODEMELER\Teknik Envanter Takip Şefliği\IPC\B737\" &D3464&"\"& A3464 & ".png", "Resim için basınız") -> Resim için basınız
A3465: 1742F8 | B3465: LOGIC CONTROL MODULE | D3465: 38 | E3465: ATE | F3465: 18 | G3465: 0 | I3465: =HYPERLINK("\\avrasya\THY_BSK_TEKNIK\MD_TEKNIK_ANLASMALAR_VE_ODEMELER\Teknik Envanter Takip Şefliği\IPC\B737\" &D3465&"\"& A3465 & ".png", "Resim için basınız") -> Resim için basınız
A3466: 20102070-106 | B3466: SERVOVALVE | D3466: 32 | E3466: HYDRAUL | F3466: 42 | G3466: 0 | I3466: =HYPERLINK("\\avrasya\THY_BSK_TEKNIK\MD_TEKNIK_ANLASMALAR_VE_ODEMELER\Teknik Envanter Takip Şefliği\IPC\B737\" &D3466&"\"& A3466 & ".png", "Resim için basınız") -> Resim için basınız
A3467: 37-231 | B3467: VALVE,THREE WAY SERVO VLV | D3467: 32 | E3467: HYDRAUL | F3467: 145 | G3467: 0 | I3467: =HYPERLINK("\\avrasya\THY_BSK_TEKNIK\MD_TEKNIK_ANLASMALAR_VE_ODEMELER\Teknik Envanter Takip Şefliği\IPC\B737\" &D3467&"\"& A3467 & ".png", "Resim için basınız") -> Resim için basınız
A3468: S315N370-3 | B3468: SYNCHRO-SHAFT LOCK | D3468: 78 | E3468: HYDRAUL | F3468: 29 | G3468: 0 | I3468: =HYPERLINK("\\avrasya\THY_BSK_TEKNIK\MD_TEKNIK_ANLASMALAR_VE_ODEMELER\Teknik Envanter Takip Şefliği\IPC\B737\" &D3468&"\"& A3468 & ".png", "Resim için basınız") -> Resim için basınız
A3469: 473957-1 | B3469: FIRE EXT. CARGO | D3469: 26 | E3469: OXYGEN | F3469: 2 | G3469: 0 | I3469: =HYPERLINK("\\avrasya\THY_BSK_TEKNIK\MD_TEKNIK_ANLASMALAR_VE_ODEMELER\Teknik Envanter Takip Şefliği\IPC\B737\" &D3469&"\"& A3469 & ".png", "Resim için basınız") -> Resim için basınız
A3470: 115A5211-8 | B3470: SUPPORT FITTING | D3470: 32 | E3470: STRCTURE | F3470: 1 | G3470: 0 | I3470: =HYPERLINK("\\avrasya\THY_BSK_TEKNIK\MD_TEKNIK_ANLASMALAR_VE_ODEMELER\Teknik Envanter Takip Şefliği\IPC\B737\" &D3470&"\"& A3470 & ".png", "Resim için basınız") -> Resim için basınız
A3471: 56193-02 | B3471: HYD VARIABLE DISP AC PUMP | D3471: 29 | E3471: HYDRAUL | F3471: 71 | G3471: 0 | I3471: =HYPERLINK("\\avrasya\THY_BSK_TEKNIK\MD_TEKNIK_ANLASMALAR_VE_ODEMELER\Teknik Envanter Takip Şefliği\IPC\B737\" &D3471&"\"& A3471 & ".png", "Resim için basınız") -> Resim için basınız
... A5549: QA07563 | B5549: FILTER OIL SCAVENGE | D5549: 79 | E5549: HYDRAUL | F5549: 1 | G5549: 0 | I5549: =HYPERLINK("\\avrasya\THY_BSK_TEKNIK\MD_TEKNIK_ANLASMALAR_VE_ODEMELER\Teknik Envanter Takip Şefliği\IPC\B737\" &D5549&"\"& A5549 & ".png", "Resim için basınız") -> Resim için basınız

Sheet B747
A1: PN | B1: PN DESC | C1: ilgili | D1: Chapter | E1: Sub Category | F1: QTY | G1: FA Amount | H1: Fonksiyonu | I1: Görsel | J1: Resim Notu
A2: GCP4110-001-001 | B2: 7" VIP PCU | D2: 44 | E2: IFE | F2: 4 | G2: 246466.96 | I2: =HYPERLINK("\\avrasya\THY_BSK_TEKNIK\MD_TEKNIK_ANLASMALAR_VE_ODEMELER\Teknik Envanter Takip Şefliği\IPC\B747\" &D2&"\"& A2 & ".png", "Resim için basınız") -> Resim için basınız
A3: RD-FW7329-01 | B3: 32" HD LCD MONITOR | D3: 23 | E3: IFE | F3: 2 | G3: 53887.68 | I3: =HYPERLINK("\\avrasya\THY_BSK_TEKNIK\MD_TEKNIK_ANLASMALAR_VE_ODEMELER\Teknik Envanter Takip Şefliği\IPC\B747\" &D3&"\"& A3 & ".png", "Resim için basınız") -> Resim için basınız
A4: 20102060-103 | B4: A/B PRESS CONTROL MODULE | D4: 32 | E4: HYDRAUL | F4: 162 | G4: 821568.86 | I4: =HYPERLINK("\\avrasya\THY_BSK_TEKNIK\MD_TEKNIK_ANLASMALAR_VE_ODEMELER\Teknik Envanter Takip Şefliği\IPC\B747\" &D4&"\"& A4 & ".png", "Resim için basınız") -> Resim için basınız
A5: NULL | B5: A/B PRESS CONTROL MODULE | D5: 32 | E5: HYDRAUL | F5: 172 | G5: 546860.8 | I5: =HYPERLINK("\\avrasya\THY_BSK_TEKNIK\MD_TEKNIK_ANLASMALAR_VE_ODEMELER\Teknik Envanter Takip Şefliği\IPC\B747\" &D5&"\"& A5 & ".png", "Resim için basınız") -> Resim için basınız
A6: F5746268800400 | B6: A330 SLAT NO 6(LH) | D6: 27 | E6: COMPOSIT | F6: 23 | G6: 0 | I6: =HYPERLINK("\\avrasya\THY_BSK_TEKNIK\MD_TEKNIK_ANLASMALAR_VE_ODEMELER\Teknik Envanter Takip Şefliği\IPC\B747\" &D6&"\"& A6 & ".png", "Resim için basınız") -> Resim için basınız
A7: F5746268800500 | B7: A330 SLAT NO 6(RH) | D7: 27 | E7: COMPOSIT | F7: 24 | G7: 0 | I7: =HYPERLINK("\\avrasya\THY_BSK_TEKNIK\MD_TEKNIK_ANLASMALAR_VE_ODEMELER\Teknik Envanter Takip Şefliği\IPC\B747\" &D7&"\"& A7 & ".png", "Resim için basınız") -> Resim için basınız
A8: 57186-10 | B8: AC DRIVEN PUMP | D8: 29 | E8: HYDRAUL | F8: 63 | G8: 759572.5 | I8: =HYPERLINK("\\avrasya\THY_BSK_TEKNIK\MD_TEKNIK_ANLASMALAR_VE_ODEMELER\Teknik Envanter Takip Şefliği\IPC\B747\" &D8&"\"& A8 & ".png", "Resim için basınız") -> Resim için basınız
A9: 57186-11 | B9: AC DRIVEN PUMP | D9: 29 | E9: HYDRAUL | F9: 165 | G9: 759572.5 | I9: =HYPERLINK("\\avrasya\THY_BSK_TEKNIK\MD_TEKNIK_ANLASMALAR_VE_ODEMELER\Teknik Envanter Takip Şefliği\IPC\B747\" &D9&"\"& A9 & ".png", "Resim için basınız") -> Resim için basınız
A10: 30730 | B10: ACCUMULATOR ASSY | D10: 29 | E10: HYDRAUL | F10: 143 | G10: 31304.18 | I10: =HYPERLINK("\\avrasya\THY_BSK_TEKNIK\MD_TEKNIK_ANLASMALAR_VE_ODEMELER\Teknik Envanter Takip Şefliği\IPC\B747\" &D10&"\"& A10 & ".png", "Resim için basınız") -> Resim için basınız
A11: AD8650503 | B11: ACTUATOR | D11: 25 | E11: ELECTMEC | F11: 73 | G11: 96214.98 | I11: =HYPERLINK("\\avrasya\THY_BSK_TEKNIK\MD_TEKNIK_ANLASMALAR_VE_ODEMELER\Teknik Envanter Takip Şefliği\IPC\B747\" &D11&"\"& A11 & ".png", "Resim için basınız") -> Resim için basınız
A12: SP8551005 | B12: ACTUATOR | D12: 25 | E12: SEAT | F12: 2 | G12: 129685.58 | I12: =HYPERLINK("\\avrasya\THY_BSK_TEKNIK\MD_TEKNIK_ANLASMALAR_VE_ODEMELER\Teknik Envanter Takip Şefliği\IPC\B747\" &D12&"\"& A12 & ".png", "Resim için basınız") -> Resim için basınız
A13: 2A258-0487 | B13: ACTUATOR | D13: 25 | E13: ELECTMEC | F13: 50 | G13: 96298.38 | I13: =HYPERLINK("\\avrasya\THY_BSK_TEKNIK\MD_TEKNIK_ANLASMALAR_VE_ODEMELER\Teknik Envanter Takip Şefliği\IPC\B747\" &D13&"\"& A13 & ".png", "Resim için basınız") -> Resim için basınız
... A37: BDP3009-001-001 | B37: B747-8 BLURAY DISC PLAYER | D37: 44 | E37: IFE | F37: 6 | G37: 127524.63 | I37: =HYPERLINK("\\avrasya\THY_BSK_TEKNIK\MD_TEKNIK_ANLASMALAR_VE_ODEMELER\Teknik Envanter Takip Şefliği\IPC\B747\" &D37&"\"& A37 & ".png", "Resim için basınız") -> Resim için basınız
A38: 8-930-03 | B38: BATTERY CHARGER | C38: TAHA | D38: 24 | E38: ATE | F38: 254 | G38: 28948.98 | H38: BA35 ve BA06 bataryalarını şarj etmeye ve Transformer-Rectifier Unit parçasını yönetmeye yarar | I38: =HYPERLINK("\\avrasya\THY_BSK_TEKNIK\MD_TEKNIK_ANLASMALAR_VE_ODEMELER\Teknik Envanter Takip Şefliği\IPC\B747\" &D38&"\"& A38 & ".png", "Resim için basınız") -> Resim için basınız | J38: Resim girildi
A39: 025920-000 | B39: BATTERY NI-CAD | D39: 24 | E39: BATTERY | F39: 3 | G39: 109522.2 | I39: =HYPERLINK("\\avrasya\THY_BSK_TEKNIK\MD_TEKNIK_ANLASMALAR_VE_ODEMELER\Teknik Envanter Takip Şefliği\IPC\B747\" &D39&"\"& A39 & ".png", "Resim için basınız") -> Resim için basınız
A40: ABS-3214-30 | B40: BATTERY PACK | D40: 33 | E40: BATTERY | F40: 5 | G40: 25370.39 | I40: =HYPERLINK("\\avrasya\THY_BSK_TEKNIK\MD_TEKNIK_ANLASMALAR_VE_ODEMELER\Teknik Envanter Takip Şefliği\IPC\B747\" &D40&"\"& A40 & ".png", "Resim için basınız") -> Resim için basınız
A41: 312BS801-1 | B41: BATTERY PACK ASSEMBLY | D41: 34 | E41: ATE | F41: 224 | G41: 63505.03 | I41: =HYPERLINK("\\avrasya\THY_BSK_TEKNIK\MD_TEKNIK_ANLASMALAR_VE_ODEMELER\Teknik Envanter Takip Şefliği\IPC\B747\" &D41&"\"& A41 & ".png", "Resim için basınız") -> Resim için basınız
A42: 21435-00 | B42: BEACON, LF-ULB | D42: 25 | E42: IFE | F42: 512 | G42: 128493.89 | I42: =HYPERLINK("\\avrasya\THY_BSK_TEKNIK\MD_TEKNIK_ANLASMALAR_VE_ODEMELER\Teknik Envanter Takip Şefliği\IPC\B747\" &D42&"\"& A42 & ".png", "Resim için basınız") -> Resim için basınız
A43: 1153206-1 | B43: BITE DISPLAY UNIT | D43: 47 | E43: INSTRMNT | F43: 173 | G43: 49206.97 | I43: =HYPERLINK("\\avrasya\THY_BSK_TEKNIK\MD_TEKNIK_ANLASMALAR_VE_ODEMELER\Teknik Envanter Takip Şefliği\IPC\B747\" &D43&"\"& A43 & ".png", "Resim için basınız") -> Resim için basınız
A44: 2341M52G04 | B44: BLADE STG 1 | D44: 72 | E44: ENGINE | F44: 74 | G44: 1029122 | I44: =HYPERLINK("\\avrasya\THY_BSK_TEKNIK\MD_TEKNIK_ANLASMALAR_VE_ODEMELER\Teknik Envanter Takip Şefliği\IPC\B747\" &D44&"\"& A44 & ".png", "Resim için basınız") -> Resim için basınız
A45: 475134-1 | B45: BOTTLE ASSY - NO. 1 ETOPS OPT FIRE BOTTLE | D45: 26 | E45: OXYGEN | F45: 2 | G45: 449478.26 | I45: =HYPERLINK("\\avrasya\THY_BSK_TEKNIK\MD_TEKNIK_ANLASMALAR_VE_ODEMELER\Teknik Envanter Takip Şefliği\IPC\B747\" &D45&"\"& A45 & ".png", "Resim için basınız") -> Resim için basınız
A46: N164-1 | B46: BOX, CONTROL | D46: 25 | E46: ELECTMEC | F46: 50 | G46: 39088.41 | I46: =HYPERLINK("\\avrasya\THY_BSK_TEKNIK\MD_TEKNIK_ANLASMALAR_VE_ODEMELER\Teknik Envanter Takip Şefliği\IPC\B747\" &D46&"\"& A46 & ".png", "Resim için basınız") -> Resim için basınız
A47: N164 | B47: BOX, CONTROL | D47: 25 | E47: ELECTMEC | F47: 46 | G47: 178232.9 | I47: =HYPERLINK("\\avrasya\THY_BSK_TEKNIK\MD_TEKNIK_ANLASMALAR_VE_ODEMELER\Teknik Envanter Takip Şefliği\IPC\B747\" &D47&"\"& A47 & ".png", "Resim için basınız") -> Resim için basınız
A48: 2-1727 | B48: BRAKE ASSY | C48: TAHA | D48: 32 | E48: BRAKE | F48: 20 | G48: 893740.85 | H48: Uçağın iniş ve kalkışta yavaşlamasını sağlayan fren disklerini sıkıştırarak tekerleklerin durmasını ve yavaşlamasını sağlar | I48: =HYPERLINK("\\avrasya\THY_BSK_TEKNIK\MD_TEKNIK_ANLASMALAR_VE_ODEMELER\Teknik Envanter Takip Şefliği\IPC\B747\" &D48&"\"& A48 & ".png", "Resim için basınız") -> Resim için basınız | J48: Resim girildi
A49: 142-159 | B49: BRAKE CONTROL UNIT | D49: 32 | E49: HYDRAUL | F49: 2 | G49: 1637744.9 | I49: =HYPERLINK("\\avrasya\THY_BSK_TEKNIK\MD_TEKNIK_ANLASMALAR_VE_ODEMELER\Teknik Envanter Takip Şefliği\IPC\B747\" &D49&"\"& A49 & ".png", "Resim için basınız") -> Resim için basınız
A50: RD-NB2500-01 | B50: BROADBAND CONTROLLER | D50: 23 | E50: IFE | F50: 55 | G50: 561111.68 | I50: =HYPERLINK("\\avrasya\THY_BSK_TEKNIK\MD_TEKNIK_ANLASMALAR_VE_ODEMELER\Teknik Envanter Takip Şefliği\IPC\B747\" &D50&"\"& A50 & ".png", "Resim için basınız") -> Resim için basınız
A51: RD-NB2504-01 | B51: BROADBAND CONTROLLER(BC-03) | D51: 44 | E51: IFE | F51: 217 | G51: 3392248.5 | I51: =HYPERLINK("\\avrasya\THY_BSK_TEKNIK\MD_TEKNIK_ANLASMALAR_VE_ODEMELER\Teknik Envanter Takip Şefliği\IPC\B747\" &D51&"\"& A51 & ".png", "Resim için basınız") -> Resim için basınız
A52: 4312300-90-00-00 | B52: BUN WARMER | C52: TAHA | D52: 25 | E52: GALLEY | F52: 1 | G52: 50187.38 | H52: Her türlü ekmek tipini kızartmaya ve ısıtmaya yarar | I52: =HYPERLINK("\\avrasya\THY_BSK_TEKNIK\MD_TEKNIK_ANLASMALAR_VE_ODEMELER\Teknik Envanter Takip Şefliği\IPC\B747\" &D52&"\"& A52 & ".png", "Resim için basınız") -> Resim için basınız | J52: Resim girildi
A53: 1713671 | B53: BUS POWER CONTROL UNIT | D53: 24 | E53: ATE | F53: 3 | G53: 847850 | I53: =HYPERLINK("\\avrasya\THY_BSK_TEKNIK\MD_TEKNIK_ANLASMALAR_VE_ODEMELER\Teknik Envanter Takip Şefliği\IPC\B747\" &D53&"\"& A53 & ".png", "Resim için basınız") -> Resim için basınız
A54: RD-AC1111-01 | B54: CABIN SERVICES SYSTEM CONTROLLER | D54: 23 | E54: RADIO | F54: 2 | G54: 170319.05 | I54: =HYPERLINK("\\avrasya\THY_BSK_TEKNIK\MD_TEKNIK_ANLASMALAR_VE_ODEMELER\Teknik Envanter Takip Şefliği\IPC\B747\" &D54&"\"& A54 & ".png", "Resim için basınız") -> Resim için basınız
A55: RD-AT1004-01 | B55: CABIN TELEPHONE UNIT | D55: 23 | E55: IFE | F55: 1 | G55: 5226.9 | I55: =HYPERLINK("\\avrasya\THY_BSK_TEKNIK\MD_TEKNIK_ANLASMALAR_VE_ODEMELER\Teknik Envanter Takip Şefliği\IPC\B747\" &D55&"\"& A55 & ".png", "Resim için basınız") -> Resim için basınız
A56: RD-AC1130-01 | B56: CABIN ZONE UNIT | D56: 23 | E56: IFE | F56: 2 | G56: 70761.29 | I56: =HYPERLINK("\\avrasya\THY_BSK_TEKNIK\MD_TEKNIK_ANLASMALAR_VE_ODEMELER\Teknik Envanter Takip Şefliği\IPC\B747\" &D56&"\"& A56 & ".png", "Resim için basınız") -> Resim için basınız
A57: 1000-1300-001 | B57: CAM HD-1 | D57: 23 | E57: RADIO | F57: 2 | G57: 624819.76 | I57: =HYPERLINK("\\avrasya\THY_BSK_TEKNIK\MD_TEKNIK_ANLASMALAR_VE_ODEMELER\Teknik Envanter Takip Şefliği\IPC\B747\" &D57&"\"& A57 & ".png", "Resim için basınız") -> Resim için basınız
A58: 446842-1 | B58: CARTRIDGE | D58: 26 | E58: OXYGEN | F58: 13 | G58: 8291.9 | I58: =HYPERLINK("\\avrasya\THY_BSK_TEKNIK\MD_TEKNIK_ANLASMALAR_VE_ODEMELER\Teknik Envanter Takip Şefliği\IPC\B747\" &D58&"\"& A58 & ".png", "Resim için basınız") -> Resim için basınız
A59: 822-2543-102 | B59: COCKPIT VOICE RECORDER | D59: 23 | E59: IFE | F59: 1 | G59: 228439.9 | I59: =HYPERLINK("\\avrasya\THY_BSK_TEKNIK\MD_TEKNIK_ANLASMALAR_VE_ODEMELER\Teknik Envanter Takip Şefliği\IPC\B747\" &D59&"\"& A59 & ".png", "Resim için basınız") -> Resim için basınız
A60: HFA2000-10 | B60: COFFEE MAKER | D60: 25 | E60: GALLEY | F60: 21 | G60: 22695.54 | I60: =HYPERLINK("\\avrasya\THY_BSK_TEKNIK\MD_TEKNIK_ANLASMALAR_VE_ODEMELER\Teknik Envanter Takip Şefliği\IPC\B747\" &D60&"\"& A60 & ".png", "Resim için basınız") -> Resim için basınız
A61: 822-1239-151 | B61: COMMUNICATION MNGT. UNIT | D61: 23 | E61: RADIO | F61: 103 | G61: 310286.1 | I61: =HYPERLINK("\\avrasya\THY_BSK_TEKNIK\MD_TEKNIK_ANLASMALAR_VE_ODEMELER\Teknik Envanter Takip Şefliği\IPC\B747\" &D61&"\"& A61 & ".png", "Resim için basınız") -> Resim için basınız
A62: 564CA04A11Y00 | B62: CONTACTOR-THREE POLE | D62: 24 | E62: ELECTRIC | F62: 3 | G62: 1746.34 | I62: =HYPERLINK("\\avrasya\THY_BSK_TEKNIK\MD_TEKNIK_ANLASMALAR_VE_ODEMELER\Teknik Envanter Takip Şefliği\IPC\B747\" &D62&"\"& A62 & ".png", "Resim için basınız") -> Resim için basınız
A63: RD-FA1071-01 | B63: CONTENT SERVER | D63: 23 | E63: IFE | F63: 172 | G63: 198641.55 | I63: =HYPERLINK("\\avrasya\THY_BSK_TEKNIK\MD_TEKNIK_ANLASMALAR_VE_ODEMELER\Teknik Envanter Takip Şefliği\IPC\B747\" &D63&"\"& A63 & ".png", "Resim için basınız") -> Resim için basınız
A64: 6251-1 | B64: CONTROL MODULE | D64: 38 | E64: INSTRMNT | F64: 35 | G64: 263717.3 | I64: =HYPERLINK("\\avrasya\THY_BSK_TEKNIK\MD_TEKNIK_ANLASMALAR_VE_ODEMELER\Teknik Envanter Takip Şefliği\IPC\B747\" &D64&"\"& A64 & ".png", "Resim için basınız") -> Resim için basınız
... A1007: LM-321-SA19-V | B1007: ISOLATOR VIBRATION AFT EN | D1007: 54 | E1007: MECHANIC | F1007: 1 | G1007: 0 | I1007: =HYPERLINK("\\avrasya\THY_BSK_TEKNIK\MD_TEKNIK_ANLASMALAR_VE_ODEMELER\Teknik Envanter Takip Şefliği\IPC\B747\" &D1007&"\"& A1007 & ".png", "Resim için basınız") -> Resim için basınız

Sheet B777
A1: PID_PN | B1: PN DESC | C1: ilgili | D1: Chapter | E1: Sub Category | F1: QTY | G1: FA Amount | H1: Fonksiyonu | I1: Görsel | J1: Resim Notu
A2: GE90-110B1 | B2: ENGINE, GE90 | D2: 72 | E2: ENGINE | F2: 23 | G2: 4.0972577e+08 | I2: =HYPERLINK("\\avrasya\THY_BSK_TEKNIK\MD_TEKNIK_ANLASMALAR_VE_ODEMELER\Teknik Envanter Takip Şefliği\IPC\B777\" &D2&"\"& A2 & ".png", "Resim için basınız") -> Resim için basınız
A3: GE90-115B | B3: GE90-115B ENGINE | D3: 72 | E3: ENGINE | F3: 81 | G3: 1.2331611e+08 | I3: =HYPERLINK("\\avrasya\THY_BSK_TEKNIK\MD_TEKNIK_ANLASMALAR_VE_ODEMELER\Teknik Envanter Takip Şefliği\IPC\B777\" &D3&"\"& A3 & ".png", "Resim için basınız") -> Resim için basınız
A4: 113W2100-72 | B4: INBD TE FLAP | D4: 27 | E4: STRCTURE | F4: 5 | G4: 52472713 | I4: =HYPERLINK("\\avrasya\THY_BSK_TEKNIK\MD_TEKNIK_ANLASMALAR_VE_ODEMELER\Teknik Envanter Takip Şefliği\IPC\B777\" &D4&"\"& A4 & ".png", "Resim için basınız") -> Resim için basınız
A5: NULL | B5: ACTUATOR | D5: 28 | E5: ELECTMEC | F5: 304 | G5: 49447459 | I5: =HYPERLINK("\\avrasya\THY_BSK_TEKNIK\MD_TEKNIK_ANLASMALAR_VE_ODEMELER\Teknik Envanter Takip Şefliği\IPC\B777\" &D5&"\"& A5 & ".png", "Resim için basınız") -> Resim için basınız
A6: 1962M80P05 | B6: HYDRO-MEC UNIT | D6: 73 | E6: FUEL | F6: 67 | G6: 28204458 | I6: =HYPERLINK("\\avrasya\THY_BSK_TEKNIK\MD_TEKNIK_ANLASMALAR_VE_ODEMELER\Teknik Envanter Takip Şefliği\IPC\B777\" &D6&"\"& A6 & ".png", "Resim için basınız") -> Resim için basınız
A7: 314W1400-24 | B7: INLET COWL | D7: 71 | E7: COMPOSIT | F7: 61 | G7: 27568888 | I7: =HYPERLINK("\\avrasya\THY_BSK_TEKNIK\MD_TEKNIK_ANLASMALAR_VE_ODEMELER\Teknik Envanter Takip Şefliği\IPC\B777\" &D7&"\"& A7 & ".png", "Resim için basınız") -> Resim için basınız
A8: 3505830-13 | B8: STARTER, AIR | D8: 80 | E8: PNEUMATC | F8: 60 | G8: 21908072 | I8: =HYPERLINK("\\avrasya\THY_BSK_TEKNIK\MD_TEKNIK_ANLASMALAR_VE_ODEMELER\Teknik Envanter Takip Şefliği\IPC\B777\" &D8&"\"& A8 & ".png", "Resim için basınız") -> Resim için basınız
A9: 3505830-12 | B9: STARTER, AIR | D9: 80 | E9: PNEUMATC | F9: 25 | G9: 21201360 | I9: =HYPERLINK("\\avrasya\THY_BSK_TEKNIK\MD_TEKNIK_ANLASMALAR_VE_ODEMELER\Teknik Envanter Takip Şefliği\IPC\B777\" &D9&"\"& A9 & ".png", "Resim için basınız") -> Resim için basınız
A10: 315W1298-54 | B10: THRUST REVERSER ASSY, RH | D10: 78 | E10: COMPOSIT | F10: 25 | G10: 21070010 | I10: =HYPERLINK("\\avrasya\THY_BSK_TEKNIK\MD_TEKNIK_ANLASMALAR_VE_ODEMELER\Teknik Envanter Takip Şefliği\IPC\B777\" &D10&"\"& A10 & ".png", "Resim için basınız") -> Resim için basınız
A11: 113W2100-53 | B11: L/H INB.MAIN FLAP ASSY. | D11: 27 | E11: COMPOSIT | F11: 16 | G11: 19842244 | I11: =HYPERLINK("\\avrasya\THY_BSK_TEKNIK\MD_TEKNIK_ANLASMALAR_VE_ODEMELER\Teknik Envanter Takip Şefliği\IPC\B777\" &D11&"\"& A11 & ".png", "Resim için basınız") -> Resim için basınız
A12: 161W1000-81 | B12: MLG BUILD-UP ASSY LH | D12: 32 | E12: LDG | F12: 35 | G12: 18230561 | I12: =HYPERLINK("\\avrasya\THY_BSK_TEKNIK\MD_TEKNIK_ANLASMALAR_VE_ODEMELER\Teknik Envanter Takip Şefliği\IPC\B777\" &D12&"\"& A12 & ".png", "Resim için basınız") -> Resim için basınız
A13: 161W1000-82 | B13: BUILDUP ASSY-MLG | D13: 32 | E13: LDG | F13: 35 | G13: 18230544 | I13: =HYPERLINK("\\avrasya\THY_BSK_TEKNIK\MD_TEKNIK_ANLASMALAR_VE_ODEMELER\Teknik Envanter Takip Şefliği\IPC\B777\" &D13&"\"& A13 & ".png", "Resim için basınız") -> Resim için basınız
... A36: 63604-332 | B36: B777 SLIDE/RAFT D4 RH | D36: 25 | E36: EMERGNCY | F36: 7 | G36: 4863685.5 | I36: =HYPERLINK("\\avrasya\THY_BSK_TEKNIK\MD_TEKNIK_ANLASMALAR_VE_ODEMELER\Teknik Envanter Takip Şefliği\IPC\B777\" &D36&"\"& A36 & ".png", "Resim için basınız") -> Resim için basınız
A37: 284T0052-43 | B37: RADOME ASSY | C37: TAHA | D37: 53 | E37: COMPOSIT | F37: 2 | G37: 4736742 | H37: Uçakta yer alan GPS, Radar, Anten gibi ekipmanların korunmasını sağlar | I37: =HYPERLINK("\\avrasya\THY_BSK_TEKNIK\MD_TEKNIK_ANLASMALAR_VE_ODEMELER\Teknik Envanter Takip Şefliği\IPC\B777\" &D37&"\"& A37 & ".png", "Resim için basınız") -> Resim için basınız | J37: Resim Girildi
A38: 62771-127 | B38: SLIDE/RAFT D1 D2 LH | D38: 25 | E38: EMERGNCY | F38: 79 | G38: 4654066.6 | I38: =HYPERLINK("\\avrasya\THY_BSK_TEKNIK\MD_TEKNIK_ANLASMALAR_VE_ODEMELER\Teknik Envanter Takip Şefliği\IPC\B777\" &D38&"\"& A38 & ".png", "Resim için basınız") -> Resim için basınız
A39: 810207-9 | B39: DIFFUSER FANINLET HAUSING | D39: 21 | E39: MECHANIC | F39: 36 | G39: 4277568.8 | I39: =HYPERLINK("\\avrasya\THY_BSK_TEKNIK\MD_TEKNIK_ANLASMALAR_VE_ODEMELER\Teknik Envanter Takip Şefliği\IPC\B777\" &D39&"\"& A39 & ".png", "Resim için basınız") -> Resim için basınız
A40: 3399100-31 | B40: HP/FAV AIR CONTROLLER | D40: 36 | E40: PNEUMATC | F40: 88 | G40: 4249719.3 | I40: =HYPERLINK("\\avrasya\THY_BSK_TEKNIK\MD_TEKNIK_ANLASMALAR_VE_ODEMELER\Teknik Envanter Takip Şefliği\IPC\B777\" &D40&"\"& A40 & ".png", "Resim için basınız") -> Resim için basınız
A41: 65344-428 | B41: B777 SLIDE/RAFT D5 RH | D41: 25 | E41: EMERGNCY | F41: 36 | G41: 4092085.3 | I41: =HYPERLINK("\\avrasya\THY_BSK_TEKNIK\MD_TEKNIK_ANLASMALAR_VE_ODEMELER\Teknik Envanter Takip Şefliği\IPC\B777\" &D41&"\"& A41 & ".png", "Resim için basınız") -> Resim için basınız
A42: 65344-427 | B42: B777 SLIDE/RAFT D5 LH | D42: 25 | E42: EMERGNCY | F42: 37 | G42: 4070332.5 | I42: =HYPERLINK("\\avrasya\THY_BSK_TEKNIK\MD_TEKNIK_ANLASMALAR_VE_ODEMELER\Teknik Envanter Takip Şefliği\IPC\B777\" &D42&"\"& A42 & ".png", "Resim için basınız") -> Resim için basınız
A43: ELM2001-12-10 | B43: COMPUTING AND COMM UNIT | D43: 24 | E43: ATE | F43: 26 | G43: 3981075 | I43: =HYPERLINK("\\avrasya\THY_BSK_TEKNIK\MD_TEKNIK_ANLASMALAR_VE_ODEMELER\Teknik Envanter Takip Şefliği\IPC\B777\" &D43&"\"& A43 & ".png", "Resim için basınız") -> Resim için basınız
A44: 2704442-5 | B44: ELECTRICAL STARTER MOTOR | D44: 49 | E44: ELECTRIC | F44: 62 | G44: 3979669 | I44: =HYPERLINK("\\avrasya\THY_BSK_TEKNIK\MD_TEKNIK_ANLASMALAR_VE_ODEMELER\Teknik Envanter Takip Şefliği\IPC\B777\" &D44&"\"& A44 & ".png", "Resim için basınız") -> Resim için basınız
A45: 62771-128 | B45: SLIDE/RAFT D1 D2 RH | D45: 25 | E45: EMERGNCY | F45: 78 | G45: 3917895 | I45: =HYPERLINK("\\avrasya\THY_BSK_TEKNIK\MD_TEKNIK_ANLASMALAR_VE_ODEMELER\Teknik Envanter Takip Şefliği\IPC\B777\" &D45&"\"& A45 & ".png", "Resim için basınız") -> Resim için basınız
A46: 63604-339 | B46: B777 SLIDE/RAFT D4 LH | D46: 25 | E46: EMERGNCY | F46: 34 | G46: 3908995.2 | I46: =HYPERLINK("\\avrasya\THY_BSK_TEKNIK\MD_TEKNIK_ANLASMALAR_VE_ODEMELER\Teknik Envanter Takip Şefliği\IPC\B777\" &D46&"\"& A46 & ".png", "Resim için basınız") -> Resim için basınız
A47: 100-005-297-001 | B47: RELAY - SEALED LATCHED | D47: 24 | E47: ELECTRIC | F47: 3 | G47: 3798659.7 | I47: =HYPERLINK("\\avrasya\THY_BSK_TEKNIK\MD_TEKNIK_ANLASMALAR_VE_ODEMELER\Teknik Envanter Takip Şefliği\IPC\B777\" &D47&"\"& A47 & ".png", "Resim için basınız") -> Resim için basınız
A48: 100-005-305-001 | B48: RELAY | D48: 24 | E48: ELECTRIC | F48: 42 | G48: 3708728.3 | I48: =HYPERLINK("\\avrasya\THY_BSK_TEKNIK\MD_TEKNIK_ANLASMALAR_VE_ODEMELER\Teknik Envanter Takip Şefliği\IPC\B777\" &D48&"\"& A48 & ".png", "Resim için basınız") -> Resim için basınız
A49: 810208-9 | B49: DUAL HEAT EXCHANGER | D49: 21 | E49: MECHANIC | F49: 108 | G49: 3628737.5 | I49: =HYPERLINK("\\avrasya\THY_BSK_TEKNIK\MD_TEKNIK_ANLASMALAR_VE_ODEMELER\Teknik Envanter Takip Şefliği\IPC\B777\" &D49&"\"& A49 & ".png", "Resim için basınız") -> Resim için basınız
... A150: 757183G | B150: CONVERTER ASSY-BACKUP PWR SYS FREQUENCY | D150: 24 | E150: ATE | F150: 43 | G150: 1194795 | I150: =HYPERLINK("\\avrasya\THY_BSK_TEKNIK\MD_TEKNIK_ANLASMALAR_VE_ODEMELER\Teknik Envanter Takip Şefliği\IPC\B777\" &D150&"\"& A150 & ".png", "Resim için basınız") -> Resim için basınız
A151: 3210005WB093 | B151: TRASH COMPACTOR | C151: TAHA | D151: 25 | E151: ELECTMEC | F151: 61 | G151: 1182509.8 | H151: Uçakta içecek ve besinlerden dolayı oluşan atıkların boyutlarını küçülterek daha uygun boyuta getirir | I151: =HYPERLINK("\\avrasya\THY_BSK_TEKNIK\MD_TEKNIK_ANLASMALAR_VE_ODEMELER\Teknik Envanter Takip Şefliği\IPC\B777\" &D151&"\"& A151 & ".png", "Resim için basınız") -> Resim için basınız | J151: Resim Girildi
A152: 351-702-706-0 | B152: SENSOR, T3 | D152: 77 | E152: INSTRMNT | F152: 63 | G152: 1179352 | I152: =HYPERLINK("\\avrasya\THY_BSK_TEKNIK\MD_TEKNIK_ANLASMALAR_VE_ODEMELER\Teknik Envanter Takip Şefliği\IPC\B777\" &D152&"\"& A152 & ".png", "Resim için basınız") -> Resim için basınız
A153: 293W3001-1 | B153: MLG DOWNLOCK ACTUATOR | D153: 32 | E153: HYDRAUL | F153: 185 | G153: 1175905.1 | I153: =HYPERLINK("\\avrasya\THY_BSK_TEKNIK\MD_TEKNIK_ANLASMALAR_VE_ODEMELER\Teknik Envanter Takip Şefliği\IPC\B777\" &D153&"\"& A153 & ".png", "Resim için basınız") -> Resim için basınız
A154: 351-701-607-0 | B154: HARNESS CORE ELEC, W721 | D154: 73 | E154: HARNESS | F154: 79 | G154: 1157616 | I154: =HYPERLINK("\\avrasya\THY_BSK_TEKNIK\MD_TEKNIK_ANLASMALAR_VE_ODEMELER\Teknik Envanter Takip Şefliği\IPC\B777\" &D154&"\"& A154 & ".png", "Resim için basınız") -> Resim için basınız
A155: 701310-500 | B155: CAMERA-DURING TAXI NLG | D155: 31 | E155: IFE | F155: 20 | G155: 1153726.6 | I155: =HYPERLINK("\\avrasya\THY_BSK_TEKNIK\MD_TEKNIK_ANLASMALAR_VE_ODEMELER\Teknik Envanter Takip Şefliği\IPC\B777\" &D155&"\"& A155 & ".png", "Resim için basınız") -> Resim için basınız
A156: 1567700-7 | B156: FLAPERON PCU | D156: 27 | E156: HYDRAUL | F156: 124 | G156: 1149763 | I156: =HYPERLINK("\\avrasya\THY_BSK_TEKNIK\MD_TEKNIK_ANLASMALAR_VE_ODEMELER\Teknik Envanter Takip Şefliği\IPC\B777\" &D156&"\"& A156 & ".png", "Resim için basınız") -> Resim için basınız
A157: 3876219-2 | B157: DELTA PRESSURE SENSOR | D157: 49 | E157: INSTRMNT | F157: 48 | G157: 1144653.6 | I157: =HYPERLINK("\\avrasya\THY_BSK_TEKNIK\MD_TEKNIK_ANLASMALAR_VE_ODEMELER\Teknik Envanter Takip Şefliği\IPC\B777\" &D157&"\"& A157 & ".png", "Resim için basınız") -> Resim için basınız
A158: 261700-1 | B158: ELECTRONIC FLIGHT BAG | D158: 46 | E158: IFE | F158: 91 | G158: 1142261.4 | I158: =HYPERLINK("\\avrasya\THY_BSK_TEKNIK\MD_TEKNIK_ANLASMALAR_VE_ODEMELER\Teknik Envanter Takip Şefliği\IPC\B777\" &D158&"\"& A158 & ".png", "Resim için basınız") -> Resim için basınız
A159: 4088240-901 | B159: FMS-CDU | D159: 34 | E159: ATE | F159: 87 | G159: 1082541.1 | I159: =HYPERLINK("\\avrasya\THY_BSK_TEKNIK\MD_TEKNIK_ANLASMALAR_VE_ODEMELER\Teknik Envanter Takip Şefliği\IPC\B777\" &D159&"\"& A159 & ".png", "Resim için basınız") -> Resim için basınız
A160: 8TJ124ERJ1 | B160: FUEL FLOW TRANSMITTER | D160: 73 | E160: FUEL | F160: 65 | G160: 1070830 | I160: =HYPERLINK("\\avrasya\THY_BSK_TEKNIK\MD_TEKNIK_ANLASMALAR_VE_ODEMELER\Teknik Envanter Takip Şefliği\IPC\B777\" &D160&"\"& A160 & ".png", "Resim için basınız") -> Resim için basınız
A161: 810205-2 | B161: FAN BYPASS CHECK VALVE | D161: 21 | E161: PNEUMATC | F161: 15 | G161: 1053515.4 | I161: =HYPERLINK("\\avrasya\THY_BSK_TEKNIK\MD_TEKNIK_ANLASMALAR_VE_ODEMELER\Teknik Envanter Takip Şefliği\IPC\B777\" &D161&"\"& A161 & ".png", "Resim için basınız") -> Resim için basınız
A162: 810205-3 | B162: FAN BYPASS CHECK VALVE | D162: 21 | E162: PNEUMATC | F162: 29 | G162: 1053515.4 | I162: =HYPERLINK("\\avrasya\THY_BSK_TEKNIK\MD_TEKNIK_ANLASMALAR_VE_ODEMELER\Teknik Envanter Takip Şefliği\IPC\B777\" &D162&"\"& A162 & ".png", "Resim için basınız") -> Resim için basınız
A163: 6026-02 | B163: INTG FUEL PANEL ASSY | D163: 28 | E163: INSTRMNT | F163: 27 | G163: 1032073 | I163: =HYPERLINK("\\avrasya\THY_BSK_TEKNIK\MD_TEKNIK_ANLASMALAR_VE_ODEMELER\Teknik Envanter Takip Şefliği\IPC\B777\" &D163&"\"& A163 & ".png", "Resim için basınız") -> Resim için basınız
... A2934: 2253M40G06 | B2934: INNER LINER COMBUSTOR | D2934: 72 | E2934: ENGINE | F2934: 1 | G2934: 0 | I2934: =HYPERLINK("\\avrasya\THY_BSK_TEKNIK\MD_TEKNIK_ANLASMALAR_VE_ODEMELER\Teknik Envanter Takip Şefliği\IPC\B777\" &D2934&"\"& A2934 & ".png", "Resim için basınız") -> Resim için basınız

Sheet B787
A1: PN | B1: PN DESC | C1: ilgili | D1: Chapter | E1: Sub Category | F1: QTY | G1: Fa Amount | H1: Fonksiyonu | I1: Görsel | J1: Resim Notu
A2: RD-NB4312-01 | B2: 3G EXPHONE SIEMENS NETWORK CONTROLLER UNIT | D2: 23 | E2: IFE | F2: 26 | G2: 8310376 | I2: =HYPERLINK("\\avrasya\THY_BSK_TEKNIK\MD_TEKNIK_ANLASMALAR_VE_ODEMELER\Teknik Envanter Takip Şefliği\IPC\B787\" &D2&"\"& A2 & ".png", "Resim için basınız") -> Resim için basınız
A3: RD-AA8190-01 | B3: 4G ENHANCED CELL MODEM (4G ECM) | D3: 23 | E3: IFE | F3: 247 | G3: 898253.44 | I3: =HYPERLINK("\\avrasya\THY_BSK_TEKNIK\MD_TEKNIK_ANLASMALAR_VE_ODEMELER\Teknik Envanter Takip Şefliği\IPC\B787\" &D3&"\"& A3 & ".png", "Resim için basınız") -> Resim için basınız
A4: RD-FD2822-01 | B4: 12 INCH SMART MONITOR V3 | D4: 23 | E4: IFE | F4: 16153 | G4: 617337 | I4: =HYPERLINK("\\avrasya\THY_BSK_TEKNIK\MD_TEKNIK_ANLASMALAR_VE_ODEMELER\Teknik Envanter Takip Şefliği\IPC\B787\" &D4&"\"& A4 & ".png", "Resim için basınız") -> Resim için basınız
A5: RD-FE9116-01 | B5: 16 INCH MONITOR | D5: 23 | E5: IFE | F5: 156 | G5: 216339.06 | I5: =HYPERLINK("\\avrasya\THY_BSK_TEKNIK\MD_TEKNIK_ANLASMALAR_VE_ODEMELER\Teknik Envanter Takip Şefliği\IPC\B787\" &D5&"\"& A5 & ".png", "Resim için basınız") -> Resim için basınız
A6: F5746268800400 | B6: A330 SLAT NO 6(LH) | D6: 27 | E6: COMPOSIT | F6: 23 | G6: 0 | I6: =HYPERLINK("\\avrasya\THY_BSK_TEKNIK\MD_TEKNIK_ANLASMALAR_VE_ODEMELER\Teknik Envanter Takip Şefliği\IPC\B787\" &D6&"\"& A6 & ".png", "Resim için basınız") -> Resim için basınız
A7: F5746268800500 | B7: A330 SLAT NO 6(RH) | D7: 27 | E7: COMPOSIT | F7: 24 | G7: 0 | I7: =HYPERLINK("\\avrasya\THY_BSK_TEKNIK\MD_TEKNIK_ANLASMALAR_VE_ODEMELER\Teknik Envanter Takip Şefliği\IPC\B787\" &D7&"\"& A7 & ".png", "Resim için basınız") -> Resim için basınız
A8: P35502M010 | B8: ACTUATOR | D8: 25 | E8: SEAT | F8: 94 | G8: 291874.83 | I8: =HYPERLINK("\\avrasya\THY_BSK_TEKNIK\MD_TEKNIK_ANLASMALAR_VE_ODEMELER\Teknik Envanter Takip Şefliği\IPC\B787\" &D8&"\"& A8 & ".png", "Resim için basınız") -> Resim için basınız
A9: 6537H2 | B9: ACTUATOR - ROTARY | D9: 21 | E9: ELECTMEC | F9: 4 | G9: 908335.85 | I9: =HYPERLINK("\\avrasya\THY_BSK_TEKNIK\MD_TEKNIK_ANLASMALAR_VE_ODEMELER\Teknik Envanter Takip Şefliği\IPC\B787\" &D9&"\"& A9 & ".png", "Resim için basınız") -> Resim için basınız
A10: 72538-4 | B10: ACTUATOR ASSY | D10: 52 | E10: PNEUMATC | F10: 206 | G10: 574827.12 | I10: =HYPERLINK("\\avrasya\THY_BSK_TEKNIK\MD_TEKNIK_ANLASMALAR_VE_ODEMELER\Teknik Envanter Takip Şefliği\IPC\B787\" &D10&"\"& A10 & ".png", "Resim için basınız") -> Resim için basınız
A11: 7011003-109 | B11: ACTUATOR ASSY - ROTARY | D11: 47 | E11: ELECTMEC | F11: 6 | G11: 117114.87 | I11: =HYPERLINK("\\avrasya\THY_BSK_TEKNIK\MD_TEKNIK_ANLASMALAR_VE_ODEMELER\Teknik Envanter Takip Şefliği\IPC\B787\" &D11&"\"& A11 & ".png", "Resim için basınız") -> Resim için basınız
A12: 2121M84P03 | B12: ACTUATOR-VBV | D12: 75 | E12: FUEL | F12: 115 | G12: 340115.62 | I12: =HYPERLINK("\\avrasya\THY_BSK_TEKNIK\MD_TEKNIK_ANLASMALAR_VE_ODEMELER\Teknik Envanter Takip Şefliği\IPC\B787\" &D12&"\"& A12 & ".png", "Resim için basınız") -> Resim için basınız
A13: 2122M17P04 | B13: ACTUATOR-VSV | D13: 75 | E13: FUEL | F13: 116 | G13: 340115.62 | I13: =HYPERLINK("\\avrasya\THY_BSK_TEKNIK\MD_TEKNIK_ANLASMALAR_VE_ODEMELER\Teknik Envanter Takip Şefliği\IPC\B787\" &D13&"\"& A13 & ".png", "Resim için basınız") -> Resim için basınız
... A25: 866-0077-101 | B25: AUDIO CONTROL PANEL - ACP-2100 | D25: 23 | E25: RADIO | F25: 77 | G25: 415922.4 | I25: =HYPERLINK("\\avrasya\THY_BSK_TEKNIK\MD_TEKNIK_ANLASMALAR_VE_ODEMELER\Teknik Envanter Takip Şefliği\IPC\B787\" &D25&"\"& A25 & ".png", "Resim için basınız") -> Resim için basınız
A26: 515Z2002-501 | B26: AXLE ASSEMBLY | C26: TAHA | D26: 32 | E26: LDG | F26: 47 | G26: 9473807.9 | H26: Uçağın tekerleklerini taşıyan,dönmesini sağlayan ve uçağın ağırlığını destekleyen yapıdır | I26: =HYPERLINK("\\avrasya\THY_BSK_TEKNIK\MD_TEKNIK_ANLASMALAR_VE_ODEMELER\Teknik Envanter Takip Şefliği\IPC\B787\" &D26&"\"& A26 & ".png", "Resim için basınız") -> Resim için basınız | J26: Resim Girildi
A27: 822-0407-101 | B27: BACKDRIVE ACTUATOR | D27: 22 | E27: ELECTMEC | F27: 348 | G27: 44852.56 | I27: =HYPERLINK("\\avrasya\THY_BSK_TEKNIK\MD_TEKNIK_ANLASMALAR_VE_ODEMELER\Teknik Envanter Takip Şefliği\IPC\B787\" &D27&"\"& A27 & ".png", "Resim için basınız") -> Resim için basınız
A28: 7000426-105 | B28: BASE CONTACTOR | D28: 24 | E28: BOEING | F28: 1 | G28: 121074.36 | I28: =HYPERLINK("\\avrasya\THY_BSK_TEKNIK\MD_TEKNIK_ANLASMALAR_VE_ODEMELER\Teknik Envanter Takip Şefliği\IPC\B787\" &D28&"\"& A28 & ".png", "Resim için basınız") -> Resim için basınız
A29: B3856-904 | B29: BATTERY | D29: 24 | E29: BATTERY | F29: 59 | G29: 4747013.7 | I29: =HYPERLINK("\\avrasya\THY_BSK_TEKNIK\MD_TEKNIK_ANLASMALAR_VE_ODEMELER\Teknik Envanter Takip Şefliği\IPC\B787\" &D29&"\"& A29 & ".png", "Resim için basınız") -> Resim için basınız
A30: BA53-02 | B30: BATTERY | D30: 27 | E30: BATTERY | F30: 57 | G30: 1419215.9 | I30: =HYPERLINK("\\avrasya\THY_BSK_TEKNIK\MD_TEKNIK_ANLASMALAR_VE_ODEMELER\Teknik Envanter Takip Şefliği\IPC\B787\" &D30&"\"& A30 & ".png", "Resim için basınız") -> Resim için basınız
A31: 05N62123 | B31: BATTERY, ELT | D31: 25 | E31: RADIO | F31: 560 | G31: 27712.67 | I31: =HYPERLINK("\\avrasya\THY_BSK_TEKNIK\MD_TEKNIK_ANLASMALAR_VE_ODEMELER\Teknik Envanter Takip Şefliği\IPC\B787\" &D31&"\"& A31 & ".png", "Resim için basınız") -> Resim için basınız
A32: 21435-00 | B32: BEACON, LF-ULB | D32: 25 | E32: IFE | F32: 512 | G32: 128493.89 | I32: =HYPERLINK("\\avrasya\THY_BSK_TEKNIK\MD_TEKNIK_ANLASMALAR_VE_ODEMELER\Teknik Envanter Takip Şefliği\IPC\B787\" &D32&"\"& A32 & ".png", "Resim için basınız") -> Resim için basınız
A33: 4680-0002-00 | B33: BEVERAGE CUP | D33: 25 | E33: GALLEY | F33: 103 | G33: 143914.1 | I33: =HYPERLINK("\\avrasya\THY_BSK_TEKNIK\MD_TEKNIK_ANLASMALAR_VE_ODEMELER\Teknik Envanter Takip Şefliği\IPC\B787\" &D33&"\"& A33 & ".png", "Resim için basınız") -> Resim için basınız
A34: 7001749H03 | B34: BLADE ASSY - WIPER | D34: 30 | E34: MECHANIC | F34: 18 | G34: 153149.64 | I34: =HYPERLINK("\\avrasya\THY_BSK_TEKNIK\MD_TEKNIK_ANLASMALAR_VE_ODEMELER\Teknik Envanter Takip Şefliği\IPC\B787\" &D34&"\"& A34 & ".png", "Resim için basınız") -> Resim için basınız
A35: 2051M72G03 | B35: BLADE, FAN RTR-S1 (GENX) | D35: 72 | E35: ENGINE | F35: 580 | G35: 7096040.6 | I35: =HYPERLINK("\\avrasya\THY_BSK_TEKNIK\MD_TEKNIK_ANLASMALAR_VE_ODEMELER\Teknik Envanter Takip Şefliği\IPC\B787\" &D35&"\"& A35 & ".png", "Resim için basınız") -> Resim için basınız
A36: 2051M72G05 | B36: BLADE, FAN RTR-S1 (GENX) | D36: 72 | E36: ENGINE | F36: 310 | G36: 7096040.6 | I36: =HYPERLINK("\\avrasya\THY_BSK_TEKNIK\MD_TEKNIK_ANLASMALAR_VE_ODEMELER\Teknik Envanter Takip Şefliği\IPC\B787\" &D36&"\"& A36 & ".png", "Resim için basınız") -> Resim için basınız
A37: 003-CM-00-0200 | B37: BOARD - ZONE CONTROLLER PRINTED CKT | D37: 30 | E37: ATE | F37: 603 | G37: 740895.41 | I37: =HYPERLINK("\\avrasya\THY_BSK_TEKNIK\MD_TEKNIK_ANLASMALAR_VE_ODEMELER\Teknik Envanter Takip Şefliği\IPC\B787\" &D37&"\"& A37 & ".png", "Resim için basınız") -> Resim için basınız
A38: 41004654-5 | B38: BOTTLE ASSY - EPAS RSVR | D38: 52 | E38: OXYGEN | F38: 200 | G38: 690984 | I38: =HYPERLINK("\\avrasya\THY_BSK_TEKNIK\MD_TEKNIK_ANLASMALAR_VE_ODEMELER\Teknik Envanter Takip Şefliği\IPC\B787\" &D38&"\"& A38 & ".png", "Resim için basınız") -> Resim için basınız
... A84: 956-0028-001 | B84: DISTANCE MEASURING EQUIPMENT (DME) ANTENNA | D84: 34 | E84: RADIO | F84: 55 | G84: 75653.13 | I84: =HYPERLINK("\\avrasya\THY_BSK_TEKNIK\MD_TEKNIK_ANLASMALAR_VE_ODEMELER\Teknik Envanter Takip Şefliği\IPC\B787\" &D84&"\"& A84 & ".png", "Resim için basınız") -> Resim için basınız
A85: 7001014H01 | B85: DOOR POSITION SWITCH | C85: TAHA | D85: 49 | E85: INSTRMNT | F85: 1 | G85: 23107.58 | H85: Kapının açıldığı sırada APU'ya sinyal göndererek kapının açık olduğunu bildirir | I85: =HYPERLINK("\\avrasya\THY_BSK_TEKNIK\MD_TEKNIK_ANLASMALAR_VE_ODEMELER\Teknik Envanter Takip Şefliği\IPC\B787\" &D85&"\"& A85 & ".png", "Resim için basınız") -> Resim için basınız | J85: Resim Girildi
A86: 1289L2000010 | B86: DUAL CAMERA UNIT | D86: 23 | E86: RADIO | F86: 18 | G86: 236114.43 | I86: =HYPERLINK("\\avrasya\THY_BSK_TEKNIK\MD_TEKNIK_ANLASMALAR_VE_ODEMELER\Teknik Envanter Takip Şefliği\IPC\B787\" &D86&"\"& A86 & ".png", "Resim için basınız") -> Resim için basınız
A87: 7007076H01 | B87: DUAL-OIL PRESSURE SENSOR | D87: 49 | E87: HYDRAUL | F87: 56 | G87: 505634.43 | I87: =HYPERLINK("\\avrasya\THY_BSK_TEKNIK\MD_TEKNIK_ANLASMALAR_VE_ODEMELER\Teknik Envanter Takip Şefliği\IPC\B787\" &D87&"\"& A87 & ".png", "Resim için basınız") -> Resim için basınız
A88: C20604100 | B88: EBA MOTOR | D88: 32 | E88: BRAKE | F88: 192 | G88: 92923.28 | I88: =HYPERLINK("\\avrasya\THY_BSK_TEKNIK\MD_TEKNIK_ANLASMALAR_VE_ODEMELER\Teknik Envanter Takip Şefliği\IPC\B787\" &D88&"\"& A88 & ".png", "Resim için basınız") -> Resim için basınız
A89: C20604001 | B89: EBA MOTOR | D89: 32 | E89: BRAKE | F89: 398 | G89: 323003.41 | I89: =HYPERLINK("\\avrasya\THY_BSK_TEKNIK\MD_TEKNIK_ANLASMALAR_VE_ODEMELER\Teknik Envanter Takip Şefliği\IPC\B787\" &D89&"\"& A89 & ".png", "Resim için basınız") -> Resim için basınız
A90: C20604000 | B90: EBA MOTOR | D90: 32 | E90: BRAKE | F90: 162 | G90: 0 | I90: =HYPERLINK("\\avrasya\THY_BSK_TEKNIK\MD_TEKNIK_ANLASMALAR_VE_ODEMELER\Teknik Envanter Takip Şefliği\IPC\B787\" &D90&"\"& A90 & ".png", "Resim için basınız") -> Resim için basınız
A91: RD-FD2824-01 | B91: ECO 12A/S V3 PLUS SMART MONITOR | D91: 23 | E91: IFE | F91: 1872 | G91: 629683.74 | I91: =HYPERLINK("\\avrasya\THY_BSK_TEKNIK\MD_TEKNIK_ANLASMALAR_VE_ODEMELER\Teknik Envanter Takip Şefliği\IPC\B787\" &D91&"\"& A91 & ".png", "Resim için basınız") -> Resim için basınız
A92: RD-FD3830-01 | B92: ECO 13 V3 PLUS | D92: 44 | E92: IFE | F92: 11467 | G92: 793719 | I92: =HYPERLINK("\\avrasya\THY_BSK_TEKNIK\MD_TEKNIK_ANLASMALAR_VE_ODEMELER\Teknik Envanter Takip Şefliği\IPC\B787\" &D92&"\"& A92 & ".png", "Resim için basınız") -> Resim için basınız
A93: P78700M111 | B93: ECU | D93: 25 | E93: ATE | F93: 32 | G93: 110091.73 | I93: =HYPERLINK("\\avrasya\THY_BSK_TEKNIK\MD_TEKNIK_ANLASMALAR_VE_ODEMELER\Teknik Envanter Takip Şefliği\IPC\B787\" &D93&"\"& A93 & ".png", "Resim için basınız") -> Resim için basınız
A94: 261690-101 | B94: EFB DISPLAY UNIT | D94: 46 | E94: ATE | F94: 88 | G94: 122544 | I94: =HYPERLINK("\\avrasya\THY_BSK_TEKNIK\MD_TEKNIK_ANLASMALAR_VE_ODEMELER\Teknik Envanter Takip Şefliği\IPC\B787\" &D94&"\"& A94 & ".png", "Resim için basınız") -> Resim için basınız
A95: 277950-1 | B95: EFB ELECTRONIC UNIT | D95: 46 | E95: ATE | F95: 52 | G95: 5290084.6 | I95: =HYPERLINK("\\avrasya\THY_BSK_TEKNIK\MD_TEKNIK_ANLASMALAR_VE_ODEMELER\Teknik Envanter Takip Şefliği\IPC\B787\" &D95&"\"& A95 & ".png", "Resim için basınız") -> Resim için basınız
A96: 7000151H03 | B96: EGT THERMOCOUPLE | D96: 49 | E96: INSTRMNT | F96: 28 | G96: 38987.46 | I96: =HYPERLINK("\\avrasya\THY_BSK_TEKNIK\MD_TEKNIK_ANLASMALAR_VE_ODEMELER\Teknik Envanter Takip Şefliği\IPC\B787\" &D96&"\"& A96 & ".png", "Resim için basınız") -> Resim için basınız
A97: C20605100 | B97: ELECTRIC BRAKE HARNESS | D97: 32 | E97: HARNESS | F97: 179 | G97: 956295.95 | I97: =HYPERLINK("\\avrasya\THY_BSK_TEKNIK\MD_TEKNIK_ANLASMALAR_VE_ODEMELER\Teknik Envanter Takip Şefliği\IPC\B787\" &D97&"\"& A97 & ".png", "Resim için basınız") -> Resim için basınız
... A1595: 7010226H21 | B1595: HARNESS, CACTCS, CAC, RIGHT | D1595: 21 | E1595: PNEUMATC | F1595: 1 | G1595: 0 | I1595: =HYPERLINK("\\avrasya\THY_BSK_TEKNIK\MD_TEKNIK_ANLASMALAR_VE_ODEMELER\Teknik Envanter Takip Şefliği\IPC\B787\" &D1595&"\"& A1595 & ".png", "Resim için basınız") -> Resim için basınız
